Workbook

Sheet CODIFICACIÓN_DPA
A1: DPA_DESCRI | B1: COD_DPA | D1: MODALIDAD_DESCRIP | E1: COD_MODALIDAD | G1: NODO_DESCRP | H1: NODO_LOCALIDAD | J1: CENTRALIDAD_DESCRIP | K1: COD_CENTRALIDAD
A2: BELISARIO QUEVEDO | B2: 170101 | D2: NATURAL | E2: NA | G2: URBANO | H2: 01 | J2: Centro Histórico | K2: 01
A3: CARCELÉN | B3: 170102 | D3: GASTRONÓMICO | E3: GA | G3: RURAL | H3: 02 | J3: La Mariscal | K3: 02
A4: CENTRO HISTÓRICO | B4: 170103 | D4: CULTURAL | E4: CU | J4: Centro Norte | K4: 03
A5: COCHAPAMBA | B5: 170104 | D5: AVENTURA | E5: AV | J5: Parroquias Equinocciales | K5: 04
A6: COMITÉ DEL PUEBLO | B6: 170105 | D6: COMUNITARIO | E6: CO | J6: Chocó Andino | K6: 05
A7: COTOCOLLAO | B7: 170106 | J7: Ruta Escondida | K7: 06
A8: CHILIBULO | B8: 170107 | J8: Valle de los Chillos | K8: 07
A9: CHILLOGALLO | B9: 170108 | J9: Valle de Tumbaco | K9: 08
A10: CHIMBACALLE | B10: 170109 | J10: Calderón | K10: 09
A11: EL CONDADO | B11: 170110
A12: GUAMANÍ | B12: 170111
A13: IÑAQUITO | B13: 170112
A14: ITCHIMBIA | B14: 170113
A15: JIPIJAPA | B15: 170114 | C15: URBANAS
A16: KENNEDY | B16: 170115
A17: LA ARGELIA | B17: 170116
A18: LA CONCEPCIÓN | B18: 170117
A19: LA ECUATORIANA | B19: 170118
A20: LA FERROVIARIA | B20: 170119
A21: LA LIBERTAD | B21: 170120 | D21: CÓDIGO QT
A22: LA MAGDALENA | B22: 170121 | D22: 170112GA0103001
A23: LA MENA | B23: 170122
A24: MARISCAL SUCRE | B24: 170123
A25: PONCEANO | B25: 170124 | D25: PARROQUIA | E25: MODALIDAD | F25: NODO | G25: CENTRALIDAD | H25: ORDEN EN LISTADO
A26: PUENGASÍ | B26: 170125 | D26: 170112 | E26: GA | F26: 01 | G26: 03 | H26: 001
A27: QUITUMBE | B27: 170126 | D27: IÑAQUITO | E27: GASTRONÓMICO | F27: URBANO | G27: Centro Norte | H27: 001
A28: RUMIPAMBA | B28: 170127
A29: SAN BARTOLO | B29: 170128
A30: SAN ISIDRO DEL INCA | B30: 170129
A31: SAN JUAN | B31: 170130
A32: SOLANDA | B32: 170131
A33: TURUBAMBA | B33: 170132
A34: ALANGASÍ | B34: 170151
A35: AMAGUAÑA | B35: 170152
A36: ATAHUALPA | B36: 170153
A37: CALACALÍ | B37: 170154
A38: CALDERÓN | B38: 170155
A39: CONOCOTO | B39: 170156
... A43: EL QUINCHE | B43: 170160
A44: GUALEA | B44: 170161 | C44: RURALES
A45: GUANGOPOLO | B45: 170162
A46: GUAYLLABAMBA | B46: 170163
A47: LA MERCED | B47: 170164
A48: LLANO CHICO | B48: 170165
A49: LLOA | B49: 170166
A50: NANEGAL | B50: 170168
A51: NANEGALITO | B51: 170169
A52: NAYÓN | B52: 170170
A53: NONO | B53: 170171
A54: PACTO | B54: 170172
A55: PERUCHO | B55: 170174
A56: PIFO | B56: 170175
... A70: 51-86 EXCEPTO 73 | B70: RURAL

Sheet ESTRUCTURA CÓDIGO
A1: FICHA PARA EL LEVANTAMIENTO DE EXPERIENCIAS TURÍSTICAS
A3: CÓDIGO DE LA EXPERIENCIA
A5: El código, está compuesto por 15 dígitos (caracteres alfanuméricos), únicos e irrepetibles, mismo que aparecerá al inicio de la ficha para su identificación.
A6: 1. División Política Administrativa (DPA) obtenida del Clasificador Geográfico 2023 del Instituto Nacional de Estadística y Censos - INEC, (códigos provincial, cantonal y parroquial).
A7: 2. Se colocará las letras iniciales de la modalidad de la experiencia ejemplo: Gastronómica "GA"
A8: 3. Clasificación de experiencia turística (Nodo), (ver documento Centralidades - Nodos Turísticos Complementarios Urbanos y Rurales, 2024).
A9: 4. Clasificación de experiencia turística (Centralidad), (ver documento Centralidades - Nodos Turísticos Complementarios Urbanos y Rurales, 2024).
A10: 5. FInalmente; los tres dígitos finales corresponden al orden en que se levante la información de las experiencias turísticas que iniciará desde 001.
A14: FUENTE: Manual Metodología para Jerarquización de Atractivos y Generación de Espacios Turísticos, MINTUR 2017.
A15: Centralidades - Nodos Turísticos Complementarios Urbanos y Rurales, QUITO TURISMO 2024.

Sheet EXPERIENCIAS
A1: N° | B1: ESTADO EXPERIENCIA | C1: CÓDIGO EXPERIENCIA QT | D1: PARROQUIA | E1: NODO | F1: CENTRALIDAD | G1: MODALIDAD | H1: NOMBRE DE LA EXPERIENCIA | I1: BREVE DESCRIPCIÓN Y ACTIVIDADES A REALIZAR | J1: DIRECCIÓN | K1: LATITUD | L1: LONGITUD | M1: TIEMPO DE DURACIÓN | N1: HORARIO DE ATENCIÓN | O1: COSTO | P1: CAPACIDAD | Q1: RESTRICCIONES | R1: CONTACTOS
A2: 001 | B2: ACTIVO | C2: =CONCATENATE(VLOOKUP($D2,CODIFICACIÓN_DPA!$A$2:$B$66,2,FALSE),VLOOKUP($G2,CODIFICACIÓN_DPA!$D$2:$E$6,2,FALSE),CONCATENATE(VLOOKUP($E2,CODIFICACIÓN_DPA!$G$2:$H$3,2,FALSE),VLOOKUP($F2,CODIFICACIÓN_DPA!$J$2:$K$10,2,FALSE)),A2) -> 170154CO0205001 | D2: CALACALÍ | E2: RURAL | F2: Chocó Andino | G2: COMUNITARIO | H2: Comunidad Yunguilla | I2: Sumérgete en el Chocó Andino y explorar su rica herencia cultural y natural, al tiempo que apoyas activamente a la comunidad local. La comunidad Yunguilla ofrece a los visitantes una experiencia auténtica de la ruralidad, disfrutando de emocionantes recorridos guiados por antiguos caminos precolombinos, aventúrate en apasionantes trekkings por reservas naturales cercanas y conecta con la naturaleza a través de experiencias de camping bajo el cielo estrellado. ¡Descubre la autenticidad de su gente mientras contribuyes al desarrollo sostenible de la región! | J2: Parroquia Calacalí, km 12 vía al noroccidente de Quito, en el ACUS Yunguilla del Distrito Metropolitano de Quito. | K2: -0.020786319 | L2: -78.553248 | M2: 3 a 4 horas | N2: 24 horas Todos los días Previa reserva | O2: Depende mucho del servicio que se solicite | P2: - Alojamiento comunitario capaciadad 30 pax - Restaurante capacidad 80 pax - Salón de eventos capacida 80 personas - Senderos establecidos: 4 - Miradores: 2 - Tours organizados: 6 alternativas - Guías nativos - Tiendas de artesanías y productos orgánicos | Q2: Prohibido el ingreso de mascotas debido a su estatus como Área de Conservación y Uso Sustentable (ACUS) y su modelo de turismo comunitario, que busca proteger la fauna silvestre (como el oso de anteojos y diversas aves endémicas) de posibles enfermedades o estrés causado por animales domésticos. | R2: (593) 98 021 5476 https://www.yunguilla.org.ec/contact-us/ info@yunguilla.org.ec (593) 99 954 1537
A3: 002 | B3: ACTIVO | C3: =CONCATENATE(VLOOKUP($D3,CODIFICACIÓN_DPA!$A$2:$B$66,2,FALSE),VLOOKUP($G3,CODIFICACIÓN_DPA!$D$2:$E$6,2,FALSE),CONCATENATE(VLOOKUP($E3,CODIFICACIÓN_DPA!$G$2:$H$3,2,FALSE),VLOOKUP($F3,CODIFICACIÓN_DPA!$J$2:$K$10,2,FALSE)),A3) -> 170155CO0204002 | D3: CALDERÓN | E3: RURAL | F3: Parroquias Equinocciales | G3: COMUNITARIO | H3: Chucchurillos Ñaupa Ayllu Manta | I3: Chucchurillos Ñaupa Ayllu Manta celebra la herencia Kitu Kara con danzas, rituales y relatos que honran a la Pachamama, en torno al tzáwar (agave andino), “planta de las mil maravillas”. La experiencia integra saberes intergeneracionales, festividades de siembra y cosecha del tzawarmishki, gastronomía ancestral, mieles y bebidas tradicionales, además de artesanías en cabuya que revelan usos sostenibles del territorio. Un encuentro cultural auténtico, inmersivo y emotivo, donde la memoria viva de los Andes se manifiesta en cada canto, aroma y textura. | J3: Quito-Pomasqui Barrio el Común | K3: -0.057963558 | L3: -78.449687 | N3: Bajo reserva | O3: Depende del grupo y actividad | P3: Se adapta a la necesidad del grupo. | R3: (02) 235 8001 (+593) 98 765 6946 Email: chucchurillos@hotmail.com Whatsapp: (+593) 97 905 4213
A4: 003 | B4: ACTIVO | C4: =CONCATENATE(VLOOKUP($D4,CODIFICACIÓN_DPA!$A$2:$B$66,2,FALSE),VLOOKUP($G4,CODIFICACIÓN_DPA!$D$2:$E$6,2,FALSE),CONCATENATE(VLOOKUP($E4,CODIFICACIÓN_DPA!$G$2:$H$3,2,FALSE),VLOOKUP($F4,CODIFICACIÓN_DPA!$J$2:$K$10,2,FALSE)),A4) -> 170155CO0209003 | D4: CALDERÓN | E4: RURAL | F4: Calderón | G4: COMUNITARIO | H4: Ecoferia Allpa Maki | I4: Ecoferia Allpa Maki es la vitrina agroecológica de la Comuna Llano Grande: una asociación de huertos que impulsa el estilo de vida LOHAS (Vida Saludable y Sustentable) y la economía solidaria Kitu Kara, fusionando saberes ancestrales, soberanía alimentaria y empoderamiento comunitario. Entre agro-biodiversidad, productos frescos “de la mata a la olla”, cocina en vivo y manifestaciones culturales, la feria celebra el respeto a la Pachamama, la justicia alimentaria y la producción responsable, ofreciendo un mercado vivo donde salud, sabor y comunidad se encuentran en armonía con el planeta. | J4: Llano Grande, Quito | K4: -0.12329098 | L4: -78.426923 | M4: 1 hora | N4: Domingos de 07h00 a 12h00 Puede variar el horario | O4: Costo de los productos que se vayan a comprar | P4: Se adapta a la necesidad del grupo. | R4: allpamaki2021@gmail.com
A5: 004 | B5: ACTIVO | C5: =CONCATENATE(VLOOKUP($D5,CODIFICACIÓN_DPA!$A$2:$B$66,2,FALSE),VLOOKUP($G5,CODIFICACIÓN_DPA!$D$2:$E$6,2,FALSE),CONCATENATE(VLOOKUP($E5,CODIFICACIÓN_DPA!$G$2:$H$3,2,FALSE),VLOOKUP($F5,CODIFICACIÓN_DPA!$J$2:$K$10,2,FALSE)),A5) -> 170101CU0102004 | D5: BELISARIO QUEVEDO | E5: URBANO | F5: La Mariscal | G5: CULTURAL | H5: Mercado Santa Clara | I5: Un ícono donde confluyen tradiciones ancestrales y vorágine urbana actual, el mercado Santa Clara seduce los sentidos. En sus pasillos, las caceras ofrecen especias, frutas, verduras y flores, mientras en el patio de comidas desborda gastronomía tradicional como hornado, yaguarlocro y seco de chivo con refrescantes jugos y batidos de huertos andinos. Afuera, artesanos exhiben trenzadas creaciones de mimbre, cabuya y alfarería. Las "yuyeras", mujeres que realizan "limpias", ritual curativo ancestral de purificación y florecimiento con flores y plantas andinas. Una cautivadora experiencia sensorial. | J5: Calle Antonio de Ulloa | K5: -0.19958008 | L5: -78.49946 | M5: 1 hora | N5: Lunes a Sábado 07h00 a 17h30 domingo 07h00 a 15h00 | O5: Depende del grupo y actividad | P5: Máximo 20 pax | Q5: Se consulta al momento de la limpia, si desea que se le limpie con el licor | R5: (+593) 99 271 8696 (+593) 98 742 0863
A6: 005 | B6: ACTIVO | C6: =CONCATENATE(VLOOKUP($D6,CODIFICACIÓN_DPA!$A$2:$B$66,2,FALSE),VLOOKUP($G6,CODIFICACIÓN_DPA!$D$2:$E$6,2,FALSE),CONCATENATE(VLOOKUP($E6,CODIFICACIÓN_DPA!$G$2:$H$3,2,FALSE),VLOOKUP($F6,CODIFICACIÓN_DPA!$J$2:$K$10,2,FALSE)),A6) -> 170112CU0103005 | D6: IÑAQUITO | E6: URBANO | F6: Centro Norte | G6: CULTURAL | H6: Salsoteca Lavoe | I6: Salsoteca Lavoe es el punto de encuentro ideal para los amantes de la salsa y para quienes desean descubrir la magia de este apasionante ritmo latino. Su ambiente vibrante acoge tanto a locales como a visitantes extranjeros que buscan vivir la noche quiteña al compás de la música y el baile. El lugar ofrece talleres de salsa y bachata para todos los niveles, invitando a disfrutar, aprender y dejarse llevar por la energía contagiosa del movimiento. Cada noche, la música en vivo y los DJ invitados transforman el espacio en una auténtica fiesta caribeña, donde la alegría, el sabor y la danza garantizan una experiencia inolvidable. | J6: "Iñaquito E2-17 y NNUU (Junto a la gasolinera Primax)" | K6: -0.1744392 | L6: -78.487209 | M6: Talleres de baile se realiza 20h00 durante una hora, en el horario de atención | N6: Miércoles a Sábado: 19h00 a 03h00 Domingos: 15h00 a 00h00 | O6: $7.00 - $8.00 | Q6: Mayores de 18 años | R6: Julio Olmedo (+593) 96 400 4478 lavoe.quito@gmail.com
A7: 006 | B7: ACTIVO | C7: =CONCATENATE(VLOOKUP($D7,CODIFICACIÓN_DPA!$A$2:$B$66,2,FALSE),VLOOKUP($G7,CODIFICACIÓN_DPA!$D$2:$E$6,2,FALSE),CONCATENATE(VLOOKUP($E7,CODIFICACIÓN_DPA!$G$2:$H$3,2,FALSE),VLOOKUP($F7,CODIFICACIÓN_DPA!$J$2:$K$10,2,FALSE)),A7) -> 170103CU0101006 | D7: CENTRO HISTÓRICO | E7: URBANO | F7: Centro Histórico | G7: CULTURAL | H7: Quito Eterno | I7: Quito Eterno convierte el Centro Histórico en un gran escenario donde la ciudad se cuenta a sí misma: recorridos teatralizados que enlazan iglesias, conventos, museos y barrios emblemáticos con una dramaturgia cuidada, protagonizada por personajes tradicionales que revelan leyendas, oficios antiguos y costumbres arraigadas. La arquitectura colonial y republicana dialoga con el patrimonio intangible en un hilo narrativo que emociona, mientras la música, la luz y la palabra ejecutada en vivo dibujan atmósferas íntimas en plazas, claustros y callejones. Es una experiencia estética y cultural de alta calidad, que rescata memoria y sentido de lugar, y hace brillar la riqueza histórica de Quito con sensibilidad contemporánea. | J7: Loma Grande. Fernández Madrid N 113 y Rocafuerte Capilla de los Milagros | K7: -0.22662326 | L7: -78.509493 | M7: 1 hora y 30 minutos | N7: Sábado 11h00 16h00,16h30 puede variar hasta las 19h00 Miércoles 19h00 | O7: Miércoles $20.00 (2x1) Sábados 11h00 ( $10.00 adultos) ($6.00 Tarifa diferenciada) Sábados 16h00 a 19h00 ($20.00 adultos) ($10.00 tarifa diferenciada) Pronto pago ($17.00 adultos) ($7.00 Tarifa diferenciada) | Q7: Recorridos a pie, Si se requiere un guía que hable en otro idioma, comunicar con anticipación al contacto 098 488 1018. Se puede reservar hasta con 4 horas de anticipación | R7: http://quitoeterno.org/ (+593) 98 488 1018 info@quitoeterno.org Adrián Gutiérrez
A8: 007 | B8: ACTIVO | C8: =CONCATENATE(VLOOKUP($D8,CODIFICACIÓN_DPA!$A$2:$B$66,2,FALSE),VLOOKUP($G8,CODIFICACIÓN_DPA!$D$2:$E$6,2,FALSE),CONCATENATE(VLOOKUP($E8,CODIFICACIÓN_DPA!$G$2:$H$3,2,FALSE),VLOOKUP($F8,CODIFICACIÓN_DPA!$J$2:$K$10,2,FALSE)),A8) -> 170123CU0102007 | D8: MARISCAL SUCRE | E8: URBANO | F8: La Mariscal | G8: CULTURAL | H8: Mon Atelier Quito | I8: En Mon Atelier, tanto parejas como padres e hijos disfrutan de una experiencia creativa y divertida mientras aprenden técnicas de pintura bajo la guía de talleristas especializados. Además de sumergirse en el arte, tienen la oportunidad de degustar exquisitos quesos y vinos seleccionados cuidadosamente para estimular su creatividad. Durante aproximadamente 2 horas, los artistas los acompañan paso a paso, asegurando que al finalizar, cada participante haya creado una obra maestra única. Todo esto se desarrolla en un ambiente creativo y estimulante, ideal para compartir momentos inolvidables en compañía de seres queridos. | J8: José Tamayo N24-525 y Luis Cordero | K8: -0.20341724 | L8: -78.485623 | M8: 2 horas | N8: Depende de las actividades que promocionen. Sin embargo su horario para actividad libre es: Lunes a Sabado en la mañana de 10:00-12:00 y en la tarde de 4:00 a 6:00 | O8: Costo por persona: $35.00 Incluye todos los materiales y una copa de vino | P8: Se adapta a la necesidad | R8: https://www.monatelierecuador.com/ 099 643 7788
A9: 008 | B9: ACTIVO | C9: =CONCATENATE(VLOOKUP($D9,CODIFICACIÓN_DPA!$A$2:$B$66,2,FALSE),VLOOKUP($G9,CODIFICACIÓN_DPA!$D$2:$E$6,2,FALSE),CONCATENATE(VLOOKUP($E9,CODIFICACIÓN_DPA!$G$2:$H$3,2,FALSE),VLOOKUP($F9,CODIFICACIÓN_DPA!$J$2:$K$10,2,FALSE)),A9) -> 170130CU0101008 | D9: SAN JUAN | E9: URBANO | F9: Centro Histórico | G9: CULTURAL | H9: La Caponata | I9: La Caponata es un rincón encantador del Centro Histórico que conquista con el auténtico sabor de la cocina italiana y siciliana. En un ambiente colonial acogedor, con patio interior y detalles artísticos, se disfrutan pastas frescas, pizzas al estilo tradicional y opciones vegetarianas y veganas que sorprenden por su sabor. A esto se suma la magia de la música en vivo, que crea una atmósfera vibrante y especial, haciendo de cada velada un encuentro inolvidable. Además, la experiencia se enriquece con actividades culturales como el tour a pie “Pata Caliente” a través de talleres y tiendas especializadas. | J9: García Moreno y Manabí Centro Histórico | K9: -0.21755945 | L9: -78.510565 | M9: 1 hora 30 minutos | N9: - Lunes a Sábado: 12h00 a 00h00 - Domingo: 12h00 a 20h00 | O9: Rango de precios $ 6.00 - $14.00 | Q9: Mayores de 18 años Recorridos a pie | R9: Pablo Iturralde (+593) 98 014 8251 info@lacaponata.com
A10: 009 | B10: ACTIVO | C10: =CONCATENATE(VLOOKUP($D10,CODIFICACIÓN_DPA!$A$2:$B$66,2,FALSE),VLOOKUP($G10,CODIFICACIÓN_DPA!$D$2:$E$6,2,FALSE),CONCATENATE(VLOOKUP($E10,CODIFICACIÓN_DPA!$G$2:$H$3,2,FALSE),VLOOKUP($F10,CODIFICACIÓN_DPA!$J$2:$K$10,2,FALSE)),A10) -> 170103CU0101009 | D10: CENTRO HISTÓRICO | E10: URBANO | F10: Centro Histórico | G10: CULTURAL | H10: Escuela Quiteña: Taller de Taracea | I10: La Escuela Quiteña: Taller de Taracea deslumbra con el arte de las incrustaciones finas—madera, concha, hueso, nácar y metales—que dan vida a piezas de autor, con los emblemáticos bargueños como sello distintivo. En este atelier, la maestría del tallado y el taraceado dialoga con la pintura y la escultura, integrando legado quiteño y diseño contemporáneo en obras de acabado exquisito. Un espacio donde el oficio alcanza categoría de arte, la historia se hace tangible en cada detalle y la elegancia artesanal conquista a primera vista. | J10: Calle Morales y Calle Venezuela , Casa 9-89 calle la “Ronda “ centro histórico de Quito , Quito, Ecuador | K10: -0.224263 | L10: -78.514054 | M10: 2 horas diarias | N10: Lunes a Viernes 9h00 a 18h00 | O10: $ 20 dólares por persona por hora | P10: mínimo 2 pax, máximo 15 pax | Q10: (No incluye materiales) | R10: José Luis Jiménez (+593) 98 444 1999 jjimenezarteaga@gmail.com
A11: 010 | B11: ACTIVO | C11: =CONCATENATE(VLOOKUP($D11,CODIFICACIÓN_DPA!$A$2:$B$66,2,FALSE),VLOOKUP($G11,CODIFICACIÓN_DPA!$D$2:$E$6,2,FALSE),CONCATENATE(VLOOKUP($E11,CODIFICACIÓN_DPA!$G$2:$H$3,2,FALSE),VLOOKUP($F11,CODIFICACIÓN_DPA!$J$2:$K$10,2,FALSE)),A11) -> 170103CU0101010 | D11: CENTRO HISTÓRICO | E11: URBANO | F11: Centro Histórico | G11: CULTURAL | H11: Hojalatería Silva | I11: En el corazón de Quito, la Hojalatería Silva mantiene viva una de las tradiciones más emblemáticas del arte popular quiteño. Bajo la dedicación de Martha Silva, quien heredó este oficio de su padre, el taller invita a los visitantes a descubrir el fascinante mundo de la hojalata a través de talleres participativos donde se aprende, se crea y se valora el trabajo artesanal. Cada pieza, desde coloridos juguetes hasta delicados utensilios, refleja la historia, la destreza y la pasión de generaciones de artesanos. Al finalizar la experiencia, los visitantes pueden adquirir piezas únicas y llevar consigo un auténtico recuerdo del arte tradicional quiteño. | J11: Calle Morales - La Ronda casa 925 | K11: -0.224263 | L11: -78.514054 | M11: 45 minutos | N11: lunes a jueves 10h00 a 17h00 viernes y sábados 10h00 - 20h00 domingo 10h00 - 16h00 | O11: Elaboración de silbato: $3.00 Elaboración de repujado: $3.00 Taller de blindado: $5.00 | P11: máximos 15 pax | R11: Marthita Silva (+593) 98 424 7622
A12: 011 | B12: ACTIVO | C12: =CONCATENATE(VLOOKUP($D12,CODIFICACIÓN_DPA!$A$2:$B$66,2,FALSE),VLOOKUP($G12,CODIFICACIÓN_DPA!$D$2:$E$6,2,FALSE),CONCATENATE(VLOOKUP($E12,CODIFICACIÓN_DPA!$G$2:$H$3,2,FALSE),VLOOKUP($F12,CODIFICACIÓN_DPA!$J$2:$K$10,2,FALSE)),A12) -> 170103CU0101011 | D12: CENTRO HISTÓRICO | E12: URBANO | F12: Centro Histórico | G12: CULTURAL | H12: Mercado De San Francisco | I12: Ubicado en el corazón del Centro Histórico, el Mercado de San Francisco es uno de los más antiguos y auténticos de Quito. Este espacio patrimonial conserva la esencia de la vida quiteña, donde los aromas, los colores y las tradiciones se entrelazan para ofrecer una experiencia única. Reconocido por ser el epicentro de las “curas” o “limpias” realizadas por las tradicionales hierbateras, el mercado invita a descubrir la sabiduría ancestral de la medicina andina, un legado que ha perdurado por generaciones. Además, sus puestos gastronómicos ofrecen una deliciosa muestra de la cocina popular quiteña, con caldos, jugos y platos típicos preparados con el sabor de la tradición. Visitar el Mercado de San Francisco es sumergirse en el corazón cultural de Quito, donde cada rincón cuenta una historia y cada aroma despierta la memoria de lo auténtico. | J12: Calle Rocafuerte. | K12: -0.21973704 | L12: -78.518576 | M12: 1 hora | N12: lunes a domingo 07h00 - 16h10 | O12: Depende del grupo y actividad | Q12: Se consulta al momento de la limpia, si desea que se le limpie con el licor
A13: 012 | B13: ACTIVO | C13: =CONCATENATE(VLOOKUP($D13,CODIFICACIÓN_DPA!$A$2:$B$66,2,FALSE),VLOOKUP($G13,CODIFICACIÓN_DPA!$D$2:$E$6,2,FALSE),CONCATENATE(VLOOKUP($E13,CODIFICACIÓN_DPA!$G$2:$H$3,2,FALSE),VLOOKUP($F13,CODIFICACIÓN_DPA!$J$2:$K$10,2,FALSE)),A13) -> 170112GA0103012 | D13: IÑAQUITO | E13: URBANO | F13: Centro Norte | G13: GASTRONÓMICO | H13: TO'AK Chocolate | I13: TO'AK ofrece una "Experiencia de Chocolate y Arte" donde los participantes disfrutarán de un recorrido privado por la casa del maestro Oswaldo Guayasamín, explorando todas sus estancias más íntimas de uno de los artistas más creativos de América Latina en el siglo pasado. La experiencia sensorial continúa con una degustación completa de granos de cacao crudos y tostados, así como de cuatro ediciones diferentes de To'ak Chocolate. Durante esta experiencia, los participantes recibirán explicaciones sobre las diferentes variedades de cacao ecuatoriano, su lugar de origen, los métodos de fermentación y el envejecimiento en barricas. Se explorará cómo estas variables de producción influyen en el perfil de sabor y aroma de cada expresión del chocolate. | J13: Mariano Calvache E18-94 y, Quito 170135 | K13: -0.19024789 | L13: -78.469012 | M13: 2 horas | N13: Lunes a Viernes 09h00 a 18h00 (EST) | O13: $125.00 por persona, con un mínimo de dos personas y un máximo de ocho personas. Los niños hasta 12 años entran gratis si van acompañados de dos adultos. | P13: 2 personas mínimo, 8 máximo | R13: Llamada/Texto: +1 (805) 600 8625 Ecuador: (+593) 2322 7520 https://toakchocolate.com/pages/chocolate-tour
A14: 013 | B14: ACTIVO | C14: =CONCATENATE(VLOOKUP($D14,CODIFICACIÓN_DPA!$A$2:$B$66,2,FALSE),VLOOKUP($G14,CODIFICACIÓN_DPA!$D$2:$E$6,2,FALSE),CONCATENATE(VLOOKUP($E14,CODIFICACIÓN_DPA!$G$2:$H$3,2,FALSE),VLOOKUP($F14,CODIFICACIÓN_DPA!$J$2:$K$10,2,FALSE)),A14) -> 170103GA0101013 | D14: CENTRO HISTÓRICO | E14: URBANO | F14: Centro Histórico | G14: GASTRONÓMICO | H14: Chez Tiff | I14: En el corazón de la ciudad, Chez Tiff invita a vivir una experiencia sensorial que celebra el cacao ecuatoriano en su máxima expresión. Esta chocolatería artesanal, pionera en el proceso “bean to bar”, transforma granos seleccionados de distintas regiones del país en auténticas obras de arte comestibles. Los visitantes pueden disfrutar de catas guiadas, conocer el proceso de elaboración del chocolate y descubrir la historia y diversidad del cacao nacional, reconocido entre los mejores del mundo. Cada barra, bombón o trufa elaborada en Chez Tiff refleja la pasión por la calidad, la innovación y el compromiso con la producción sostenible. | J14: García Moreno N7-39 y, Quito 170401 | K14: -0.21769412 | L14: -78.510837 | M14: Capacitación 1: 30 minutos Capacitación 2: 40 minutos Capacitación 3: 90 minutos Capacitación 4: 90 minutos Capacitación 5: 60 minutos | N14: Lunes a Viernes de 10h00 a 18h30 Sabado y Domingo de 11h00 a 17h30 | O14: Capacitación 1: De 1 pax a 5 pax: $20,00 + IVA (costo por grupo) A partir de la 6ta persona: $3,50 + IVA (costo por persona) Capacitación 2: 1 a 5 $39,50 + IVA (costo por grupo) De 6 pax en adelante: $6,50 + IVA (costo por persona) Capacitación 3: De 1 pax a 5 pax: $54 + IVA (costo por grupo) De 6 pax en adelante: $ 10,50 + IVA (costo por persona) Capacitación 4: COSTOS: 1 a 5 pax: $85 + IVA (costo por grupo) 6 a 9 pax: $15 + IVA (costo por persona) Capacitación 5: 1 a 5 pax: $85 + IVA (costo por grupo) 6 a 9 pax: $15 + IVA (costo por persona) | P14: 30 personas maxino | R14: Cristina Báez-Montenegro WhatsApp: (+593) 99 625 8948.
A15: 014 | B15: ACTIVO | C15: =CONCATENATE(VLOOKUP($D15,CODIFICACIÓN_DPA!$A$2:$B$66,2,FALSE),VLOOKUP($G15,CODIFICACIÓN_DPA!$D$2:$E$6,2,FALSE),CONCATENATE(VLOOKUP($E15,CODIFICACIÓN_DPA!$G$2:$H$3,2,FALSE),VLOOKUP($F15,CODIFICACIÓN_DPA!$J$2:$K$10,2,FALSE)),A15) -> 170123GA0102014 | D15: MARISCAL SUCRE | E15: URBANO | F15: La Mariscal | G15: GASTRONÓMICO | H15: Chocolate Pacari | I15: Chocolate Pacari ofrece experiencias de cata de chocolate y elaboración de trufas, durante las cuales los participantes pueden degustar una selección de bombones mientras se sumergen en la rica historia del cacao en Ecuador. Además, tienen la oportunidad de conocer la dedicada trayectoria y compromiso de sostenibilidad de Pacari con los productores de cacao. Estas catas representan una experiencia sensorial completa, invitando a los participantes a agudizar sus sentidos para apreciar las cualidades únicas de cada chocolate. Se explora su aspecto visual, aroma, sonido al partirlo y, por supuesto, su delicioso sabor. Esta experiencia no solo es placentera, sino también educativa, brindando la oportunidad de aprender sobre el proceso histórico del cacao ecuatoriano. | J15: Julio Zaldumbide N24-713 Y, Quito 170150 | K15: -0.20590726 | L15: -78.480807 | M15: 1 hora | N15: Lunes a Jueves 8h00 a 20h00 Viernes a Sábado a domingo 8h00 a 10h00 | O15: $10.00 por persona, el guía y personal gratis. | P15: 1 persona - 50 personas | Q15: Alérgicos a las almendras | R15: "https://www.facebook.com/PaccariChocolate (02) 380 9230/ 0958749233 Alejandra Calderón."
A16: 015 | B16: ACTIVO | C16: =CONCATENATE(VLOOKUP($D16,CODIFICACIÓN_DPA!$A$2:$B$66,2,FALSE),VLOOKUP($G16,CODIFICACIÓN_DPA!$D$2:$E$6,2,FALSE),CONCATENATE(VLOOKUP($E16,CODIFICACIÓN_DPA!$G$2:$H$3,2,FALSE),VLOOKUP($F16,CODIFICACIÓN_DPA!$J$2:$K$10,2,FALSE)),A16) -> 170103GA0101015 | D16: CENTRO HISTÓRICO | E16: URBANO | F16: Centro Histórico | G16: GASTRONÓMICO | H16: Hotel Carlota | I16: Ubicado en una casa patrimonial del siglo XIX, el Hotel Carlota combina historia, diseño y sostenibilidad en pleno corazón del Centro Histórico de Quito. Su restauración ha preservado los detalles arquitectónicos originales, integrándolos con un estilo moderno que resalta la autenticidad de su entorno. Cada habitación cuenta una historia distinta, inspirada en la ciudad y su cultura, mientras que los espacios comunes invitan al descanso y la contemplación. Su terraza ofrece una vista privilegiada de los tejados coloniales y las cúpulas quiteñas, creando un ambiente ideal para disfrutar de una bebida o una cena con encanto local. El Hotel Carlota es más que un alojamiento: es una experiencia urbana y patrimonial que refleja la esencia de Quito con elegancia, calidez y compromiso ambiental. | J16: Benalcázar N 6-26 y Mejía. Quito, Ecuador | K16: -0.21801886 | L16: -78.512052 | M16: 2 horas | N16: Bajo reserva | O16: Arte en Carlota: Desayuno + clase: $65.00 Brunch + clase: $88.00 Menú Lounge + clase: $82.00 Clase:$55.00 Clase de cocina: $45.00 Cata de chocolate y gin: $45.00 | R16: https://carlota.ec/ (+593) 99 922 3336 / (+593) 98 495 2689
A17: 016 | B17: ACTIVO | C17: =CONCATENATE(VLOOKUP($D17,CODIFICACIÓN_DPA!$A$2:$B$66,2,FALSE),VLOOKUP($G17,CODIFICACIÓN_DPA!$D$2:$E$6,2,FALSE),CONCATENATE(VLOOKUP($E17,CODIFICACIÓN_DPA!$G$2:$H$3,2,FALSE),VLOOKUP($F17,CODIFICACIÓN_DPA!$J$2:$K$10,2,FALSE)),A17) -> 170179GA0208016 | D17: PUEMBO | E17: RURAL | F17: Valle de Tumbaco | G17: GASTRONÓMICO | H17: Páramo Brauhaus | I17: La Cervecería Páramo ofrece una experiencia única para los amantes de la cerveza artesanal. Los visitantes tienen la oportunidad de conocer de cerca el proceso de elaboración de la cerveza artesanal durante una visita a su fábrica. Además, pueden disfrutar de una emocionante cata de cerveza artesanal, donde pueden deleitarse con una variedad de sabores y estilos únicos. Esta experiencia brinda una mirada íntima al mundo de la cerveza artesanal y promete satisfacer los paladares más exigentes con sus deliciosas creaciones. | J17: Puembo- Santa Rosa y, Av. Oswaldo Guayasamín, Quito 170905 | K17: -0.20718541 | L17: -78.365028 | M17: 1 hora 30 minutos | N17: Lunes a Viernes 08:00 – 17:00 Páramo Biergarten: Viernes: 12:00 – 22:00 Sábado y domingo: 10:00 – 17:00 | O17: $15.00 por persona | P17: 20 a 50 personas | R17: (02) 389 5435 (+593) 99 271 5573 / (+593) 99 306 9654 Judith Bauer.
A18: 017 | B18: ACTIVO | C18: =CONCATENATE(VLOOKUP($D18,CODIFICACIÓN_DPA!$A$2:$B$66,2,FALSE),VLOOKUP($G18,CODIFICACIÓN_DPA!$D$2:$E$6,2,FALSE),CONCATENATE(VLOOKUP($E18,CODIFICACIÓN_DPA!$G$2:$H$3,2,FALSE),VLOOKUP($F18,CODIFICACIÓN_DPA!$J$2:$K$10,2,FALSE)),A18) -> 170177GA0204017 | D18: POMASQUI | E18: RURAL | F18: Parroquias Equinocciales | G18: GASTRONÓMICO | H18: Cervecería Quiteña Craft Beer Company | I18: Cervecería Quiteña Craft Beer Company ofrece una experiencia única de maridaje entre cerveza artesanal y embutidos también artesanales, elaborados en el lugar con dedicación y pasión. Los visitantes tienen la oportunidad de sumergirse en la historia y el proceso de producción de la cerveza, mediante un recorrido por las instalaciones de la planta cervecera, donde se revelan los secretos de la elaboración de esta bebida milenaria. Además, se ofrece una degustación completa de todos los tipos de cerveza producidos, permitiendo a los participantes explorar una amplia gama de sabores y estilos, mientras aprenden sobre las características únicas de cada una. Este encuentro con la artesanía cervecera y la tradición culinaria local promete deleitar los sentidos y brindar una experiencia memorable para los amantes de la buena comida y la cerveza de calidad. | J18: Av. Manuel Córdova Galarza S4-187 y Marcelina Nolivos. 300 m más al norte del Colegio Francés. Junto a Helados Avelina. | K18: -0.057720144 | L18: -78.457537 | M18: 1 hora | N18: Bajo reserva | O18: $ 15.00 por persona | P18: Mínimo 6 pax (incluido guía) en un horario fuera de lo normal Máximo 40 pax (incluido guía) | R18: andres.eraso@gmail.com https://www.facebook.com/CerveceriaQuiteña (+593) 99 552 8651
A19: 018 | B19: ACTIVO | C19: =CONCATENATE(VLOOKUP($D19,CODIFICACIÓN_DPA!$A$2:$B$66,2,FALSE),VLOOKUP($G19,CODIFICACIÓN_DPA!$D$2:$E$6,2,FALSE),CONCATENATE(VLOOKUP($E19,CODIFICACIÓN_DPA!$G$2:$H$3,2,FALSE),VLOOKUP($F19,CODIFICACIÓN_DPA!$J$2:$K$10,2,FALSE)),A19) -> 170180GA0204018 | D19: SAN ANTONIO | E19: RURAL | F19: Parroquias Equinocciales | G19: GASTRONÓMICO | H19: Santana Brewing Company | I19: Santana Brewing Company, establecida en 2012, es un destino imprescindible para los amantes de la cerveza artesanal. Ofrecen una experiencia única donde los visitantes pueden disfrutar de una cata de cervezas artesanales en armonía con una selección de platos nacionales contemporáneos. Cada plato está cuidadosamente elaborado para realzar y complementar los sabores de las cervezas, brindando así una experiencia gastronómica excepcional. En Santana Brewing Company, la pasión por la cerveza de calidad y la cocina local se fusionan para crear una experiencia memorable para los paladares más exigentes. | J19: Mitad del Mundo | K19: 0.001039806 | L19: -78.451559 | M19: 1 hora | N19: Miércoles a Domingo 12h00 a 17h00 | O19: $15.00 por persona | P19: Máximo 10 pax | R19: (+593) 96 125 3653 info@santanabc.com
A20: 019 | B20: ACTIVO | C20: =CONCATENATE(VLOOKUP($D20,CODIFICACIÓN_DPA!$A$2:$B$66,2,FALSE),VLOOKUP($G20,CODIFICACIÓN_DPA!$D$2:$E$6,2,FALSE),CONCATENATE(VLOOKUP($E20,CODIFICACIÓN_DPA!$G$2:$H$3,2,FALSE),VLOOKUP($F20,CODIFICACIÓN_DPA!$J$2:$K$10,2,FALSE)),A20) -> 170103GA0101019 | D20: CENTRO HISTÓRICO | E20: URBANO | F20: Centro Histórico | G20: GASTRONÓMICO | H20: Heladería Dulce Jesús Mío | I20: La Heladería Dulce Jesús Mío ofrece una experiencia única para los amantes del helado, donde la degustación se transforma en un viaje por la tradición y la innovación. Reconocida por su impresionante variedad de helados artesanales, aquí se combina la creatividad contemporánea con la técnica ancestral del helado de paila, elaborado de forma tradicional y con ingredientes frescos. Durante la visita, los anfitriones comparten la historia detrás de cada creación, invitando a probar propuestas exóticas como morocho, colada morada, canelazo o mojito, que sorprenden por su autenticidad y equilibrio. Más que un lugar para disfrutar un postre, Dulce Jesús Mío es una celebración del ingenio local y de la riqueza de la cultura gastronómica quiteña, donde cada cucharada evoca dulzura, identidad y alegría. | J20: Morales OE 325 170130 Quito, Ecuador | K20: -0.22401415 | L20: -78.514053 | M20: 1 hora | N20: Todos los días de 10h00 a 18h00 | O20: Depende del recipiente para servirse. $1.00 - $3.50 | P20: Hasta 32 personas | R20: (+593) 98 408 5720
A21: 020 | B21: ACTIVO | C21: =CONCATENATE(VLOOKUP($D21,CODIFICACIÓN_DPA!$A$2:$B$66,2,FALSE),VLOOKUP($G21,CODIFICACIÓN_DPA!$D$2:$E$6,2,FALSE),CONCATENATE(VLOOKUP($E21,CODIFICACIÓN_DPA!$G$2:$H$3,2,FALSE),VLOOKUP($F21,CODIFICACIÓN_DPA!$J$2:$K$10,2,FALSE)),A21) -> 170123GA0102020 | D21: MARISCAL SUCRE | E21: URBANO | F21: La Mariscal | G21: GASTRONÓMICO | H21: Cherusker | I21: Cherusker, desde su fundación en 2011, se ha dedicado a elaborar cervezas artesanales que rinden homenaje a los estilos clásicos alemanes y europeos. Siguiendo la icónica ley de pureza alemana "Reinheitsgebot" de 1516, diversifican detalles y texturas para adaptarse al gusto nacional, logrando así una perfecta fusión entre la tradición cervecera y el encanto del Ecuador. En Cherusker, los visitantes tienen la oportunidad de vivir una experiencia única al degustar su variedad de cervezas artesanales, explorando los distintos matices y sabores que ofrecen. | J21: Joaquín Pinto E7-85 y Diego de Almagro | K21: -0.2035489 | L21: -78.490986 | M21: Depende del grupo | N21: Lunes 16h00 a 00h00 Martes y miercoles 13h00 a 00h00 Jueves a sábado de 12h00 a 02h00 | O21: Variados | P21: Se adapta a la necesidad | Q21: Mayores de 18 años | R21: (02) 6012 142 reservaciones.uio@cherusker.com
A22: 021 | B22: ACTIVO | C22: =CONCATENATE(VLOOKUP($D22,CODIFICACIÓN_DPA!$A$2:$B$66,2,FALSE),VLOOKUP($G22,CODIFICACIÓN_DPA!$D$2:$E$6,2,FALSE),CONCATENATE(VLOOKUP($E22,CODIFICACIÓN_DPA!$G$2:$H$3,2,FALSE),VLOOKUP($F22,CODIFICACIÓN_DPA!$J$2:$K$10,2,FALSE)),A22) -> 170177GA0204021 | D22: POMASQUI | E22: RURAL | F22: Parroquias Equinocciales | G22: GASTRONÓMICO | H22: Casa Agave Ecuador | I22: Casa Agave Ecuador ofrece una experiencia única que combina naturaleza, cultura y degustación. Los visitantes tienen la oportunidad de explorar su impresionante jardín botánico acompañados de un guía especializado, descubriendo la diversidad y belleza de las plantas de agave. Además, podrán sumergirse en la historia y el proceso de elaboración de los productos de agave en el museo de la casa. Para culminar la experiencia, los invitados pueden deleitarse con la degustación de "mishki", una bebida tradicional, y disfrutar de una cata de cócteles preparados con maestría por el equipo de la casa. | J22: Quishuar N3-29 y Casitagua - Pomasqui | K22: -0.048083003 | L22: -78.455766 | M22: 1 hora 30 minutos | N22: Martes a domingo 11h00 a 17h00 Recorridos 11h30 13h30 15h00 17h00 | O22: Entrada al museo, jardín botánico, cata de mishke Para público general $17.00 Para agencia; $15.00 Precio no incluye IVA | R22: Belén Simbaña Llamar (+593) 99 831 6455 casaagaveoficial@gmail.com m.me/agavemitaddelmundo http://agavespiritecuador.com
A23: 022 | B23: ACTIVO | C23: =CONCATENATE(VLOOKUP($D23,CODIFICACIÓN_DPA!$A$2:$B$66,2,FALSE),VLOOKUP($G23,CODIFICACIÓN_DPA!$D$2:$E$6,2,FALSE),CONCATENATE(VLOOKUP($E23,CODIFICACIÓN_DPA!$G$2:$H$3,2,FALSE),VLOOKUP($F23,CODIFICACIÓN_DPA!$J$2:$K$10,2,FALSE)),A23) -> 170103GA0101022 | D23: CENTRO HISTÓRICO | E23: URBANO | F23: Centro Histórico | G23: GASTRONÓMICO | H23: Yumbos Chocolate | I23: Chocolate Yumbo ofrece una experiencia auténtica y deliciosa para los amantes del chocolate. Su chocolate puro, producido a mano y sin conservantes ni saborizantes artificiales, proviene de lotes de cacao seleccionado de variedades aromáticas, como el Nacional Fino y de Aroma, característico de Ecuador. En este espacio, los visitantes pueden sumergirse en el proceso de tostado y elaboración del chocolate desde cero, aprendiendo sobre las técnicas tradicionales utilizadas antiguamente y degustando su exquisito chocolate caliente acompañado de un brownie elaborado con el más puro chocolate. Además, Chocolate Yumbo ofrece actividades como el "Festín de Chocolate", una experiencia de degustación donde los participantes pueden disfrutar de una selección de chocolates acompañados de una copa de vino, para una experiencia verdaderamente indulgente. | J23: Quito: Calle Sebastián de Benalcázar N 2-26 Segundo Piso (Frente a la Iglesia San Francisco) Mindo: Avenida Quito (a 1 cuadra de la plaza central de Mindo) | K23: -0.22094148 | L23: -78.514713 | M23: 1 hora | N23: QUITO: 09h30 a 19h00 MINDO: Tours disponibles a partir de las 10h00 a 22h00 todos los días de la semana. | O23: - Mindo: Tour Chocolate Experiencia Tradicional : $10.00 Tour Chocolate Experiencia Ancestral: $15.00 - Quito: Tour Chocolate Experiencia Tradicional : $10.00 Tour Chocolate Experiencia Ancestral: $15.00 - Quito: Degustación chocolate caliente 4 oz: $4.00 Degustación chocolate caliente 6 oz: $6.00 Cata de vino: $12.00 Cata de Cerveza: $12.00 Productos: -Barras chocolate: $6.50 -Polvo de cacao: $12.00 -Syrup de cacao: $8.00 -Salsa BBQ de chocolate: $8.00 -Jarabe de jengibre: $7.00 -Té de cacao: $6.50 -Pastillas de chocolate al 100%: $15.00 -Almendra de cacao la (oz) bajo pedido : $1.00 -Mini barras: $1.50 Los precios incluyen IVA | R23: Claudia Ponce (+593) 98 000 4417 Facebook: @YumbosChocolate www.yumboschocolate.com contact@yumboschocolate.com instagram: yumboschocolate.ec
A24: 023 | B24: ACTIVO | C24: =CONCATENATE(VLOOKUP($D24,CODIFICACIÓN_DPA!$A$2:$B$66,2,FALSE),VLOOKUP($G24,CODIFICACIÓN_DPA!$D$2:$E$6,2,FALSE),CONCATENATE(VLOOKUP($E24,CODIFICACIÓN_DPA!$G$2:$H$3,2,FALSE),VLOOKUP($F24,CODIFICACIÓN_DPA!$J$2:$K$10,2,FALSE)),A24) -> 170103GA0101023 | D24: CENTRO HISTÓRICO | E24: URBANO | F24: Centro Histórico | G24: GASTRONÓMICO | H24: República del Cacao | I24: Se puede encontrar los productos del Chocolate Boutique en donde se ofrece todas las presentaciones de barras y regalos de República del Cacao. Por otro lado está el Rincón del Emprendedor, proyecto que apoya a emprendedores que realizan productos con chocolate o productos inspirados en el cacao. También está el Taller del Cacao ejecutado por el chef Santiago Cueva, en donde se ofrecen bombones únicos realizados con chocolate de cacao fino y repostería de muy alta calidad; todos estos productos se realizan en el nuevo Laboratorio de República del Cacao que también se encuentra en el local del Centro Histórico. Finalmente los clientes pueden visitar el Museo del Cacao en donde pueden aprender sobre él la historia del cacao en el Ecuador, y el proceso del mismo. | J24: Venezuela N5-45 y Chile, a 15 metros de la Plaza Grande. | K24: -0.21956107 | L24: -78.511079 | M24: 1hora 30 minutos | N24: 08h30 a 19h30 | O24: $15.00 por personas. Previa reserva de 24 horas | P24: Máximo 20 pax | Q24: Personas alérgicas al chocolate | R24: (+593) 98 346 3290 https://republicadelcacao.com/pages/stores
A25: 024 | B25: ACTIVO | C25: =CONCATENATE(VLOOKUP($D25,CODIFICACIÓN_DPA!$A$2:$B$66,2,FALSE),VLOOKUP($G25,CODIFICACIÓN_DPA!$D$2:$E$6,2,FALSE),CONCATENATE(VLOOKUP($E25,CODIFICACIÓN_DPA!$G$2:$H$3,2,FALSE),VLOOKUP($F25,CODIFICACIÓN_DPA!$J$2:$K$10,2,FALSE)),A25) -> 170112GA0103024 | D25: IÑAQUITO | E25: URBANO | F25: Centro Norte | G25: GASTRONÓMICO | H25: Mercado Iñaquito (Mercado La Carolina) | I25: La experiencia gastronómica en el Mercado Iñaquito, también conocido como Mercado La Carolina, es verdaderamente diversa y vibrante. A pesar de mantener su enfoque en la venta de productos de primera necesidad a precios accesibles, el mercado ofrece una amplia variedad de opciones culinarias que reflejan la riqueza y la autenticidad de la cocina local. Con locales adyacentes que ofrecen desde platos típicos ecuatorianos hasta opciones internacionales, los visitantes pueden deleitarse con una verdadera aventura gastronómica mientras exploran los pasillos del mercado. Desde sabores tradicionales hasta innovadoras propuestas culinarias, el Mercado Iñaquito es un destino imprescindible para los amantes de la comida que buscan una experiencia auténtica y satisfactoria. | J25: Calle Iñaquito y Pereira | K25: -0.17181432 | L25: -78.48627 | M25: 1 hora | N25: Lunes a Domingo 07h00 a 18h00 | O25: Depende del grupo y actividad | P25: Máximo 20 pax | R25: (+593) 99 468 1378
A26: 025 | B26: ACTIVO | C26: =CONCATENATE(VLOOKUP($D26,CODIFICACIÓN_DPA!$A$2:$B$66,2,FALSE),VLOOKUP($G26,CODIFICACIÓN_DPA!$D$2:$E$6,2,FALSE),CONCATENATE(VLOOKUP($E26,CODIFICACIÓN_DPA!$G$2:$H$3,2,FALSE),VLOOKUP($F26,CODIFICACIÓN_DPA!$J$2:$K$10,2,FALSE)),A26) -> 170103GA0101025 | D26: CENTRO HISTÓRICO | E26: URBANO | F26: Centro Histórico | G26: GASTRONÓMICO | H26: Mercado Central | I26: La experiencia gastronómica en el Mercado Central es una inmersión en las tradiciones culinarias de la capital. Con el 60% de los comerciantes dedicados a ofrecer platos que son emblemáticos de la cultura local, los visitantes pueden disfrutar de una variedad de delicias que incluyen la auténtica colada de churos, el reconfortante caldo bille, el sabroso caldo de guagrasinga y las deliciosas corvinas preparadas de diversas maneras. Esta diversidad de sabores y platos refleja la riqueza gastronómica de la región y ofrece a los comensales una experiencia auténtica y memorable en el corazón del Mercado Central. | J26: Av. Pichincha entre Manabí y Esmeraldas | K26: -0.21970285 | L26: -78.507084 | N26: lunes a domingo 07h00 - 15h00 | O26: Depende del grupo | Q26: Se consulta sobre el plato a degustar dado que son platos poco comunes. Anticipar alergías al maní, mariscos, intolerantes a la lactosa. | R26: (+593) 99 891 0022
A27: 026 | B27: ACTIVO | C27: =CONCATENATE(VLOOKUP($D27,CODIFICACIÓN_DPA!$A$2:$B$66,2,FALSE),VLOOKUP($G27,CODIFICACIÓN_DPA!$D$2:$E$6,2,FALSE),CONCATENATE(VLOOKUP($E27,CODIFICACIÓN_DPA!$G$2:$H$3,2,FALSE),VLOOKUP($F27,CODIFICACIÓN_DPA!$J$2:$K$10,2,FALSE)),A27) -> 170175NA0208026 | D27: PIFO | E27: RURAL | F27: Valle de Tumbaco | G27: NATURAL | H27: Hacienda Jimenita Naturhotel & Reserva de Vida Silvestre | I27: La Hacienda Jimenita Naturhotel & Reserva de Vida Silvestre ofrece una experiencia única donde la tranquilidad se fusiona con la exuberante naturaleza. Los huéspedes pueden sumergirse en un entorno de serenidad y descubrir la magia de la vida silvestre mientras participan en una variedad de actividades emocionantes y educativas. Desde la observación de aves en la reserva natural hasta la exploración de senderos históricos y la participación en actividades de siembra y cosecha de alimentos orgánicos, cada momento en la hacienda ofrece la oportunidad de conectarse con la tierra y aprender sobre la rica cultura ecológica de la región. Con opciones como clases de cocina, paseos a caballo por los Andes y tours hacia Papallacta y el Parque Nacional Antisana, la Hacienda Jimenita brinda una experiencia inolvidable para los amantes de la naturaleza y la aventura. | J27: Barrio Andrango Pasaje 2, Casa 19, Parroquia Pifo | K27: -0.23454809 | L27: -78.349949 | M27: Observación de aves: 2 horas Sendero Histórico: sin restricción Alimenta a las llamas: sin restricción Siembre y Cosecha: 06h00 a 17h00 Clases de cocina: 1 a 2 horas Paseo a Caballo en los Andes: 5 horas Tour de la Rosa Gigante: 2 horas Tour del Cóndor: 5 horas | N27: Observación de aves: 07h00 a 10h00 y de 14:00 a 18:00 Sendero Histórico: Cualquier hora Alimenta a las llamas: 06h00 a 20h00 Siembre y Cosecha: 06h00 a 17h00 Clases de cocina: 06h00 a 20h00 Paseo a Caballo en los Andes: parte desde la hacienda a las 08h00 y 09h00 Tour de la Rosa Gigante: parte desde la hacienda a las 08h00 y 09h00 Tour del Cóndor: parte desde la hacienda a las 06h00 a 07h00 | O27: Observación de aves: $60.00 Sendero Histórico: No tiene costo, debe estar hospedado Alimenta a las llamas: Canasta de alimentos $5.00, debe estar hospedado Siembre y Cosecha: No tiene costo, debe estar hospedado Clases de cocina: $50.00 a $80.00 inlcuye todos los utensillos e insumos Paseo a Caballo en los Andes: $140.00 Tour de la Rosa Gigante: $60.00 Tour del Cóndor: $180.00 Precios no incluyen IVA | P27: Entre 10 a 12 participantes, en las actividades que son necesarios guías o chef | R27: Karina Morejón (+593) 95 860 4606 (+593) 99 923 8048 info@jimenita.com ventas@jimenita.com
A28: 027 | B28: ACTIVO | C28: =CONCATENATE(VLOOKUP($D28,CODIFICACIÓN_DPA!$A$2:$B$66,2,FALSE),VLOOKUP($G28,CODIFICACIÓN_DPA!$D$2:$E$6,2,FALSE),CONCATENATE(VLOOKUP($E28,CODIFICACIÓN_DPA!$G$2:$H$3,2,FALSE),VLOOKUP($F28,CODIFICACIÓN_DPA!$J$2:$K$10,2,FALSE)),A28) -> 170175NA0208027 | D28: PIFO | E28: RURAL | F28: Valle de Tumbaco | G28: NATURAL | H28: Sacha Rose | I28: Se caracterizan por tener las rosas más grandes del mundo es la marca registrada de esta florícola. Se caracterizan por constantes en la calidad, el compromiso con la comunidad, la productividad sostenible y el compromiso con el medio ambiente. Brinda la experiencia de Tour guiados para turistas nacionales y extranjeros y la visita al invernadero donde están las rosas, explicación de la productividad, tipo de cultivo, post cosecha, café con galletas de cortesía. | J28: Vía Pifo-Papallacta Km 8 | K28: -0.26947666 | L28: -78.285611 | M28: 45 minutos | N28: 07h00 a 15h00 | O28: Tours guiados $10.00 + IVA | P28: Mínimo 5 turistas | Q28: Los días sábado y domingo; para brindar la experiencia, debe haber mínimo 5 turistas, de lunes a viernes no es inconveniente la cantidad de turistas. Siempre hacer reserva con 3 días de anticipación, al correo auxiliar@sacharose.com o al número +593 99 833 8944. Los guías hablan español, en caso de necesitar un guía que hable inglés, el dueño podría ayudar con la experiencia | R28: Ing. Guillermo Bustamante Teléfono: (02) 450 8929 Celular: (+593) 99 833 8944 VENTAS: Hemerson Salazar Correo: Skype sales_sacha Instagram: @sacharoseec Mail: gerencia@sacharose.com Ana Cajamarca auxiliar@sacharose.com
A29: 028 | B29: ACTIVO | C29: =CONCATENATE(VLOOKUP($D29,CODIFICACIÓN_DPA!$A$2:$B$66,2,FALSE),VLOOKUP($G29,CODIFICACIÓN_DPA!$D$2:$E$6,2,FALSE),CONCATENATE(VLOOKUP($E29,CODIFICACIÓN_DPA!$G$2:$H$3,2,FALSE),VLOOKUP($F29,CODIFICACIÓN_DPA!$J$2:$K$10,2,FALSE)),A29) -> 170172NA0205028 | D29: PACTO | E29: RURAL | F29: Chocó Andino | G29: NATURAL | H29: Pambiliño Bosque escuela. | I29: Pambiliño Bosque Escuela ofrece una experiencia inmersiva en el exuberante bosque lluvioso del Chocó Andino, situado a 550 metros sobre el nivel del mar, en las afueras de Quito. Este espacio único presenta una biodiversidad impresionante que está bajo amenaza, brindando la oportunidad de participar en el turismo vivencial. Los visitantes pueden explorar el bosque con una variedad de actividades flexibles, que incluyen cursos y talleres sobre agricultura sostenible, descubrimiento sensorial en el bosque, laboratorios de alimentos, así como también opciones de turismo vivencial como gastronomía y senderismo guiado. Con opciones de hospedaje y alimentación disponibles dentro de la finca Pambiliño, los visitantes pueden diseñar una experiencia a medida que se adapte a sus intereses y preferencias. | J29: Vía a Mashpi. 53 JR+Q45, Quito | K29: 0.18211233 | L29: -78.909785 | M29: Sendero Regeneración Natural: 2 horas Gastronomía del Bosque: 4 horas Sendero Eco Restauración: 3 horas Aves, fauna y flora: 2 horas Baño en el río: tiempo libre | N29: Bajo reserva | O29: Sendero Regeneración Natural: $10.00 Gastronomía del Bosque:$20.00 Sendero Eco Restauración:$15.00 Aves, fauna y flora: $10.00 Baño en el río: aporte voluntario | P29: Se adapta a la necesidad del grupo. | R29: https://www.pambilino.org/turismo-vivencial
A30: 029 | B30: INACTIVO | C30: =CONCATENATE(VLOOKUP($D30,CODIFICACIÓN_DPA!$A$2:$B$66,2,FALSE),VLOOKUP($G30,CODIFICACIÓN_DPA!$D$2:$E$6,2,FALSE),CONCATENATE(VLOOKUP($E30,CODIFICACIÓN_DPA!$G$2:$H$3,2,FALSE),VLOOKUP($F30,CODIFICACIÓN_DPA!$J$2:$K$10,2,FALSE)),A30) -> 170103CU0101029 | D30: CENTRO HISTÓRICO | E30: URBANO | F30: Centro Histórico | G30: CULTURAL | H30: Convento de San Agustín | I30: En pleno Centro Histórico, el Convento de San Agustín resguarda siglos de historia, arte y espiritualidad. Este majestuoso conjunto arquitectónico, construido entre los siglos XVI y XVII, alberga una de las iglesias más bellas de Quito y el Museo Miguel de Santiago, donde se conservan lienzos y esculturas de la Escuela Quiteña. Habitualmente abierto para recorridos por la iglesia principal, los claustros y las salas que guardan verdaderas joyas del arte barroco. En ocasiones especiales, se habilitan visitas ampliadas que incluyen patios, torres o espacios internos, ofreciendo una mirada exclusiva a este tesoro patrimonial. Más que un monumento religioso, el Convento de San Agustín es un encuentro con la esencia de Quito: un lugar donde el silencio, la belleza y la historia se funden para inspirar a quienes lo recorren. No se olvide de probar sus productos como licor canario, galletas, pasteles frescos, o agua de rosas. | J30: Guayaquil N5-59 y Chile | K30: -0.22135 | L30: -78.51298 | M30: Depende del recorrido | N30: Bajo reserva | O30: Depende del grupo
A31: 030 | B31: ACTIVO | C31: =CONCATENATE(VLOOKUP($D31,CODIFICACIÓN_DPA!$A$2:$B$66,2,FALSE),VLOOKUP($G31,CODIFICACIÓN_DPA!$D$2:$E$6,2,FALSE),CONCATENATE(VLOOKUP($E31,CODIFICACIÓN_DPA!$G$2:$H$3,2,FALSE),VLOOKUP($F31,CODIFICACIÓN_DPA!$J$2:$K$10,2,FALSE)),A31) -> 170154GA0205030 | D31: CALACALÍ | E31: RURAL | F31: Chocó Andino | G31: GASTRONÓMICO | H31: LA CUCHARA ORGÁNICA | I31: La Cuchara Orgánica es mucho más que un restaurante, es un espacio comprometido con la revalorización de saberes ancestrales, el comercio justo y la cocina saludable y consciente. Ofrecen una variedad de experiencias gastronómicas únicas que van desde talleres especializados de cocina saludable con Mamita Pastora, donde se enseñan platos tradicionales ecuatorianos y recetas con plantas no convencionales del Chocó Andino, hasta experiencias de aprendizaje y degustación de productos como la savia del agave andino y productos derivados. También ofrecen catas y elaboración de infusiones, bebidas, barras de chocolate y bombones con café y cacao del Chocó Andino. Los domingos, brindan actividades educativas y divertidas para niños con clases de cocina y juegos tradicionales. Además, ofrecen tours educativos por su pequeña huerta andina y por la localidad de Calacalí, donde se visitan monumentos, se degustan dulces tradicionales y se participa en rituales andinos de agradecimiento. Estas experiencias proporcionan una conexión profunda con la cultura, la naturaleza y la gastronomía de la región. | J31: Juan José Flores E536 y pasaje Luis Calderón, Calacalí, Ecuador | K31: -0.0005587098 | L31: -78.509011 | M31: Depende del recorrido | N31: Miercoles a domingo 10h00 a 17h00 | O31: Experiencia cocinando con Mamita Pastora: depende de la activida que se elija si especializada o express. Experiencia Tzawar: USD 7 Experiencia Café y Cacao del Chocó Andino: USD 7 Experiencia Wawas en La Cuchara: actividad gratuita con aporte voluntario. | P31: Mínimo 10 personas, máximo 20. | R31: 969006237
A32: 031 | B32: ACTIVO | C32: =CONCATENATE(VLOOKUP($D32,CODIFICACIÓN_DPA!$A$2:$B$66,2,FALSE),VLOOKUP($G32,CODIFICACIÓN_DPA!$D$2:$E$6,2,FALSE),CONCATENATE(VLOOKUP($E32,CODIFICACIÓN_DPA!$G$2:$H$3,2,FALSE),VLOOKUP($F32,CODIFICACIÓN_DPA!$J$2:$K$10,2,FALSE)),A32) -> 170176AV0207031 | D32: PÍNTAG | E32: RURAL | F32: Valle de los Chillos | G32: AVENTURA | H32: Laguna de secas | I32: La Laguna de Secas ofrece una experiencia natural única, ideal para disfrutar en familia y sumergirse en la belleza del entorno. Este espacio natural permite realizar una variedad de actividades recreativas, como camping, pesca deportiva y excursiones, que brindan la oportunidad de conectar con la naturaleza y crear recuerdos inolvidables. Ya sea relajándose junto a la laguna o explorando los senderos circundantes, los visitantes pueden disfrutar de momentos de tranquilidad y aventura en este hermoso entorno natural. | J32: Se toma la vía pavimentada que sube desde Pintag a la Reserva Ecológica Antisana, unos 12 kilómetros y se podrá observar a la izquierda La Laguna de Secas. | K32: -0.44569525 | L32: -78.327904 | M32: Pintag - Mirador Lagunas de Secas 30 min Vía al Antisana - Lagunas de Secas 1 hora y 20 minutos | N32: Lunes a Domingo Hora de Ingreso 07h00 a 15h00 Hora de Salida 18h00 | O32: Gratuito | P32: Depende del grupo | Q32: No cazar No mascotas
A33: 032 | B33: INACTIVO | C33: =CONCATENATE(VLOOKUP($D33,CODIFICACIÓN_DPA!$A$2:$B$66,2,FALSE),VLOOKUP($G33,CODIFICACIÓN_DPA!$D$2:$E$6,2,FALSE),CONCATENATE(VLOOKUP($E33,CODIFICACIÓN_DPA!$G$2:$H$3,2,FALSE),VLOOKUP($F33,CODIFICACIÓN_DPA!$J$2:$K$10,2,FALSE)),A33) -> 170175AV0208032 | D33: PIFO | E33: RURAL | F33: Valle de Tumbaco | G33: AVENTURA | H33: Laguna de Loreto | I33: La Laguna de Loreto, ubicada dentro del Parque Nacional Cayambe-Coca, ofrece una experiencia incomparable para los amantes de la naturaleza y los aventureros. Este impresionante paisaje es un lugar ideal para acampar y realizar excursiones, permitiendo a los visitantes sumergirse en la belleza natural de la región. Con su entorno pintoresco y su atmósfera serena, la Laguna de Loreto invita a los viajeros a desconectarse del bullicio de la vida cotidiana y conectarse con la tranquilidad y la majestuosidad de la naturaleza. | J33: Se empieza desde la población de Papallacta, se toma el desvío hacia las termas de Papallacta y luego al Parque Nacional Cayambe Coca. Ahí se deja el vehículo y se debe ir caminando o en bicicleta hasta la laguna. | K33: -0.30986655 | L33: -78.146516 | M33: Termas de Papallacta - Contol de la Reserva 17 minutos Control de la Reserva - Laguna de Loreto 15 minutos | N33: Martes a Domingo Horario de Ingreso 08h00 a 14h00 Hora de Salida 17h00 | O33: Gratuito | P33: Por día 400 personas | Q33: No botar basura No mascotas
A34: 033 | B34: ACTIVO | C34: =CONCATENATE(VLOOKUP($D34,CODIFICACIÓN_DPA!$A$2:$B$66,2,FALSE),VLOOKUP($G34,CODIFICACIÓN_DPA!$D$2:$E$6,2,FALSE),CONCATENATE(VLOOKUP($E34,CODIFICACIÓN_DPA!$G$2:$H$3,2,FALSE),VLOOKUP($F34,CODIFICACIÓN_DPA!$J$2:$K$10,2,FALSE)),A34) -> 170176AV0207033 | D34: PÍNTAG | E34: RURAL | F34: Valle de los Chillos | G34: AVENTURA | H34: Laguna de Tipo Pugro | I34: La Laguna de Tipo Pugro es un destino turístico de fácil acceso que cautiva con su belleza natural y su historia geológica. Formada principalmente por erupciones secundarias del volcán Antisana y alimentada por el represamiento del río Chacauco, esta laguna ofrece un paisaje impresionante y una atmósfera tranquila. Los visitantes pueden disfrutar de actividades como la pesca deportiva, emocionantes excursiones y la oportunidad de acampar en sus alrededores, brindando una experiencia inolvidable en contacto directo con la naturaleza. | J34: Laguna Tipopugro, Via Antisana, Quito | K34: -0.44751175 | L34: -78.33664 | M34: 1 hora 30 minutos | N34: Miércoles a Domingo Hora de Ingreso 07h00 a 15h00 Hora de Salida 18h00 | O34: Costo de Entrada por Persona: $3 | P34: Depende del grupo | Q34: No botar basura No mascotas
A35: 034 | B35: ACTIVO | C35: =CONCATENATE(VLOOKUP($D35,CODIFICACIÓN_DPA!$A$2:$B$66,2,FALSE),VLOOKUP($G35,CODIFICACIÓN_DPA!$D$2:$E$6,2,FALSE),CONCATENATE(VLOOKUP($E35,CODIFICACIÓN_DPA!$G$2:$H$3,2,FALSE),VLOOKUP($F35,CODIFICACIÓN_DPA!$J$2:$K$10,2,FALSE)),A35) -> 170154AV0204034 | D35: CALACALÍ | E35: RURAL | F35: Parroquias Equinocciales | G35: AVENTURA | H35: Reserva Geobotánica El Pululahua | I35: La Reserva Geobotánica El Pululahua es una joya natural única, siendo la única área protegida con esta designación en Ecuador. Este lugar ofrece una experiencia excepcional para los amantes de la naturaleza, donde pueden sumergirse en la biodiversidad y la belleza escénica de la región. Además de ser un refugio para una gran variedad de flora y fauna, la reserva proporciona un entorno ideal para actividades al aire libre, como el camping y las emocionantes excursiones, permitiendo a los visitantes conectarse íntimamente con este paisaje volcánico impresionante. | J35: Ingreso por Ventanillas. Por la carretera Quito – Calacalí. A 6 kilómetros del Monumento a la Mitad del Mundo, en el sector de Caspigasí (hay una gasolinera en el sector), se desvía hacia la derecha y se sigue 1,2 kilómetros hasta el mirador. Ingreso por Moraspungo. Por la vía Quito – Calacalí se continúa 8 kilómetros después del sector de Caspigasí, hasta llegar a una segunda gasolinera. A 500 metros se encuentra una vía de tierra a mano derecha. Tras 3 kilómetros se llega al control de Moraspungo. Desde este sector toma 30 minutos llegar a la caldera por una vía con muchas curvas y de fuerte pendiente que cubre una extensión de 12 kilómetros. | K35: -0.025227897 | L35: -78.482745 | M35: Trekking y senderismo: 2 a 5 horas Caminata de 1 día: 6 horas Recorrido Completo: 5 horas | N35: Todos los días de 08h00 a 17h00 | O35: Gratuito | P35: Depende del grupo | Q35: No cazar No mascotas | R35: (02) 239-6543
A36: 035 | B36: ACTIVO | C36: =CONCATENATE(VLOOKUP($D36,CODIFICACIÓN_DPA!$A$2:$B$66,2,FALSE),VLOOKUP($G36,CODIFICACIÓN_DPA!$D$2:$E$6,2,FALSE),CONCATENATE(VLOOKUP($E36,CODIFICACIÓN_DPA!$G$2:$H$3,2,FALSE),VLOOKUP($F36,CODIFICACIÓN_DPA!$J$2:$K$10,2,FALSE)),A36) -> 170172AV0205035 | D36: PACTO | E36: RURAL | F36: Chocó Andino | G36: AVENTURA | H36: San José de Mashpi | I36: San José de Mashpi ofrece una experiencia auténtica en un entorno natural espectacular. Esta pequeña comunidad es un destino ideal para los amantes de la aventura y la naturaleza. Rodeada de exuberante vegetación y ubicada junto al río que lleva el mismo nombre, San José de Mashpi brinda la oportunidad de realizar emocionantes excursiones, explorar la zona en bicicleta y disfrutar del campismo en un ambiente sereno y tranquilo. Con su belleza natural y su ambiente acogedor, esta comunidad es el lugar perfecto para desconectar y disfrutar de la vida al aire libre. | J36: Desde Quito tomar un autobús desde el Terminal Terrestre de Carcelén hacia Pedro Vicente Maldonado, allí tomar la línea rural Mashpi – Pachijal. | K36: 0.1756544 | L36: -78.907339 | M36: 2 horas 30 minutos hasta 3 horas | N36: Todos los días | O36: Depende del grupo | P36: Depende del grupo | Q36: No basura No mascotas
A37: 036 | B37: INACTIVO | C37: =CONCATENATE(VLOOKUP($D37,CODIFICACIÓN_DPA!$A$2:$B$66,2,FALSE),VLOOKUP($G37,CODIFICACIÓN_DPA!$D$2:$E$6,2,FALSE),CONCATENATE(VLOOKUP($E37,CODIFICACIÓN_DPA!$G$2:$H$3,2,FALSE),VLOOKUP($F37,CODIFICACIÓN_DPA!$J$2:$K$10,2,FALSE)),A37) -> 170175AV0208036 | D37: PIFO | E37: RURAL | F37: Valle de Tumbaco | G37: AVENTURA | H37: Laguna de Parcacocha | I37: La Laguna de Parcacocha, situada dentro del impresionante Parque Nacional Cayambe Coca, ofrece una experiencia única para los amantes de la naturaleza y la aventura. Este pintoresco lugar es perfecto para actividades al aire libre como el campismo, la pesca deportiva y emocionantes excursiones. Rodeada de majestuosas montañas y una exuberante vegetación, la Laguna de Parcacocha brinda un escenario tranquilo y sereno para disfrutar de la belleza natural de la región. Con su ambiente relajante y sus actividades emocionantes, esta laguna es un destino imperdible para aquellos que buscan conectarse con la naturaleza y explorar nuevas experiencias al aire libre. | J37: vía a Lago Agrio, el ingreso es por la Virgen de Papallacta | K37: -0.2957811 | L37: -78.179061 | M37: 1 hora de caminata | N37: Todos los dias 06h00 a 18h00 | O37: Gratuito | P37: Depende del grupo | Q37: No cazar No mascotas | R37: (02) 211-0370. (06) 232-9743
A38: 037 | B38: INACTIVO | C38: =CONCATENATE(VLOOKUP($D38,CODIFICACIÓN_DPA!$A$2:$B$66,2,FALSE),VLOOKUP($G38,CODIFICACIÓN_DPA!$D$2:$E$6,2,FALSE),CONCATENATE(VLOOKUP($E38,CODIFICACIÓN_DPA!$G$2:$H$3,2,FALSE),VLOOKUP($F38,CODIFICACIÓN_DPA!$J$2:$K$10,2,FALSE)),A38) -> 170176AV0207037 | D38: PÍNTAG | E38: RURAL | F38: Valle de los Chillos | G38: AVENTURA | H38: Laguna de Micacocha | I38: La Laguna de Micacocha, ubicada en la Reserva Ecológica Antisana, ofrece una experiencia inolvidable en medio de un entorno natural impresionante. Esta laguna es el escenario perfecto para una variedad de actividades al aire libre, como emocionantes excursiones, campismo bajo las estrellas y pesca deportiva en aguas cristalinas. Además, los visitantes tienen la oportunidad de deleitarse con el avistamiento de la rica fauna y flora nativa que habita en los alrededores de la laguna, lo que añade un toque de aventura y belleza a esta experiencia única en la naturaleza. | J38: Quito–Píntag–Laguna Micacocha o la carretera Quito–Av. rumiñahui-Colibrí- vía Píntag. Otra vía alterna es la carretera Quito–Tumbaco–Pifo–vía Píntag. | K38: -0.50190041 | L38: -78.217109 | M38: 50 minutos | N38: Todos los dias 08h00 a 17h00 | O38: Gratuito | P38: Depende del grupo | Q38: No botar basura No mascotas
A39: 038 | B39: INACTIVO | C39: =CONCATENATE(VLOOKUP($D39,CODIFICACIÓN_DPA!$A$2:$B$66,2,FALSE),VLOOKUP($G39,CODIFICACIÓN_DPA!$D$2:$E$6,2,FALSE),CONCATENATE(VLOOKUP($E39,CODIFICACIÓN_DPA!$G$2:$H$3,2,FALSE),VLOOKUP($F39,CODIFICACIÓN_DPA!$J$2:$K$10,2,FALSE)),A39) -> 170175AV0208038 | D39: PIFO | E39: RURAL | F39: Valle de Tumbaco | G39: AVENTURA | H39: Laguna de Loreto, Parcacocha y anteojos | I39: La Laguna de Loreto, la Laguna de Parcacocha y los Anteojos son destinos fascinantes dentro del Parque Nacional Cayambe-Coca, donde los visitantes pueden disfrutar de una variedad de actividades al aire libre. Desde el camping hasta las emocionantes excursiones, estas áreas ofrecen la oportunidad de sumergirse en la belleza natural de la región. Rodeadas de majestuosas montañas y una exuberante vegetación, estas lagunas son lugares ideales para relajarse y disfrutar de la tranquilidad de la naturaleza. | J39: Se empieza desde la población de Papallacta, se toma el desvío hacia las termas de Papallacta y luego al Parque Nacional Cayambe Coca. Ahí se deja el vehículo y se debe ir caminando o en bicicleta hasta la laguna. | K39: -0.30986655 | L39: -78.146516 | P39: Depende del grupo | Q39: No botar basura No mascotas
A40: 039 | B40: ACTIVO | C40: =CONCATENATE(VLOOKUP($D40,CODIFICACIÓN_DPA!$A$2:$B$66,2,FALSE),VLOOKUP($G40,CODIFICACIÓN_DPA!$D$2:$E$6,2,FALSE),CONCATENATE(VLOOKUP($E40,CODIFICACIÓN_DPA!$G$2:$H$3,2,FALSE),VLOOKUP($F40,CODIFICACIÓN_DPA!$J$2:$K$10,2,FALSE)),A40) -> 170172AV0205039 | D40: PACTO | E40: RURAL | F40: Chocó Andino | G40: AVENTURA | H40: Mirador La Amagusa | I40: El Mirador La Amagusa es un destino excepcional para los amantes de las aves y la naturaleza. Esta reserva ofrece una experiencia enriquecedora de avistamiento de aves, con la posibilidad de presenciar una variedad de especies en su hábitat natural. Además, cuenta con paquetes de excursión diseñados específicamente para la observación y fotografía de aves, brindando a los visitantes la oportunidad de capturar momentos únicos en imágenes. Para aquellos que desean sumergirse completamente en esta experiencia, la reserva también ofrece la opción de alojamiento en el espacio, lo que permite una inmersión completa en el entorno natural y la tranquilidad que lo rodea. Con su ambiente sereno y su abundante vida silvestre, el Mirador La Amagusa es el destino perfecto para aquellos que buscan conectarse con la naturaleza y disfrutar de la belleza de las aves en su hábitat natural. | J40: Por la vía a Pactoloma, pasando el recinto La Delicia, hasta el mirador de Mashpi, apenas 13 kilómetros conducen a la reserva Amagusa. | K40: 0.16183756 | L40: -78.845174 | N40: Bajo reserva | P40: Depende del grupo | Q40: No botar basura No mascotas | R40: info@mashpi-amagusa.com +593-98-321-7713.
A41: 040 | B41: ACTIVO | C41: =CONCATENATE(VLOOKUP($D41,CODIFICACIÓN_DPA!$A$2:$B$66,2,FALSE),VLOOKUP($G41,CODIFICACIÓN_DPA!$D$2:$E$6,2,FALSE),CONCATENATE(VLOOKUP($E41,CODIFICACIÓN_DPA!$G$2:$H$3,2,FALSE),VLOOKUP($F41,CODIFICACIÓN_DPA!$J$2:$K$10,2,FALSE)),A41) -> 170103GA0101040 | D41: CENTRO HISTÓRICO | E41: URBANO | F41: Centro Histórico | G41: GASTRONÓMICO | H41: Heladería San Agustin | I41: Demostración gratuita del oficio artesanal de elaborar Helado de Paila bajo reserva Servicio a domicilio con plataforma de motorizados Fénix costo km de distancia $0.50 Helado con humo si eres cumpleañero (válido por 10 días antes o después del cumpleaños History Time con la Abuelita Encarnación, de viernes a domingo de 13:00 a 14:30. Desde el purgatorio viene la segunda propietaria de Heladería San Agustín para contarte las leyendas de Quito | J41: Guayaquil N5-59 y, Quito | K41: -0.21992835 | L41: -78.510567 | M41: De Lunes a Domingo de 9:30am hasta 16:00pm | N41: De Lunes a Domingo de 9:30am hasta 16:00pm. Reserva de Mesa con 72 horas de anticipación si deseas para el mismo día solicitar información vía WhatsApp | O41: Demostracion del oficio artesanal de elaborar helado de paila: De lunes a jueves no tiene costo alguno la demostracion en el horario de 10:30am a 11:45am y debe reservas con 1 dia de antelacion. Fines de semana tiene un costo de $10 por grupo | P41: Depende del grupo | R41: Reserva de Mesa con 72 horas de anticipación si deseas para el mismo día solicitar información vía WhatsApp
A42: 041 | B42: ACTIVO | C42: =CONCATENATE(VLOOKUP($D42,CODIFICACIÓN_DPA!$A$2:$B$66,2,FALSE),VLOOKUP($G42,CODIFICACIÓN_DPA!$D$2:$E$6,2,FALSE),CONCATENATE(VLOOKUP($E42,CODIFICACIÓN_DPA!$G$2:$H$3,2,FALSE),VLOOKUP($F42,CODIFICACIÓN_DPA!$J$2:$K$10,2,FALSE)),A42) -> 170171AV0205041 | D42: NONO | E42: RURAL | F42: Chocó Andino | G42: AVENTURA | H42: Reserva Orquideológica Pahuma | I42: Sumergirse en la Reserva Orquideológica Pahuma es adentrarse en un mundo de misterio y belleza en el corazón del bosque nublado. Aquí, los visitantes pueden explorar una variedad de actividades que van desde emocionantes excursiones hasta cautivadoras sesiones de fotografía. La reserva no solo ofrece una experiencia de conexión con la naturaleza, sino también oportunidades de educación ambiental, avistamiento de aves y la posibilidad de sumergirse en la investigación de especies nativas. Además, la aventura se intensifica con la visita a cascadas majestuosas y la emocionante práctica de rapel, haciendo de cada momento en Pahuma una experiencia inolvidable y enriquecedora. | J42: Vía Calacalí - La Independencia. | K42: 0.025960704 | L42: -78.63241 | M42: De 10 minutos a 4 horas. | N42: Todos los días de 8h00 a 17h00 | O42: USD 2.50 | P42: Depende del grupo | Q42: No botar basura No mascotas | R42: 969612807 pahuma@gmail.com
A43: 042 | B43: ACTIVO | C43: =CONCATENATE(VLOOKUP($D43,CODIFICACIÓN_DPA!$A$2:$B$66,2,FALSE),VLOOKUP($G43,CODIFICACIÓN_DPA!$D$2:$E$6,2,FALSE),CONCATENATE(VLOOKUP($E43,CODIFICACIÓN_DPA!$G$2:$H$3,2,FALSE),VLOOKUP($F43,CODIFICACIÓN_DPA!$J$2:$K$10,2,FALSE)),A43) -> 170169AV0205042 | D43: NANEGALITO | E43: RURAL | F43: Chocó Andino | G43: AVENTURA | H43: Bellavista Cloud Forest | I43: Explorar la Bellavista Cloud Forest es sumergirse en un mundo de maravillas naturales donde cada paquete ofrece una experiencia única y envolvente. Desde el vibrante Paraíso de los Colibríes hasta la inmersión completa en el misterioso Bosque Nublado, los visitantes son recibidos con transporte desde Quito, deliciosas comidas y la guía experta para cada excursión. Con opciones de hospedaje para todas las duraciones, desde una noche hasta tres días, los exploradores tienen la oportunidad de sumergirse en el avistamiento de aves y descubrir la fascinante vida silvestre, incluyendo el emblemático gallito de la peña. Cada paquete promete una experiencia inolvidable en este paraíso natural. | J43: Nanegalito, km 62 vía antigua Nono – Tandayapa – Los Bancos. | K43: -0.012297445 | L43: -78.681564 | M43: 1. Full day 2. 2 días y 1 noche.. 3. 3 días y 2 noches | N43: Todos los días de 09h00 a 20h00 (Check-In) y (Check-Out) 11h00 | O43: "Ofece paquetes de: 1.El Paraíso de los Colibríes: Transporte desde Quito, desayuno, almuerzo, guida para recorrido. 2. Descubra El Bosque Nublado: Transporte desde Quito, hospedaje, todas las comidas, guia pra las excursiones, avistamiento de aves. 3. Paquete 2 días y una noche: Transporte desde Quito, hospedaje, todas las comidas, guia pra las excursiones, avistamiento de aves + el gallito de la peña. 4. Descubrimiento de Bellavista: Transporte desde Quito, hospedaje, todas las comidas, guia pra las excursiones, avistamiento de aves 5. Paquete 3 días y 2 noches: Transporte desde Quito, hospedaje, todas las comidas, guia pra las excursiones, avistamiento de aves + gallito de la peña." 1. 1 personas USD 129, + de 5 personas USD 95 2. más de 2 personas USD 211 + niños de 5 -11 USD 117 3. más de 2 personas USD270 + niños de 5 - 11 USD 164 | P43: Depende del grupo | Q43: No mascotas | R43: 0 994165868 / 0999490891 info@bellavistacloudforest.com
A44: 043 | B44: ACTIVO | C44: =CONCATENATE(VLOOKUP($D44,CODIFICACIÓN_DPA!$A$2:$B$66,2,FALSE),VLOOKUP($G44,CODIFICACIÓN_DPA!$D$2:$E$6,2,FALSE),CONCATENATE(VLOOKUP($E44,CODIFICACIÓN_DPA!$G$2:$H$3,2,FALSE),VLOOKUP($F44,CODIFICACIÓN_DPA!$J$2:$K$10,2,FALSE)),A44) -> 170171AV0205043 | D44: NONO | E44: RURAL | F44: Chocó Andino | G44: AVENTURA | H44: Reserva Yanacocha | I44: Explorar la naturaleza con Jocotours es una experiencia enriquecedora y emocionante que te sumerge en la belleza y diversidad de los Andes. Con guías especializados, los visitantes pueden recorrer los senderos, avistar aves exóticas, como los impresionantes colibríes, y tener la posibilidad única de avistar osos andinos en su hábitat natural. Además de esta emocionante aventura, Jocotours ofrece una variedad de comodidades, desde zonas de camping hasta áreas de picnic, perfectas para disfrutar de la serenidad del entorno. Con un centro de interpretación para aprender sobre la rica flora nativa y ocho senderos de diferentes niveles de dificultad, cada visita promete una conexión profunda con la naturaleza y momentos inolvidables en este paraíso andino. | J44: Vía Nono, 2 kilómetros pasando la EPMAPS | K44: -0.11153019 | L44: -78.584894 | M44: Depende el recorrido | N44: Lunes a viernes 7h00 a 15h00 Último ingreso a las 11h30 | O44: USD 15 extranjeros USD 5 nacionales | P44: Depende del grupo | Q44: No se permite el ingreso con mascotas No se permite el ingreso con bicicletas (contamos con parqueadero para bicis) No tocar ni alimentar a los animales silvestres. No botar basura | R44: 0997101535 | 0992440038
A45: 044 | B45: ACTIVO | C45: =CONCATENATE(VLOOKUP($D45,CODIFICACIÓN_DPA!$A$2:$B$66,2,FALSE),VLOOKUP($G45,CODIFICACIÓN_DPA!$D$2:$E$6,2,FALSE),CONCATENATE(VLOOKUP($E45,CODIFICACIÓN_DPA!$G$2:$H$3,2,FALSE),VLOOKUP($F45,CODIFICACIÓN_DPA!$J$2:$K$10,2,FALSE)),A45) -> 170176AV0207044 | D45: PÍNTAG | E45: RURAL | F45: Valle de los Chillos | G45: AVENTURA | H45: Chakana | I45: La experiencia en Chakana es una inmersión fascinante en la belleza natural de los Andes, donde cada momento ofrece la oportunidad de conectar con la majestuosidad de la vida silvestre. Desde el impresionante Mirador del Isco, los visitantes pueden deleitarse con el espectáculo del avistamiento de cóndores, las majestuosas aves que surcan los cielos andinos. Además, el mini centro de interpretación proporciona una ventana al rico ecosistema de la región, mientras que los humedales de páramo ofrecen un santuario para la observación de aves migratorias durante los meses de octubre a marzo. Cada experiencia en Chakana promete una conexión íntima con la naturaleza y momentos de asombro y admiración frente a la grandiosidad de los Andes. | J45: Vía Píntag, 40 minutos camino a la Reserva Chakana | K45: -0.44471981 | L45: -78.312483 | M45: Depende el recorrido | N45: Bajo reserva | O45: USD 15 extranjeros USD 5 nacionales | P45: Depende del grupo | Q45: No se permite el ingreso con mascotas No se permite el ingreso con bicicletas (contamos con parqueadero para bicis) No tocar ni alimentar a los animales silvestres. | R45: 992440038
A46: 045 | B46: ACTIVO | C46: =CONCATENATE(VLOOKUP($D46,CODIFICACIÓN_DPA!$A$2:$B$66,2,FALSE),VLOOKUP($G46,CODIFICACIÓN_DPA!$D$2:$E$6,2,FALSE),CONCATENATE(VLOOKUP($E46,CODIFICACIÓN_DPA!$G$2:$H$3,2,FALSE),VLOOKUP($F46,CODIFICACIÓN_DPA!$J$2:$K$10,2,FALSE)),A46) -> 170168AV0205045 | D46: NANEGAL | E46: RURAL | F46: Chocó Andino | G46: AVENTURA | H46: Reserva Maquipucuna | I46: Explorar la Reserva Maquipucuna es adentrarse en un paraíso natural lleno de fascinantes descubrimientos y experiencias enriquecedoras. Con un extenso sendero de 40 kilómetros, los senderistas tienen la oportunidad de sumergirse en la exuberante selva tropical y descubrir la rica variedad de fauna que habita en la reserva. Los amantes de las aves quedan maravillados por las más de 400 especies que llaman hogar a este santuario, mientras que los entusiastas de la vida silvestre pueden emocionarse con el avistamiento de osos, una experiencia única dada la congregación de estos majestuosos animales. Además, tras una jornada de exploración, los visitantes pueden refrescarse en las cristalinas aguas de la cascada, ubicada a tan solo 10 minutos a pie, completando así una experiencia inolvidable en la Reserva Maquipucuna. | J46: vía Santa Marianita | K46: 0.12449786 | L46: -78.629046 | M46: Depende el recorrido | N46: Lunes a viernes 8h00 a 17h00 | O46: Visita por Día Adultos: $25 Niños (4 a 11 años): $16 | P46: Depende del grupo | R46: 099 421 8033
A47: 046 | B47: INACTIVO | C47: =CONCATENATE(VLOOKUP($D47,CODIFICACIÓN_DPA!$A$2:$B$66,2,FALSE),VLOOKUP($G47,CODIFICACIÓN_DPA!$D$2:$E$6,2,FALSE),CONCATENATE(VLOOKUP($E47,CODIFICACIÓN_DPA!$G$2:$H$3,2,FALSE),VLOOKUP($F47,CODIFICACIÓN_DPA!$J$2:$K$10,2,FALSE)),A47) -> 170175AV0208046 | D47: PIFO | E47: RURAL | F47: Valle de Tumbaco | G47: AVENTURA | H47: Papallacta - Oyacachi Parte Alta | I47: Explorar Papallacta - Oyacachi Parte Alta es sumergirse en un oasis de aventura dentro del majestuoso Parque Nacional Cayambe - Coca. Con senderos para excursiones que serpentean a través de paisajes impresionantes, paseos en bicicleta que ofrecen una perspectiva única de la naturaleza circundante y emocionantes sesiones de escalada de montaña para los más intrépidos, cada rincón de este espacio promete una experiencia inolvidable. Los amantes de la naturaleza pueden acampar bajo el cielo estrellado o embarcarse en emocionantes cabalgatas a través del paisaje montañoso. Además, la posibilidad de avistar osos en su hábitat natural agrega un toque de emoción y asombro a esta aventura en Papallacta - Oyacachi Parte Alta. | J47: Vía Cangahua. | K47: -0.071830858 | L47: -77.836599 | M47: Depende el recorrido | N47: Todos los días | O47: Gratuito | P47: Depende del grupo | Q47: No mascotas No botar basura | R47: Zona alta. (02) 211-0370. Zona baja. (06) 232-9743 / (06) 232-0184.
A48: 047 | B48: ACTIVO | C48: =CONCATENATE(VLOOKUP($D48,CODIFICACIÓN_DPA!$A$2:$B$66,2,FALSE),VLOOKUP($G48,CODIFICACIÓN_DPA!$D$2:$E$6,2,FALSE),CONCATENATE(VLOOKUP($E48,CODIFICACIÓN_DPA!$G$2:$H$3,2,FALSE),VLOOKUP($F48,CODIFICACIÓN_DPA!$J$2:$K$10,2,FALSE)),A48) -> 170171AV0205047 | D48: NONO | E48: RURAL | F48: Chocó Andino | G48: AVENTURA | H48: Aldea Turística Puma Sacha - Cayoning | I48: Explorar la Aldea Turística Puma Sacha - Cayoning es sumergirse en una experiencia emocionante y llena de aventuras en medio de la exuberante naturaleza. Con senderos de trekking que atraviesan paisajes impresionantes, los visitantes tienen la oportunidad de deleitarse con la rica flora y fauna de la zona. La verdadera emoción llega con el cayoning en las impresionantes cascadas, una actividad realizada junto a profesionales que garantizan seguridad y diversión. Para los amantes de la vida al aire libre, la opción de camping ofrece la oportunidad de dormir bajo el cielo estrellado, mientras que el avistamiento de aves añade un toque de serenidad y belleza a la experiencia. En la Aldea Turística Puma Sacha - Cayoning, cada momento promete una aventura inolvidable en armonía con la naturaleza. | J48: Km 43 vía Calacalí la Independencia | K48: -0.033862878 | L48: -78.662415 | M48: Depende el recorrido | N48: Martes a domingo 8h00 a 18h00 | O48: Depende de la actividad | P48: depende del grupo | Q48: No mascotas No botar basura | R48: 987589117
A49: 048 | B49: ACTIVO | C49: =CONCATENATE(VLOOKUP($D49,CODIFICACIÓN_DPA!$A$2:$B$66,2,FALSE),VLOOKUP($G49,CODIFICACIÓN_DPA!$D$2:$E$6,2,FALSE),CONCATENATE(VLOOKUP($E49,CODIFICACIÓN_DPA!$G$2:$H$3,2,FALSE),VLOOKUP($F49,CODIFICACIÓN_DPA!$J$2:$K$10,2,FALSE)),A49) -> 170169AV0205048 | D49: NANEGALITO | E49: RURAL | F49: Chocó Andino | G49: AVENTURA | H49: Reserva Intillacta Tucanopy - canopy - puentes de altura | I49: Explorar la Reserva Intillacta es sumergirse en un mundo de emocionantes aventuras en medio de la exuberante naturaleza. Con actividades diseñadas para todos los amantes del aire libre, la reserva ofrece una experiencia única de Tucanopy, donde se desliza por la selva en un emocionante recorrido de canopy, siempre bajo la supervisión de personal capacitado. Los entusiastas del trekking pueden adentrarse en los senderos de la reserva para descubrir la fascinante flora y fauna que la habita, mientras que aquellos en busca de adrenalina pueden disfrutar del Canoping junto a profesionales que garantizan seguridad y diversión en cada momento. En la Reserva Intillacta, cada experiencia promete una conexión profunda con la naturaleza y momentos de emoción inolvidables. | J49: km 63,5 via Calacali, Quito | K49: 0.049539631 | L49: -78.717793 | M49: Depende el recorrido | O49: Depende de la actividad | P49: Aforo 25 personas | Q49: No mascotas No botar basura | R49: 995311625 https://tucanopy.com
A50: 049 | B50: ACTIVO | C50: =CONCATENATE(VLOOKUP($D50,CODIFICACIÓN_DPA!$A$2:$B$66,2,FALSE),VLOOKUP($G50,CODIFICACIÓN_DPA!$D$2:$E$6,2,FALSE),CONCATENATE(VLOOKUP($E50,CODIFICACIÓN_DPA!$G$2:$H$3,2,FALSE),VLOOKUP($F50,CODIFICACIÓN_DPA!$J$2:$K$10,2,FALSE)),A50) -> 170170AV0208049 | D50: NAYÓN | E50: RURAL | F50: Valle de Tumbaco | G50: AVENTURA | H50: Nayón Xtrem Valley Parque de aventura | I50: Explorar Nayón Xtrem Valley es sumergirse en un paraíso de aventuras y emoción en medio de un entorno natural impresionante. Desde emocionantes partidas de paintball hasta la adrenalina de la caída en péndulo, donde los pasajeros se elevan a grandes alturas en un columpio extremo, cada momento promete una experiencia llena de acción. El puente colgante más grande de Latinoamérica ofrece una oportunidad única para los aventureros audaces de cruzar sus 250 metros de longitud y luego regresar en un emocionante recorrido de canopy a velocidades de hasta 50 km por hora. Además de estas emocionantes actividades, el parque ofrece áreas recreativas, como piscinas y restaurantes, donde los visitantes pueden relajarse y recargar energías después de una jornada llena de emociones fuertes. En Nayón Xtrem Valley, la diversión nunca termina. | J50: Paltapamba S2-72, Quito 170170 | K50: -0.16772918 | L50: -78.41954 | M50: Depende el recorrido y el servicio que necesite | N50: Lunes a domingo 9h00 a 17h00. | O50: Depende de la actividad | P50: Depende del grupo | Q50: No basura No recolectar flora y fauna Personas con vértigo es preferible que se avisen. El servicio de hospedaje necesita reserva | R50: 099 995 8305 / 098 455 5970
A51: 050 | B51: ACTIVO | C51: =CONCATENATE(VLOOKUP($D51,CODIFICACIÓN_DPA!$A$2:$B$66,2,FALSE),VLOOKUP($G51,CODIFICACIÓN_DPA!$D$2:$E$6,2,FALSE),CONCATENATE(VLOOKUP($E51,CODIFICACIÓN_DPA!$G$2:$H$3,2,FALSE),VLOOKUP($F51,CODIFICACIÓN_DPA!$J$2:$K$10,2,FALSE)),A51) -> 170168AV0205050 | D51: NANEGAL | E51: RURAL | F51: Chocó Andino | G51: AVENTURA | H51: Cascada La Piragua | I51: Explorar la Cascada La Piragua es sumergirse en un paraíso natural de belleza sin igual. Aquí, los visitantes pueden maravillarse con la imponente cascada y sumergirse en la exuberante flora y fauna que habita en sus alrededores. Además de ser testigos de la majestuosidad de la naturaleza, los aventureros tienen la oportunidad de disfrutar de áreas de recreación para relajarse y recargar energías, así como de emocionantes caminatas por los senderos cercanos. En la Cascada La Piragua, cada momento ofrece una experiencia enriquecedora y memorables encuentros con la naturaleza. | J51: Nanegal | K51: 0.14020933 | L51: -78.683894 | O51: USD 2 por persona | P51: Depende del grupo | Q51: No basura No acampar
A52: 051 | B52: ACTIVO | C52: =CONCATENATE(VLOOKUP($D52,CODIFICACIÓN_DPA!$A$2:$B$66,2,FALSE),VLOOKUP($G52,CODIFICACIÓN_DPA!$D$2:$E$6,2,FALSE),CONCATENATE(VLOOKUP($E52,CODIFICACIÓN_DPA!$G$2:$H$3,2,FALSE),VLOOKUP($F52,CODIFICACIÓN_DPA!$J$2:$K$10,2,FALSE)),A52) -> 170171AV0205051 | D52: NONO | E52: RURAL | F52: Chocó Andino | G52: AVENTURA | H52: Cascada de Guagrapamba | I52: Explorar la Cascada de Guagrapamba es adentrarse en un mundo de belleza natural y aventura. Este proyecto turístico ofrece la oportunidad de realizar emocionantes caminatas por el bosque primario, permitiendo a los visitantes sumergirse en la exuberante flora y fauna de la región. Además, cuenta con áreas sociales donde los visitantes pueden relajarse y disfrutar de momentos de descanso. Para completar la experiencia, el servicio de restaurante está disponible, ofreciendo deliciosas opciones gastronómicas para satisfacer los antojos después de una jornada de exploración. En la Cascada de Guagrapamba, cada visita promete una conexión profunda con la naturaleza y momentos inolvidables en un entorno de ensueño. | J52: Nono | K52: -0.069915106 | L52: -78.588532 | N52: Sábados y domingos 9h00 a 16h00 Entres semana Bajo reserva | O52: Adultos USD 3 Niños USD 2.50 Adultos Mayores USD 2.50 | P52: Depende del grupo | Q52: No basura No acampar | R52: 987821652
A53: 052 | B53: ACTIVO | C53: =CONCATENATE(VLOOKUP($D53,CODIFICACIÓN_DPA!$A$2:$B$66,2,FALSE),VLOOKUP($G53,CODIFICACIÓN_DPA!$D$2:$E$6,2,FALSE),CONCATENATE(VLOOKUP($E53,CODIFICACIÓN_DPA!$G$2:$H$3,2,FALSE),VLOOKUP($F53,CODIFICACIÓN_DPA!$J$2:$K$10,2,FALSE)),A53) -> 170171AV0205052 | D53: NONO | E53: RURAL | F53: Chocó Andino | G53: AVENTURA | H53: Ruta Nono - Alaspungo | I53: Explorar la Ruta Nono - Alaspungo es sumergirse en un viaje lleno de emocionantes aventuras y vistas impresionantes. Esta ruta ofrece la experiencia única de recorrerla en bicicleta, permitiendo a los visitantes disfrutar de vistas panorámicas mientras pedalean a lo largo del camino. Además de la emoción del ciclismo, los aventureros tienen la oportunidad de avistar aves terrestres, agregando un toque de naturaleza y serenidad al recorrido. Con un nivel técnico bajo requerido, esta ruta es ideal para ciclistas de todos los niveles de experiencia, prometiendo una experiencia gratificante y memorable en medio de la belleza natural de la región. | J53: La ruta empieza en la Plaza Central de Nono y termina el trayecto en ALaspungo, cancha de voley. La ruta tiene un trayecto de 13 Km | K53: -0.065396814 | L53: -78.576951 | M53: Entre 1 hora 10 minutos a 1 hora 45 minutos | N53: La experiencia ciclistica se puede hacer a cualquier hora del día debido a su corta duración, se recomienda hacerla en la mañana ya que en la mayoría de las tardes se nubla el sector | O53: Gratuito | Q53: Prohibida la caza No botar basura | R53: Libre Acceso
A54: 053 | B54: ACTIVO | C54: =CONCATENATE(VLOOKUP($D54,CODIFICACIÓN_DPA!$A$2:$B$66,2,FALSE),VLOOKUP($G54,CODIFICACIÓN_DPA!$D$2:$E$6,2,FALSE),CONCATENATE(VLOOKUP($E54,CODIFICACIÓN_DPA!$G$2:$H$3,2,FALSE),VLOOKUP($F54,CODIFICACIÓN_DPA!$J$2:$K$10,2,FALSE)),A54) -> 170172AV0205053 | D54: PACTO | E54: RURAL | F54: Chocó Andino | G54: AVENTURA | H54: Ruta Pacto - Mashpi | I54: Explorar esta ruta ofrece una emocionante experiencia de ciclismo en un entorno protegido. A lo largo del recorrido, los visitantes pueden deleitarse con impresionantes vistas panorámicas, sumergiéndose en la belleza natural de la región. Con un nivel técnico medio-alto requerido, los ciclistas pueden desafiarse a sí mismos mientras exploran este paisaje único. Ya sea disfrutando de la adrenalina de los descensos o simplemente absorbiendo la serenidad del entorno, esta ruta promete momentos inolvidables para los amantes del ciclismo y la naturaleza. | J54: La ruta empieza en la Iglesia de Pacto y termina el trayecto en La comunidad de Mashpi. La ruta tiene un trayecto de 39 Km | K54: 0.14180918 | L54: -78.767415 | M54: Entre 2 horas 20 minutos a más de 5 horas | N54: La experiencia ciclistica se puede hacer a cualquier hora, se recomienda hacerla en la mañana | O54: Gratuito | Q54: No mascotas No botar basura | R54: Libre Acceso
A55: 054 | B55: ACTIVO | C55: =CONCATENATE(VLOOKUP($D55,CODIFICACIÓN_DPA!$A$2:$B$66,2,FALSE),VLOOKUP($G55,CODIFICACIÓN_DPA!$D$2:$E$6,2,FALSE),CONCATENATE(VLOOKUP($E55,CODIFICACIÓN_DPA!$G$2:$H$3,2,FALSE),VLOOKUP($F55,CODIFICACIÓN_DPA!$J$2:$K$10,2,FALSE)),A55) -> 170172AV0205054 | D55: PACTO | E55: RURAL | F55: Chocó Andino | G55: AVENTURA | H55: Ruta Pacto - Santa Rosa | I55: Explorar la Ruta Pacto - Santa Rosa ofrece una emocionante experiencia de ciclismo en un entorno protegido. A lo largo del recorrido, los visitantes pueden maravillarse con impresionantes vistas panorámicas, sumergiéndose en la belleza natural de la región. Es importante destacar que esta área está protegida, lo que garantiza la conservación de su entorno único. Se recomienda un nivel técnico medio-alto para abordar los desafíos que ofrece este terreno, lo que brinda a los ciclistas la oportunidad de poner a prueba sus habilidades mientras disfrutan de una aventura inolvidable en medio de la naturaleza. | J55: La ruta empieza en la Iglesia de Pacto y culmina en el cruce del río Chalpi, no existe puente. La ruta tiene un trayecto de 37 km | K55: 0.14180918 | L55: -78.767415 | M55: Entre 2 horas 24 minutos a más de 4 horas | N55: La experiencia ciclistica se puede hacer a cualquier hora, se recomienda hacerla en la mañana | O55: Gratuito | Q55: No mascotas No botar basura | R55: Libre Acceso
A56: 055 | B56: ACTIVO | C56: =CONCATENATE(VLOOKUP($D56,CODIFICACIÓN_DPA!$A$2:$B$66,2,FALSE),VLOOKUP($G56,CODIFICACIÓN_DPA!$D$2:$E$6,2,FALSE),CONCATENATE(VLOOKUP($E56,CODIFICACIÓN_DPA!$G$2:$H$3,2,FALSE),VLOOKUP($F56,CODIFICACIÓN_DPA!$J$2:$K$10,2,FALSE)),A56) -> 170157AV0208055 | D56: CUMBAYÁ | E56: RURAL | F56: Valle de Tumbaco | G56: AVENTURA | H56: Ruta El Chaquiñan - Puembo | I56: Explorar la Ruta El Chaquiñan - Puembo ofrece una enriquecedora experiencia de ciclismo en un entorno natural excepcional. A lo largo del recorrido, los visitantes pueden deleitarse con vistas panorámicas impresionantes y sumergirse en la serenidad del paisaje circundante. Además de disfrutar del ciclismo, también tienen la oportunidad de explorar los senderos que serpentean a través de este entorno pintoresco. Con un nivel técnico bajo requerido, esta ruta es ideal tanto para ciclistas principiantes como experimentados, garantizando una experiencia gratificante para todos los amantes de la bicicleta y la naturaleza. | J56: La ruta Inicia en Cumbayá (Portal de Cumbayá) y culmina en Puembo (Portal La Lomita). La ruta tiene un trayecto de 22 km | K56: -0.1995593 | L56: -78.43156 | M56: Entre 1 a 2 horas | N56: Lunes a Domingo 06h00 a 18h00 | O56: Gratuito | Q56: No fogata No botar basura | R56: Libre Acceso
A57: 056 | B57: ACTIVO | C57: =CONCATENATE(VLOOKUP($D57,CODIFICACIÓN_DPA!$A$2:$B$66,2,FALSE),VLOOKUP($G57,CODIFICACIÓN_DPA!$D$2:$E$6,2,FALSE),CONCATENATE(VLOOKUP($E57,CODIFICACIÓN_DPA!$G$2:$H$3,2,FALSE),VLOOKUP($F57,CODIFICACIÓN_DPA!$J$2:$K$10,2,FALSE)),A57) -> 170101AV0102056 | D57: BELISARIO QUEVEDO | E57: URBANO | F57: La Mariscal | G57: AVENTURA | H57: Volcán Rucu Pichincha | I57: Explorar el Volcán Rucu Pichincha ofrece una experiencia emocionante y única para los amantes del senderismo y la naturaleza. Con un espectacular sendero que parte desde el teleférico, los visitantes se embarcan en un fascinante viaje hacia la cima del volcán, donde son recibidos por vistas panorámicas impresionantes y únicas. A lo largo del camino, podrán maravillarse con la belleza de la naturaleza circundante y disfrutar de la serenidad del paisaje montañoso. Aunque el grado de dificultad es considerado bajo a medio, esta aventura ofrece una oportunidad para desafiarse a sí mismos y disfrutar de una experiencia gratificante en uno de los paisajes más impresionantes de la región. | J57: Vía Al Teleférico, Quito | K57: -0.19226908 | L57: -78.519536 | M57: Entre 5 horas a 6 Horas | N57: Lunes a Jueves 10H00 a 18H00 Viernes 08h00 a 18h00 Sábados, Domingos y Feriados 08h00 a 19h00 | O57: El sendero no tiene costo Subir al Telérico TARIFAS PROMOCIONALES *Presentando la cédula ecuatoriana Menores de 18 años: $3.25 Adultos: $5.25 Tercera Edad: $2.50 Personas con discapacidad: $2.50 TARIFAS ÚNICAS Menores de 18 años: $7.00 Adultos: $9.00 Tercera Edad: $6.50 Personas con discapacidad: $6.50 Alquiler de Locker: $2.00 *Los niños ingresan a partir de 18 meses de edad* | P57: - | Q57: Se puede acampar, pero debes informar en las boleterias y en la estacion de llegada. No se puede prender fogatas. No se permite mascotas en algunos espacios | R57: Pamel Vargas (+593) 98 406 6226 Teléfono: (+593) 2222 996 E-Mail: info@teleferico.com.ec
A58: 057 | B58: ACTIVO | C58: =CONCATENATE(VLOOKUP($D58,CODIFICACIÓN_DPA!$A$2:$B$66,2,FALSE),VLOOKUP($G58,CODIFICACIÓN_DPA!$D$2:$E$6,2,FALSE),CONCATENATE(VLOOKUP($E58,CODIFICACIÓN_DPA!$G$2:$H$3,2,FALSE),VLOOKUP($F58,CODIFICACIÓN_DPA!$J$2:$K$10,2,FALSE)),A58) -> 170152AV0207057 | D58: AMAGUAÑA | E58: RURAL | F58: Valle de los Chillos | G58: AVENTURA | H58: Refugio de vida silvestre Pasochoa | I58: Explorar el Refugio de Vida Silvestre Pasochoa es adentrarse en un mundo de biodiversidad y belleza natural. El sendero ofrece al visitante la oportunidad de sumergirse en una variedad de microclimas y descubrir una gran diversidad de especies silvestres. Sin embargo, es importante tener en cuenta que el sendero presenta pendientes pronunciadas, por lo que se recomienda el uso de palos o bastones de trekking para facilitar el ascenso. Con un grado de dificultad medio, esta experiencia brinda la oportunidad de desafiarse a sí mismo mientras se disfruta de la serenidad y la majestuosidad de la naturaleza en su estado más puro. | J58: Vía Pasochoa, por 6 km, se pasa la Comunidad de San Pedro de Pilopata, hasta llegar al estacionamiento del área protegida | K58: -0.42006038 | L58: -78.511954 | M58: Entre 5 horas a 6 Horas | N58: Lunes a Domingo 08h00 a 16h00 | O58: Adultos nacionales: $1.00 Niños nacionales menores de 12 años: $0.50 Extranjeros (excluyendo los pertenecientes a Hispanoamérica): $7.00 | Q58: No mascotas No botar basura Equipos de sonido de cualquier tamaño | R58: Ministerio de Ambiente www.ambiente.gob.ec Oficinas dentro del Refugio de Vida Silvestre Pasochoa (+593) 99 894 5704
A59: 058 | B59: ACTIVO | C59: =CONCATENATE(VLOOKUP($D59,CODIFICACIÓN_DPA!$A$2:$B$66,2,FALSE),VLOOKUP($G59,CODIFICACIÓN_DPA!$D$2:$E$6,2,FALSE),CONCATENATE(VLOOKUP($E59,CODIFICACIÓN_DPA!$G$2:$H$3,2,FALSE),VLOOKUP($F59,CODIFICACIÓN_DPA!$J$2:$K$10,2,FALSE)),A59) -> 170175AV0208058 | D59: PIFO | E59: RURAL | F59: Valle de Tumbaco | G59: AVENTURA | H59: Sendero Agua y Vida | I59: Explorar el Sendero Agua y Vida es sumergirse en un viaje lleno de asombro y serenidad a través de los páramos ecuatorianos. Esta caminata ofrece a los excursionistas la oportunidad de contemplar paisajes espectaculares, incluyendo numerosas lagunas andinas y las majestuosas montañas del callejón oriental del Ecuador. Más allá de la inigualable belleza natural, los visitantes también pueden disfrutar de la actividad de pesca en la zona, añadiendo un toque de aventura a la experiencia. Con un grado de dificultad bajo a medio, esta travesía promete momentos de conexión con la naturaleza y recuerdos inolvidables en medio de los paisajes más impresionantes del país. | J59: Se toma la autopista Pifo – Papallacta (E20) hacia el oriente hasta llegar a la parte más alta del páramo a 4000 metros de altura, sector conocido como “La Virgen”; allí hay un desvío a mano izquierda que sube a las antenas de Papallacta | K59: -0.33249666 | L59: -78.203006 | M59: Entre 5 horas a 6 Horas | N59: Se recomienda visitar este sector en los meses de Diciembre a Febrero que suele estar más seco | O59: Gratuito | Q59: No mascotas No botar basura | R59: Ministerio de Ambiente www.ambiente.gob.ec
A60: 059 | B60: INACTIVO | C60: =CONCATENATE(VLOOKUP($D60,CODIFICACIÓN_DPA!$A$2:$B$66,2,FALSE),VLOOKUP($G60,CODIFICACIÓN_DPA!$D$2:$E$6,2,FALSE),CONCATENATE(VLOOKUP($E60,CODIFICACIÓN_DPA!$G$2:$H$3,2,FALSE),VLOOKUP($F60,CODIFICACIÓN_DPA!$J$2:$K$10,2,FALSE)),A60) -> 170176AV0207059 | D60: PÍNTAG | E60: RURAL | F60: Valle de los Chillos | G60: AVENTURA | H60: Sendero Micaloma - Patourco | I60: Explorar el Sendero Micaloma - Patourco ofrece a los senderistas una experiencia enriquecedora en medio de la naturaleza. Aquí, pueden apreciar la rica flora y fauna típica del sitio, mientras disfrutan de vistas impresionantes del nevado Antisana, Cotopaxi y Sincholagua. Además, una panorámica de la laguna La Mica agrega un toque de serenidad a la aventura. Con un grado de dificultad bajo, este sendero es ideal para todos los niveles de habilidad, garantizando una experiencia gratificante y memorable en uno de los entornos más bellos del Ecuador. | J60: Vía Pintag y Vía Antisana se intersectan se convierte en Vía principal, luego tomar Vía hacia Laguna Muerte Pungo, luego tomar via a Laguna La Mica | K60: -0.53664582 | L60: -78.221933 | M60: 2 horas | N60: Se recomienda hacerlo en la mañana | O60: Gratuito | Q60: No mascotas No botar basura | R60: Ministerio de Ambiente www.ambiente.gob.ec
A61: 060 | B61: ACTIVO | C61: =CONCATENATE(VLOOKUP($D61,CODIFICACIÓN_DPA!$A$2:$B$66,2,FALSE),VLOOKUP($G61,CODIFICACIÓN_DPA!$D$2:$E$6,2,FALSE),CONCATENATE(VLOOKUP($E61,CODIFICACIÓN_DPA!$G$2:$H$3,2,FALSE),VLOOKUP($F61,CODIFICACIÓN_DPA!$J$2:$K$10,2,FALSE)),A61) -> 170168AV0205060 | D61: NANEGAL | E61: RURAL | F61: Chocó Andino | G61: AVENTURA | H61: Culunco Guantopungo - Pelagallo | I61: Explorar Culunco Guantopungo - Pelagallo es sumergirse en una experiencia única en medio del bosque nublado. Este trayecto ofrece senderos que atraviesan el paisaje semisubterráneo, con profundidades que alcanzan hasta los 5 metros. Los visitantes tienen la oportunidad de adentrarse en la misteriosa belleza del bosque mientras caminan por senderos que serpentean entre la densa vegetación. Con un grado de dificultad bajo, este recorrido es accesible para todos los niveles de habilidad, brindando una aventura emocionante y memorable en un entorno natural impresionante. | J61: Vía Yunguilla al llegar a Huayraloma girar mano izquierda | K61: 0.057250061 | L61: -78.574452 | M61: 2 horas | N61: Se recomienda hacerlo en la mañana | O61: Gratuito | Q61: No mascotas No botar basura | R61: Rolando Collaguazo (+593) 99 797 2109
A62: 061 | B62: ACTIVO | C62: =CONCATENATE(VLOOKUP($D62,CODIFICACIÓN_DPA!$A$2:$B$66,2,FALSE),VLOOKUP($G62,CODIFICACIÓN_DPA!$D$2:$E$6,2,FALSE),CONCATENATE(VLOOKUP($E62,CODIFICACIÓN_DPA!$G$2:$H$3,2,FALSE),VLOOKUP($F62,CODIFICACIÓN_DPA!$J$2:$K$10,2,FALSE)),A62) -> 170171AV0205061 | D62: NONO | E62: RURAL | F62: Chocó Andino | G62: AVENTURA | H62: Trail del Oso, Trail del Inca Reserva Yanacocha | I62: Explorar el Trail del Oso y el Trail del Inca en la Reserva Yanacocha es una experiencia fascinante que permite a los turistas sumergirse en la biodiversidad única de la zona. Con cuatro senderos disponibles, los visitantes tienen la oportunidad de admirar la rica variedad de flora y fauna que caracteriza a esta reserva. Además, la presencia de cuatro túneles de aproximadamente 30 metros de longitud añade un toque de emoción al recorrido, transportando al público de un escenario a otro en pocos minutos y proporcionando una experiencia inolvidable. Con un grado de dificultad bajo a medio, esta aventura es accesible para la mayoría de los excursionistas, garantizando momentos de asombro y conexión con la naturaleza en un entorno impresionante. | J62: Desde la Av. Occidental se debe tomar el paso a desnivel de la Av. Machala ingresando al barrio "Mena del Hierro", vía a Nono. A 9 km del recorrido y después de pasar la iglesia Rundupamba, hay un letrero la reserva Yanacocha y un camino de piedra que inicia al lado izquierdo de la carretera. Seguir 8 kilómetros hasta llegar a las instalaciones de la Empresa de Agua Potable de Quito (EPMAPS), continuar 2 kilómetros más hasta el ingreso de la Reserva. | K62: -0.11135864 | L62: -78.584967 | M62: 3 horas | N62: Lunes a Viernes 09:00 a 17:30 Sábado, Domingo y Feriados 07:00 a 15:00 (último ingreso 11:30) | O62: $15.00 Extranjeros $5.00 Nacionales | Q62: Reservar con Anticipación No mascotas No botar basura No tocar ni alimentar a los animales silvestres | R62: Fundación Jocotoco www.jocotourecuador.com (+593) 997101535 / (+593) 99 244 0038
A63: 062 | B63: ACTIVO | C63: =CONCATENATE(VLOOKUP($D63,CODIFICACIÓN_DPA!$A$2:$B$66,2,FALSE),VLOOKUP($G63,CODIFICACIÓN_DPA!$D$2:$E$6,2,FALSE),CONCATENATE(VLOOKUP($E63,CODIFICACIÓN_DPA!$G$2:$H$3,2,FALSE),VLOOKUP($F63,CODIFICACIÓN_DPA!$J$2:$K$10,2,FALSE)),A63) -> 170123GA0102062 | D63: MARISCAL SUCRE | E63: URBANO | F63: La Mariscal | G63: GASTRONÓMICO | H63: Santhorno Empanadas | I63: Santhorno Empanadas, fundado por Francisco Larco Villalva, ofrece una experiencia gastronómica única en forma de un "bar de empanadas", reconocido con el premio a la Innovación en el Turismo por el Municipio de Quito. Aquí, los visitantes tienen la oportunidad de disfrutar de una amplia variedad de rellenos en sus empanadas, que van desde opciones clásicas hasta combinaciones creativas y únicas. Además de las empanadas, Santhorno Empanadas ofrece una selección de café, cócteles, vinos y malteadas de malta, machica, así como refrescantes limonadas de guayusa. Esta experiencia gastronómica promete deleitar a los paladares más exigentes con sabores auténticos y deliciosos en un ambiente acogedor y vibrante. | J63: Wilson e5-29 y Juán León Mera | K63: -0.20276862 | L63: -78.492231 | N63: Miércoles a domingo 11:00 a 19:00 | O63: Depende del plato Reservar con anticiapación | R63: Francisco Larco 0979044795 chef@galeriaecuador.com
A64: 063 | B64: ACTIVO | C64: =CONCATENATE(VLOOKUP($D64,CODIFICACIÓN_DPA!$A$2:$B$66,2,FALSE),VLOOKUP($G64,CODIFICACIÓN_DPA!$D$2:$E$6,2,FALSE),CONCATENATE(VLOOKUP($E64,CODIFICACIÓN_DPA!$G$2:$H$3,2,FALSE),VLOOKUP($F64,CODIFICACIÓN_DPA!$J$2:$K$10,2,FALSE)),A64) -> 170123CU0102063 | D64: MARISCAL SUCRE | E64: URBANO | F64: La Mariscal | G64: CULTURAL | H64: Mindalae Museo Etnohistórico De Artesanías Del Ecuador | I64: Dentro del Mindalae, el Museo Etnohistórico de Artesanías del Ecuador, los visitantes tienen la oportunidad de sumergirse en una experiencia cultural única. A lo largo de los 5 espacios del museo, se presentan diversas exposiciones temporales que abordan temas como los ecosistemas forestales, textiles, cerámicas y la cosmovisión indígena. Este espacio ofrece una visión cercana de las ritualidades de los pueblos andinos, mientras colabora estrechamente con las comunidades locales para exhibir sus trabajos artesanales. Además, los visitantes pueden disfrutar de la degustación de productos locales, como catas de café, que complementan la experiencia cultural del museo. En Mindalae, los visitantes pueden sumergirse en la rica historia y tradiciones del Ecuador, mientras aprecian el talento artesanal de sus comunidades indígenas. | J64: Reina Victoria N26-166 y La Niña, esquina. | K64: -0.19896079 | L64: -78.487597 | N64: Lunes a sábado 9:00 a 17:00 Domingo 10:00 a 17:00 | O64: Nacionales USD 3 Extranjeros USD 5 | P64: Depende del grupo | R64: 0999803841 – 0999040484 mindalaequito@gmail.com cstianguez1@gmail.com
A65: 064 | B65: ACTIVO | C65: =CONCATENATE(VLOOKUP($D65,CODIFICACIÓN_DPA!$A$2:$B$66,2,FALSE),VLOOKUP($G65,CODIFICACIÓN_DPA!$D$2:$E$6,2,FALSE),CONCATENATE(VLOOKUP($E65,CODIFICACIÓN_DPA!$G$2:$H$3,2,FALSE),VLOOKUP($F65,CODIFICACIÓN_DPA!$J$2:$K$10,2,FALSE)),A65) -> 170123GA0102064 | D65: MARISCAL SUCRE | E65: URBANO | F65: La Mariscal | G65: GASTRONÓMICO | H65: Chawar Shop | I65: Chawar Shop ofrece una experiencia gastronómica única que refleja el espíritu de las montañas del Ecuador. Aquí, mujeres trabajan con el agave para elaborar una bebida propia de los Andes llamada Mishkita. Esta bebida tradicional, elaborada mediante un proceso ancestral e industrializado, es el corazón de la experiencia culinaria en Chawar. Los visitantes tienen la oportunidad de disfrutar de una cata de Mishkita, sumergiéndose en los sabores auténticos de esta bebida que encapsula la esencia de la región. En Chawar Shop, los comensales pueden deleitarse con una experiencia gastronómica que celebra las tradiciones y la cultura de las montañas ecuatorianas. | J65: Madrid E16-81 y Coruña | K65: -0.21159602 | L65: -78.481947 | N65: Martes - Sábado 12:00pm a 8:00pm | O65: Depende de la bebida | R65: 980781963
A66: 065 | B66: ACTIVO | C66: =CONCATENATE(VLOOKUP($D66,CODIFICACIÓN_DPA!$A$2:$B$66,2,FALSE),VLOOKUP($G66,CODIFICACIÓN_DPA!$D$2:$E$6,2,FALSE),CONCATENATE(VLOOKUP($E66,CODIFICACIÓN_DPA!$G$2:$H$3,2,FALSE),VLOOKUP($F66,CODIFICACIÓN_DPA!$J$2:$K$10,2,FALSE)),A66) -> 170112GA0103065 | D66: IÑAQUITO | E66: URBANO | F66: Centro Norte | G66: GASTRONÓMICO | H66: Joint Ec | I66: Joint Ec ofrece una experiencia gastronómica única al fusionar delicias culinarias con un toque de CBD. Los comensales pueden deleitarse con platos como el exquisito lomo fino, la pizza de la casa y una variedad de deliciosos postres, todo ello acompañado de bebidas cuidadosamente elaboradas. Lo distintivo de Joint Ec radica en la incorporación de CBD, que agrega un elemento adicional a la experiencia culinaria, brindando un toque de relajación y bienestar. Esta combinación de sabores y beneficios hace que la experiencia gastronómica en Joint Ec sea verdaderamente única y memorable. | J66: González Suárez y Jacinto Bejarano | K66: -0.1948963 | L66: -78.47764 | N66: Lunes a sábado 10:00 a 23:00 | O66: Depende del grupo | P66: Depende del grupo | R66: 995664373
A67: 066 | B67: ACTIVO | C67: =CONCATENATE(VLOOKUP($D67,CODIFICACIÓN_DPA!$A$2:$B$66,2,FALSE),VLOOKUP($G67,CODIFICACIÓN_DPA!$D$2:$E$6,2,FALSE),CONCATENATE(VLOOKUP($E67,CODIFICACIÓN_DPA!$G$2:$H$3,2,FALSE),VLOOKUP($F67,CODIFICACIÓN_DPA!$J$2:$K$10,2,FALSE)),A67) -> 170169GA0205066 | D67: NANEGALITO | E67: RURAL | F67: Chocó Andino | G67: GASTRONÓMICO | H67: Rumisitana | I67: Rumisitana ofrece una experiencia gastronómica excepcional al invitar a los visitantes a recorrer su Tour de Café con Leche. En este recorrido, los participantes tienen la oportunidad de adentrarse en el corazón del bosque nublado mientras disfrutan de una deliciosa taza de café. Casa Rumisitana abre sus puertas para brindar una experiencia única, donde la fusión de la belleza natural del entorno con el aroma y el sabor del café crea un ambiente verdaderamente encantador. Este tour promete deleitar todos los sentidos y ofrece a los visitantes la oportunidad de disfrutar de una experiencia inolvidable en medio de la exuberante vegetación de la zona. | J67: Calle Guayaquil. Km 1.1 vía a Nanegal, Nanegalito, | K67: 0.066395994 | L67: -78.676208 | M67: 1 hora | N67: Bajo reserva | O67: Depende del grupo | P67: Depende del grupo | R67: 995611026
A68: 067 | B68: ACTIVO | C68: =CONCATENATE(VLOOKUP($D68,CODIFICACIÓN_DPA!$A$2:$B$66,2,FALSE),VLOOKUP($G68,CODIFICACIÓN_DPA!$D$2:$E$6,2,FALSE),CONCATENATE(VLOOKUP($E68,CODIFICACIÓN_DPA!$G$2:$H$3,2,FALSE),VLOOKUP($F68,CODIFICACIÓN_DPA!$J$2:$K$10,2,FALSE)),A68) -> 170127CU0103067 | D68: RUMIPAMBA | E68: URBANO | F68: Centro Norte | G68: CULTURAL | H68: Rumipamba | I68: El Parque Arqueológico y Ecológico de Rumipamba ofrece una experiencia inmersiva y educativa sobre la historia de Quito Prehispánico. A través de diversos espacios interpretativos, los visitantes pueden sumergirse en la vida de los antiguos pobladores de Rumipamba y el valle de Quito. Una de las atracciones principales es el espacio de arenero, donde los niños pueden excavar réplicas de vasijas, artefactos, semillas y huesos de animales. Una vez encontrados, los objetos pueden llevarse al laboratorio para su limpieza, medición, dibujo y clasificación. Además, los visitantes pueden experimentar la emoción de la excavación de una tumba con entierro primario, utilizando brochas para descubrir un esqueleto enterrado. Esta experiencia lúdico-científica ofrece una mirada fascinante al pasado y permite a los visitantes participar activamente en la exploración arqueológica. | J68: Nuño de Valderrama s/n, Quito 170147 | K68: -0.18140565 | L68: -78.501043 | M68: Depende el recorrido | N68: Miercoles a Domingo 6:00 a 16:00 | O68: Gratuito | P68: Depende del grupo | R68: 22242313
A69: 068 | B69: ACTIVO | C69: =CONCATENATE(VLOOKUP($D69,CODIFICACIÓN_DPA!$A$2:$B$66,2,FALSE),VLOOKUP($G69,CODIFICACIÓN_DPA!$D$2:$E$6,2,FALSE),CONCATENATE(VLOOKUP($E69,CODIFICACIÓN_DPA!$G$2:$H$3,2,FALSE),VLOOKUP($F69,CODIFICACIÓN_DPA!$J$2:$K$10,2,FALSE)),A69) -> 170123CU0102068 | D69: MARISCAL SUCRE | E69: URBANO | F69: La Mariscal | G69: CULTURAL | H69: Malali Arte | I69: Malali Arte ofrece una experiencia única que fusiona la naturaleza, la convivencia y el arte. Este espacio es un santuario para la creatividad, donde los visitantes pueden sumergirse en talleres de modelado en arcilla café o terracota, utilizando sellos para dar forma a sus creaciones. Los talleres brindan la oportunidad de explorar la expresión artística mientras se conectan con la tierra y se inspiran en el entorno natural que rodea a Malali Arte. Esta experiencia promueve la creatividad, la relajación y la conexión con uno mismo a través del arte y la naturaleza. | J69: Coruña y Vizcaya, | K69: -0.20923936 | L69: -78.481948 | M69: Denpende de el taller | N69: Martes a sábado 10:00 a 19:00 | O69: USD 30 USD 90 | P69: 5 cupos por taller | R69: 098 321 2924
A70: 069 | B70: ACTIVO | C70: =CONCATENATE(VLOOKUP($D70,CODIFICACIÓN_DPA!$A$2:$B$66,2,FALSE),VLOOKUP($G70,CODIFICACIÓN_DPA!$D$2:$E$6,2,FALSE),CONCATENATE(VLOOKUP($E70,CODIFICACIÓN_DPA!$G$2:$H$3,2,FALSE),VLOOKUP($F70,CODIFICACIÓN_DPA!$J$2:$K$10,2,FALSE)),A70) -> 170112GA0103069 | D70: IÑAQUITO | E70: URBANO | F70: Centro Norte | G70: GASTRONÓMICO | H70: Mi Chá | I70: Este restaurante te permite vivir de cerca la cultura china, con sus platillos y ambiente permite vivir la experiencia de la ceremonia del té junto con música tradicional y baile propios de esta cultura. | J70: Portete E10-305 y Av.6 de diciembre | K70: -0.17326301 | L70: -78.475872 | M70: 1 hora | N70: Lunes a jueves 11:00 a 19:00 Viernes a domingo 10:00 019:00 | O70: Depende del grupo | Q70: La experiencia se da los días viernes | R70: 939185798
A71: 070 | B71: INACTIVO | C71: =CONCATENATE(VLOOKUP($D71,CODIFICACIÓN_DPA!$A$2:$B$66,2,FALSE),VLOOKUP($G71,CODIFICACIÓN_DPA!$D$2:$E$6,2,FALSE),CONCATENATE(VLOOKUP($E71,CODIFICACIÓN_DPA!$G$2:$H$3,2,FALSE),VLOOKUP($F71,CODIFICACIÓN_DPA!$J$2:$K$10,2,FALSE)),A71) -> 170114GA0103070 | D71: JIPIJAPA | E71: URBANO | F71: Centro Norte | G71: GASTRONÓMICO | H71: Les Sens | I71: Le Sens va más allá de la comida. Su ambiente medieval está meticulosamente decorado con detalles que evocan la opulencia y el misterio de la Edad Media. Desde platos de carne asada hasta guisos aromáticos y postres decadentes, cada creación está cuidadosamente elaborada para transportarte a la mesa de un noble medieval. | J71: Av. de los Shyris N43-209 y, Quito 170513 | K71: -0.16288818 | L71: -78.47885 | M71: Depende de el grupo | N71: Luneas a sábado 12:00 a 21:00 Domingo 12:00 a 17:00 | O71: Depende del grupo | R71: 099 581 1088 https://wa.link/qqf1bg
A72: 071 | B72: ACTIVO | C72: =CONCATENATE(VLOOKUP($D72,CODIFICACIÓN_DPA!$A$2:$B$66,2,FALSE),VLOOKUP($G72,CODIFICACIÓN_DPA!$D$2:$E$6,2,FALSE),CONCATENATE(VLOOKUP($E72,CODIFICACIÓN_DPA!$G$2:$H$3,2,FALSE),VLOOKUP($F72,CODIFICACIÓN_DPA!$J$2:$K$10,2,FALSE)),A72) -> 170157GA0208071 | D72: CUMBAYÁ | E72: RURAL | F72: Valle de Tumbaco | G72: GASTRONÓMICO | H72: Casa de Experiencias Pacari (Cumbayá) | I72: Descubre una amplia variedad de chocolates Pacari, cada uno con su propia historia y carácter distintivo. Desde el chocolate negro intenso hasta las combinaciones de sabores más innovadoras, cada muestra te llevará en un viaje sensorial único que estimulará tus sentidos y despertará tu paladar. Además de degustar el chocolate, aprenderás sobre su origen, los métodos de producción sostenible utilizados por Pacari y la importancia de apoyar a los productores de cacao locales. Es una experiencia educativa y deliciosa que te dejará con una apreciación renovada por este manjar celestial. | J72: Coehlo Plaza - Calle Francisco de Orellana | K72: -0.19593424 | L72: -78.433824 | M72: 1 hora | N72: Lunes a viernes 10:00 a 19:00 Sábado y domingo 9:00 a 19:00 | O72: $10.00 por persona, el guía y personal gratis. | Q72: Personas alérgicas a los frutos secos o chocolate | R72: 958749233
A73: 072 | B73: ACTIVO | C73: =CONCATENATE(VLOOKUP($D73,CODIFICACIÓN_DPA!$A$2:$B$66,2,FALSE),VLOOKUP($G73,CODIFICACIÓN_DPA!$D$2:$E$6,2,FALSE),CONCATENATE(VLOOKUP($E73,CODIFICACIÓN_DPA!$G$2:$H$3,2,FALSE),VLOOKUP($F73,CODIFICACIÓN_DPA!$J$2:$K$10,2,FALSE)),A73) -> 170123GA0102072 | D73: MARISCAL SUCRE | E73: URBANO | F73: La Mariscal | G73: GASTRONÓMICO | H73: Mercedes Benz´s Gourmet Experience | I73: El Mercedes Benz's Gourmet Experience es mucho más que una simple cena; es una experiencia culinaria que fusiona la elegancia y el lujo con la excelencia gastronómica. Ubicado en un entorno sofisticado y exclusivo, este evento gastronómico ofrece a los comensales la oportunidad de deleitarse con platos exquisitos preparados por reconocidos chefs de renombre internacional. Pero la experiencia gastronómica en el Mercedes Benz's Gourmet Experience va más allá de la comida. Los comensales tienen la oportunidad de interactuar con los chefs, aprender sobre las técnicas culinarias utilizadas y descubrir los secretos detrás de cada plato. | J73: Rubio de Arevalo &, Quito 170109 | K73: -0.20597609 | L73: -78.481088 | M73: Depende de la actividad | N73: Lunes a sábado 13:00 a 24:00 Domingo 13:00 a 17:00 | O73: Le tour du monde al revés USD 69. + maridaje de vinos USD 29.90 | P73: Cupos limitados | Q73: Avisar si se tiene alergías a algun alimento | R73: 098-583-5555 o al 099-255-6242.
A74: 073 | B74: ACTIVO | C74: =CONCATENATE(VLOOKUP($D74,CODIFICACIÓN_DPA!$A$2:$B$66,2,FALSE),VLOOKUP($G74,CODIFICACIÓN_DPA!$D$2:$E$6,2,FALSE),CONCATENATE(VLOOKUP($E74,CODIFICACIÓN_DPA!$G$2:$H$3,2,FALSE),VLOOKUP($F74,CODIFICACIÓN_DPA!$J$2:$K$10,2,FALSE)),A74) -> 170112GA0103073 | D74: IÑAQUITO | E74: URBANO | F74: Centro Norte | G74: GASTRONÓMICO | H74: La Celosa Gastropub | I74: La Celosa Gastropub ofrece una experiencia culinaria auténtica y vibrante, sumergiéndote en los sabores y la cultura de Colombia. Desde la música hasta la decoración, cada detalle te transporta a las calles de Bogotá . Los platos, comoel chicharrón colombiano, son auténticos y deliciosos, mientras que la variedad de cócteles ofrece un toque moderno a la tradición colombiana. El ambiente acogedor y el servicio amable hacen de La Celosa un destino imprescindible para los amantes de la comida colombiana y los exploradores gastronómicos por igual. | J74: Pradera, y, Quito 170517 | K74: -0.19592868 | L74: -78.484462 | M74: Depende del grupo | N74: Domingo a martes 12:00 a 20:00 Miércoles a sábado 12:00 a 4:00 | O74: Depende del grupo | P74: Bajo reserva | R74: 969246192
A75: 074 | B75: ACTIVO | C75: =CONCATENATE(VLOOKUP($D75,CODIFICACIÓN_DPA!$A$2:$B$66,2,FALSE),VLOOKUP($G75,CODIFICACIÓN_DPA!$D$2:$E$6,2,FALSE),CONCATENATE(VLOOKUP($E75,CODIFICACIÓN_DPA!$G$2:$H$3,2,FALSE),VLOOKUP($F75,CODIFICACIÓN_DPA!$J$2:$K$10,2,FALSE)),A75) -> 170180GA0204074 | D75: SAN ANTONIO | E75: RURAL | F75: Parroquias Equinocciales | G75: GASTRONÓMICO | H75: Kimos House | I75: Las cervezas artesanales de Kimo House son un tributo a la tradición cervecera local, elaboradas con ingredientes frescos y pasión por el arte de la cerveza. Ya sea disfrutando de una cerveza o coctél refrescante o una cerveza de temporada, cada trago es una aventura sensorial que te conecta con la esencia de Mompiche. | J75: OE1-217 Moraspungo S/N y, Av. Manuel Córdova Galarz | K75: -0.00043195397 | L75: -78.455 | N75: Miércoles, viernes y sábado 18:00 a 1:00 | P75: Bajo reserva | R75: 099 585 0953
A76: 075 | B76: ACTIVO | C76: =CONCATENATE(VLOOKUP($D76,CODIFICACIÓN_DPA!$A$2:$B$66,2,FALSE),VLOOKUP($G76,CODIFICACIÓN_DPA!$D$2:$E$6,2,FALSE),CONCATENATE(VLOOKUP($E76,CODIFICACIÓN_DPA!$G$2:$H$3,2,FALSE),VLOOKUP($F76,CODIFICACIÓN_DPA!$J$2:$K$10,2,FALSE)),A76) -> 170114GA0103075 | D76: JIPIJAPA | E76: URBANO | F76: Centro Norte | G76: GASTRONÓMICO | H76: Petit Crepe | I76: Petit Crêpe Ecuador ofrece mucho más que deliciosos crepes. Además de saborear exquisitas creaciones francesas, aquí también puedes desatar tu creatividad en sus talleres de pintura de imágenes en cerámica. Sumérgete en una experiencia única donde puedes disfrutar de la gastronomía francesa mientras te sumerges en el arte de la pintura. Los talleres ofrecen una oportunidad para expresar tu lado artístico mientras disfrutas de un ambiente acogedor y amigable. Ya sea que seas un aficionado al arte o simplemente busques una experiencia divertida y única, los talleres de pintura en cerámica en Petit Crêpe Ecuador son una excelente opción para disfrutar solo o en compañía de amigos y familiares. | J76: Av. Río Coca E4-116, Quito 170501 | K76: -0.16073481 | L76: -78.479521 | N76: Lunes a sábado 9:00 a 8:00 Domingo 8:00 a 18:00 | O76: Depende de la actividad | P76: Bajo reserva | R76: 099 990 5041
A77: 076 | B77: ACTIVO | C77: =CONCATENATE(VLOOKUP($D77,CODIFICACIÓN_DPA!$A$2:$B$66,2,FALSE),VLOOKUP($G77,CODIFICACIÓN_DPA!$D$2:$E$6,2,FALSE),CONCATENATE(VLOOKUP($E77,CODIFICACIÓN_DPA!$G$2:$H$3,2,FALSE),VLOOKUP($F77,CODIFICACIÓN_DPA!$J$2:$K$10,2,FALSE)),A77) -> 170114CU0103076 | D77: JIPIJAPA | E77: URBANO | F77: Centro Norte | G77: CULTURAL | H77: Bellas Artes UIO | I77: Bellas Artes UIO es el refugio perfecto para aquellos que buscan explorar y desarrollar su creatividad en un entorno estimulante y acogedor. Como una escuela especializada en fomentar las cualidades artísticas de niños, jóvenes y adultos, ofrece una amplia gama de experiencias en forma de talleres y cursos permanentes. Desde las técnicas clásicas de pintura y dibujo hasta las formas más contemporáneas de expresión artística, cada clase está diseñada para inspirar y desafiar a los estudiantes a alcanzar su máximo potencial creativo. | J77: Matriz: Av. Gaspar de Villarroel y Av. De los Shyris edificio Fénix | K77: -0.17002887 | L77: -78.479043 | M77: Depende del taller | N77: Lunes a sábado 10:00 a 19:00 | O77: Depende de la actividad | P77: Cupos limitados | R77: 099 531 0447
A78: 077 | B78: ACTIVO | C78: =CONCATENATE(VLOOKUP($D78,CODIFICACIÓN_DPA!$A$2:$B$66,2,FALSE),VLOOKUP($G78,CODIFICACIÓN_DPA!$D$2:$E$6,2,FALSE),CONCATENATE(VLOOKUP($E78,CODIFICACIÓN_DPA!$G$2:$H$3,2,FALSE),VLOOKUP($F78,CODIFICACIÓN_DPA!$J$2:$K$10,2,FALSE)),A78) -> 170157GA0208077 | D78: CUMBAYÁ | E78: RURAL | F78: Valle de Tumbaco | G78: GASTRONÓMICO | H78: Freskatzo - cocina | I78: Freskatzo - Cocina es mucho más que un lugar para disfrutar de deliciosas comidas; es un destino para explorar y aprender el arte culinario. Sus talleres ofrecen una experiencia única donde los participantes pueden sumergirse en el mundo de la cocina, desde aprender técnicas básicas hasta perfeccionar platos gourmet. Ya sea que seas un principiante entusiasta o un chef aficionado en busca de nuevas habilidades, los talleres de Freskatzo ofrecen una experiencia educativa y divertida que seguro dejará un sabor duradero en tu paladar y en tu memoria culinaria. | J78: Calle Gabriel García Moreno E3-126, Cumbaya 170157 | K78: -0.20204018 | L78: -78.428119 | M78: Depende del taller | N78: Bajo reserva | O78: Depende de la actividad | P78: Depende del grupo | R78: 994373948
A79: 078 | B79: ACTIVO | C79: =CONCATENATE(VLOOKUP($D79,CODIFICACIÓN_DPA!$A$2:$B$66,2,FALSE),VLOOKUP($G79,CODIFICACIÓN_DPA!$D$2:$E$6,2,FALSE),CONCATENATE(VLOOKUP($E79,CODIFICACIÓN_DPA!$G$2:$H$3,2,FALSE),VLOOKUP($F79,CODIFICACIÓN_DPA!$J$2:$K$10,2,FALSE)),A79) -> 170103GA0101078 | D79: CENTRO HISTÓRICO | E79: URBANO | F79: Centro Histórico | G79: GASTRONÓMICO | H79: Claro Oscuro - taller de cocina | I79: Claro Oscuro - Taller de Cocina ofrece una experiencia culinaria excepcional y variada en el corazón del centro histórico, en una encantadora casa patrimonial. Además de la oportunidad de disfrutar de deliciosos platos elaborados con ingredientes frescos y locales, este taller brinda una amplia gama de actividades culinarias, que incluyen talleres de showcooking y clases de coctelería. Durante estas clases interactivas, impartidas por chefs expertos, los participantes tienen la oportunidad de aprender técnicas de cocina y preparación de cócteles mientras disfrutan de una experiencia práctica y divertida. Desde aprender a preparar platos tradicionales hasta descubrir secretos de mixología, Claro Oscuro ofrece una experiencia culinaria completa y enriquecedora para todos los amantes de la buena comida y las bebidas creativas. | J79: Venezuela S1-26, Quito 170405 | K79: -0.22321312 | L79: -78.514481 | M79: Depende del taller | N79: Martes a jueves 12:00 a 15:00 Viernes y sábado 12:00 a 9:30 Domingo 10:00 a 15:30 | O79: Depende de la actividad | P79: Cupos limitados | R79: 992212227
A80: 079 | B80: ACTIVO | C80: =CONCATENATE(VLOOKUP($D80,CODIFICACIÓN_DPA!$A$2:$B$66,2,FALSE),VLOOKUP($G80,CODIFICACIÓN_DPA!$D$2:$E$6,2,FALSE),CONCATENATE(VLOOKUP($E80,CODIFICACIÓN_DPA!$G$2:$H$3,2,FALSE),VLOOKUP($F80,CODIFICACIÓN_DPA!$J$2:$K$10,2,FALSE)),A80) -> 170112GA0103079 | D80: IÑAQUITO | E80: URBANO | F80: Centro Norte | G80: GASTRONÓMICO | H80: Rey Asador | I80: Rey Asador ofrece una experiencia gastronómica incomparable con su enfoque en la parrillada. Ubicado en un ambiente acogedor y lleno de ambiente, este restaurante es el destino perfecto para los amantes de la carne a la parrilla. Además de su delicioso menú, Rey Asador también ofrece talleres de parrillada donde los participantes pueden aprender técnicas de asado, selección de cortes y secretos para lograr las mejores parrilladas en casa. Estos talleres proporcionan una experiencia práctica y educativa que garantiza que cada comida al aire libre sea memorable y deliciosa. | J80: Rumania S/N y Polonia | K80: -0.18988887 | L80: -78.489191 | M80: Depende del taller | N80: Previa reserva o bajo inscripción | O80: Depende del taller | P80: Bajo inscripción | R80: 962703781/ 098 858 22350
A81: 080 | B81: ACTIVO | C81: =CONCATENATE(VLOOKUP($D81,CODIFICACIÓN_DPA!$A$2:$B$66,2,FALSE),VLOOKUP($G81,CODIFICACIÓN_DPA!$D$2:$E$6,2,FALSE),CONCATENATE(VLOOKUP($E81,CODIFICACIÓN_DPA!$G$2:$H$3,2,FALSE),VLOOKUP($F81,CODIFICACIÓN_DPA!$J$2:$K$10,2,FALSE)),A81) -> 170184GA0208080 | D81: TUMBACO | E81: RURAL | F81: Valle de Tumbaco | G81: GASTRONÓMICO | H81: Cacao House | I81: Cacao House ofrece una experiencia gastronómica única centrada en el cacao, un ingrediente emblemático de la cultura ecuatoriana. En este lugar, los visitantes pueden sumergirse en el fascinante mundo del chocolate, desde la cosecha de los granos de cacao hasta la elaboración artesanal de exquisitos productos de chocolate. Además de disfrutar de deliciosos chocolates y bebidas de cacao, Cacao House también ofrece talleres donde los participantes pueden aprender sobre la historia del cacao, sus diferentes variedades y técnicas de chocolatería. Estos talleres brindan una oportunidad emocionante para explorar la cultura del cacao y experimentar la magia de crear chocolates de calidad artesanal. | J81: Vía Intervalles S/N Cununyacu, Quito 170902 | K81: -0.22830725 | L81: -78.42883 | N81: Lunes a viernes 10:00 a 20:00 | O81: USD 35 a miembros del lugar USD 45 púeblico en general | P81: Bajo reserva | R81: 962773529
A82: 081 | B82: ACTIVO | C82: =CONCATENATE(VLOOKUP($D82,CODIFICACIÓN_DPA!$A$2:$B$66,2,FALSE),VLOOKUP($G82,CODIFICACIÓN_DPA!$D$2:$E$6,2,FALSE),CONCATENATE(VLOOKUP($E82,CODIFICACIÓN_DPA!$G$2:$H$3,2,FALSE),VLOOKUP($F82,CODIFICACIÓN_DPA!$J$2:$K$10,2,FALSE)),A82) -> 170103GA0101081 | D82: CENTRO HISTÓRICO | E82: URBANO | F82: Centro Histórico | G82: GASTRONÓMICO | H82: MINKA CHOCOLATE EXPERIENCE | I82: Minka Cacao ofrece una experiencia gastronómica única centrada en el cacao, un ingrediente emblemático de la cultura ecuatoriana. Situado en un entorno encantador y acogedor, este lugar invita a los visitantes a sumergirse en el fascinante mundo del chocolate. Además de disfrutar de exquisitos productos de chocolate, los visitantes tienen la oportunidad de participar en talleres interactivos donde pueden aprender sobre la historia del cacao, sus diferentes variedades y técnicas de chocolatería artesanal. Estos talleres proporcionan una experiencia educativa y divertida que permite a los participantes explorar la rica herencia del cacao ecuatoriano mientras crean sus propias delicias de chocolate. | J82: Calle Simón Bolívar OE6-15 y Sebastián de Benalcázar Junto al Hotel Casa Gangotena ( Plaza San Francisco, de Quito, Quito 170130 | K82: -0.22108208 | L82: -78.515147 | M82: Experiencia de Cacao y chocolate: 30 minutos Experiencia de chocolate y vino: 2 horas Haz el mejor chocolate caliente: 1 hora Haz una barra de chocolate: 1 hora Haz dos barras de chocolate: 1,30 hora | N82: Siempre abierto | O82: Experiencia de Cacao y chocolate: USD 10 Experiencia de chocolate y vino: 28 Haz el mejor chocolate caliente: USD 15 Haz una barra de chocolate: USD 15 Haz dos barras de chocolate: USD 25 | P82: Bajo reserva | Q82: Alérgicos a frutos secos | R82: 099 800 2598
A83: 082 | B83: ACTIVO | C83: =CONCATENATE(VLOOKUP($D83,CODIFICACIÓN_DPA!$A$2:$B$66,2,FALSE),VLOOKUP($G83,CODIFICACIÓN_DPA!$D$2:$E$6,2,FALSE),CONCATENATE(VLOOKUP($E83,CODIFICACIÓN_DPA!$G$2:$H$3,2,FALSE),VLOOKUP($F83,CODIFICACIÓN_DPA!$J$2:$K$10,2,FALSE)),A83) -> 170114GA0103082 | D83: JIPIJAPA | E83: URBANO | F83: Centro Norte | G83: GASTRONÓMICO | H83: Zero Lab | I83: Zero Lab Restaurant redefine la experiencia gastronómica con su enfoque innovador y multisensorial del fine dining. Situado en un entorno elegante y contemporáneo, este restaurante ofrece mucho más que una comida excepcional: brinda una experiencia culinaria completa que estimula todos los sentidos. Además de su exquisito menú, Zero Lab organiza talleres multisensoriales donde los comensales pueden sumergirse en un mundo de sabores, texturas y aromas únicos. | J83: Paris n 43-41 y Emilio zola, Quito 170135 | K83: -0.16350844 | L83: -78.476776 | N83: Martes a domingo 11:00 a 23:00 | O83: Depende de la actividad | P83: Cupos limitados | R83: 099 819 8877
A84: 083 | B84: ACTIVO | C84: =CONCATENATE(VLOOKUP($D84,CODIFICACIÓN_DPA!$A$2:$B$66,2,FALSE),VLOOKUP($G84,CODIFICACIÓN_DPA!$D$2:$E$6,2,FALSE),CONCATENATE(VLOOKUP($E84,CODIFICACIÓN_DPA!$G$2:$H$3,2,FALSE),VLOOKUP($F84,CODIFICACIÓN_DPA!$J$2:$K$10,2,FALSE)),A84) -> 170163CU0208083 | D84: GUAYLLABAMBA | E84: RURAL | F84: Valle de Tumbaco | G84: CULTURAL | H84: Hacienda Siento 13 | I84: Hacienda Siento13 te invita a sumergirte en una experiencia única y revitalizante en medio de la naturaleza. Este refugio de bienestar está diseñado para explorar los beneficios del mundo cannábico en un entorno armonioso y acogedor. Disfruta de la primera experiencia multisensorial cannábica del país, donde podrás conectar con tus sentidos y encontrar equilibrio en cada momento. Nuestro espacio ofrece actividades educativas, así como espacios dedicados a la relajación y la recreación, donde podrás pasear por hermosos jardines, conocer diversas plantas, participar en sesiones de degustación y sumergirte en la serenidad de nuestros entornos naturales. Es el lugar perfecto para desconectar del estrés diario y conectar contigo mismo/a mientras exploras los beneficios del cannabis en un ambiente seguro y tranquilo. | J84: Calle de los Amancayes, 170209 | K84: -0.055839084 | L84: -78.300291 | M84: Depende de la actividad | N84: Luneas a domingo 7:00 a 16:00 | O84: Depende la actividad | P84: Bajo reserva | R84: 099 618 7637
A85: 084 | B85: ACTIVO | C85: =CONCATENATE(VLOOKUP($D85,CODIFICACIÓN_DPA!$A$2:$B$66,2,FALSE),VLOOKUP($G85,CODIFICACIÓN_DPA!$D$2:$E$6,2,FALSE),CONCATENATE(VLOOKUP($E85,CODIFICACIÓN_DPA!$G$2:$H$3,2,FALSE),VLOOKUP($F85,CODIFICACIÓN_DPA!$J$2:$K$10,2,FALSE)),A85) -> 170175NA0208084 | D85: PIFO | E85: RURAL | F85: Valle de Tumbaco | G85: NATURAL | H85: Atukpamba Mulauco | I85: Atukpamba es una granja integral y escuela de permacultura situada en las proximidades de Pifo, Ecuador. Es un destino que ofrece una experiencia enriquecedora para quienes buscan aprender sobre agricultura sostenible y soberanía alimentaria. Desde visitas turísticas que permiten explorar sus terrenos y participar en actividades prácticas hasta programas académicos diseñados para estudiantes y profesionales interesados en la permacultura, Atukpamba ofrece una amplia gama de oportunidades educativas. Además, sus experiencias enfocadas en la soberanía alimentaria proporcionan conocimientos prácticos sobre la importancia de la autosuficiencia y el respeto por los recursos naturales. | J85: Pifo | K85: -0.25900409 | L85: -78.319989 | M85: Talleres: 8 horas Visitas: 1. 3 horas 2. 6 horas Visitas académicas: 2 horas Experiencias: dependen de la actividad | N85: Bajo reserva | O85: Talleres: USD 60 -110 Visitas Turísticas: Opción 1. 2 adultos: $46.15 por persona 3 adultos: $34.30 por persona 4 adultos: $28.35 por persona 5 adultos: $24.80 por persona 6 adultos o más: Consulta el valor preferencial. Niña o niño entre 5 y 12 años: $7 extra. Niña o niño de 0 a 4 años: gratis. Opción 2. 2 adultos: $65.70 por persona 3 adultos: $46.3 por persona 4 adultos: $36.30 por persona 5 adultos: $30.78 por persona 6 adultos o más: Consulta el valor preferencial. Niña o niño entre 5 y 12 años: $7 extra Niña o niño de 0 a 4 años: gratis. Se puede potenciar la visita disfrutando de un refrigerio y/o almuerzo hechos con productos de la granja: Almuerzo: $15 adultos/$7.5 niños Refrigerio: $3 adultos/$2 niños Visita académica: Tamaño del grupo: 15-20 personas Costo por persona: $11.25 usd* Tamaño del grupo: 21-25 personas Costo por persona: $13 usd* Tamaño del grupo: 26-30 personas Costo por persona: $11.25 usd* | P85: Depende del grupo | R85: info@atukpamba.com 0989903550
A86: 085 | B86: ACTIVO | C86: =CONCATENATE(VLOOKUP($D86,CODIFICACIÓN_DPA!$A$2:$B$66,2,FALSE),VLOOKUP($G86,CODIFICACIÓN_DPA!$D$2:$E$6,2,FALSE),CONCATENATE(VLOOKUP($E86,CODIFICACIÓN_DPA!$G$2:$H$3,2,FALSE),VLOOKUP($F86,CODIFICACIÓN_DPA!$J$2:$K$10,2,FALSE)),A86) -> 170175NA0208085 | D86: PIFO | E86: RURAL | F86: Valle de Tumbaco | G86: NATURAL | H86: Escorza Granja Orgánica | I86: La experiencia en Escorza Granja Orgánica Itulcachi es un viaje sensorial a la belleza natural y la sostenibilidad. Ubicada en un entorno montañoso pintoresco, esta granja orgánica ofrece una inmersión total en la agricultura sostenible y el estilo de vida campesino. Desde recorridos por los campos donde se cultivan una variedad de productos orgánicos hasta la participación en actividades de cosecha y preparación de alimentos frescos, cada momento está impregnado de conexión con la tierra y la autenticidad rural. La hospitalidad de los anfitriones y la calidez de la comunidad local completan esta experiencia enriquecedora que deja una impresión perdurable en todos los sentidos. | J86: Pifo, Itulcachi, Calle principal y, 6ta Transversal, Quito 170175 | K86: -0.27230711 | L86: -78.356552 | M86: Depende de la actividad | N86: Viernes y Sábados de 6:00 a 23: 00pm | P86: Depende del grupo | R86: 096 271 5113 https://www.facebook.com/EscorzaGranjaOrganica/
A87: 086 | B87: ACTIVO | C87: =CONCATENATE(VLOOKUP($D87,CODIFICACIÓN_DPA!$A$2:$B$66,2,FALSE),VLOOKUP($G87,CODIFICACIÓN_DPA!$D$2:$E$6,2,FALSE),CONCATENATE(VLOOKUP($E87,CODIFICACIÓN_DPA!$G$2:$H$3,2,FALSE),VLOOKUP($F87,CODIFICACIÓN_DPA!$J$2:$K$10,2,FALSE)),A87) -> 170185GA0208086 | D87: YARUQUÍ | E87: RURAL | F87: Valle de Tumbaco | G87: GASTRONÓMICO | H87: Chaupi Estancia | I87: Chaupi Estancia, donde la pasión por el vino de altura se fusiona con un entorno natural impresionante. Más que una bodega, es una experiencia sensorial única gracias a nuestros viñedos situados en una altitud única que define el carácter de nuestras uvas. Ofrecemos dos experiencias cautivadoras: "Envuelve tus Sentidos", una visita guiada por viñedos, cava y laboratorio con degustación de selecciones premium; y "Sinfonía de Sabores", una inmersión enológica con degustación de vinos ultra premium acompañada de una tabla de charcutería premium. Para asegurar tu lugar, te pedimos contactarnos con al menos 72 horas de antelación en fines de semana y feriados, y 48 horas de antelación de miércoles a viernes, asegurando así una atención personalizada y el exclusivo disfrute de nuestra finca. | J87: Yaruquí - Ecuador | K87: -0.15310476 | L87: -78.338524 | M87: Depende de la actividad 3 o 4 horas | N87: Horarios Disponibles: • Mañana: 10:00 am - 1:00 pm • Tarde: 1:30 pm - 4:30 pm • (Horarios disponibles de miércoles a domingo) | O87: Experiencias Disponibles: 1. Envuelve tus Sentidos: • Duración: 3 horas • Precio: $35 dólares por persona más IVA • Incluye: Una visita guiada por nuestros viñedos, cava y laboratorio. Aprenderás sobre el proceso de producción del vino y, al final, disfrutarás de una degustación de nuestras selecciones premium. 2. Sinfonía de Sabores: • Duración: 4 horas • Precio: $50 dólares por persona más IVA • Incluye: Una experiencia completa con una charla enológica detallada, seguida de una degustación de nuestros vinos ultra premium. Además, disfrutarás de una tabla de charcutería premium. | P87: Depende del grupo | R87: +593-98-269-5330 chaupiestanciawinery@hotmail.com Instagram @chaupiestancia_winery
A88: 087 | B88: ACTIVO | C88: =CONCATENATE(VLOOKUP($D88,CODIFICACIÓN_DPA!$A$2:$B$66,2,FALSE),VLOOKUP($G88,CODIFICACIÓN_DPA!$D$2:$E$6,2,FALSE),CONCATENATE(VLOOKUP($E88,CODIFICACIÓN_DPA!$G$2:$H$3,2,FALSE),VLOOKUP($F88,CODIFICACIÓN_DPA!$J$2:$K$10,2,FALSE)),A88) -> 170155CU0209087 | D88: CALDERÓN | E88: RURAL | F88: Calderón | G88: CULTURAL | H88: Bordados de Llano Grande | I88: Bordados de Llano Grande preserva el arte textil Kitu-Kara en piezas donde cada puntada narra memoria y territorio: colores vibrantes recrean flora nativa, aves y símbolos ancestrales, mientras diseños contemporáneos dialogan con técnicas transmitidas por generaciones. La experiencia revela un oficio que embellece prendas y textiles a la vez que fortalece identidad, cohesión comunitaria y economía local, convirtiendo cada bordado en un manifiesto vivo de patrimonio y creatividad. | J88: Calderón, Llano Grande | K88: -0.079417048 | L88: -78.432069 | M88: 1 hora | R88: Veronica Montesdeoca 0984556934
A89: 088 | B89: ACTIVO | C89: =CONCATENATE(VLOOKUP($D89,CODIFICACIÓN_DPA!$A$2:$B$66,2,FALSE),VLOOKUP($G89,CODIFICACIÓN_DPA!$D$2:$E$6,2,FALSE),CONCATENATE(VLOOKUP($E89,CODIFICACIÓN_DPA!$G$2:$H$3,2,FALSE),VLOOKUP($F89,CODIFICACIÓN_DPA!$J$2:$K$10,2,FALSE)),A89) -> 170185GA0208088 | D89: YARUQUÍ | E89: RURAL | F89: Valle de Tumbaco | G89: GASTRONÓMICO | H89: Andean Agave (Chawar) | I89: Allí se brinda chawar mishki, una bebida de los dioses, ancestral y medicinal cuya materia prima se utiliza para el proceso del destilado. Asimismo, en este lugar podrás apreciar los cultivos del agave y ser parte de un recorrido explicativo por la destilería, al tiempo que podrás conocer el procesamiento del chawar mishki, acompañado de una degustación. | J89: Calles Luis Pallares y Quito | K89: -0.16460663 | L89: -78.327207 | M89: 0.1875 | N89: Bajo reserva | P89: Aforo límitado, bajo inscripción | Q89: No menores de edad | R89: https://www.facebook.com/andeanagave/about
A90: 089 | B90: ACTIVO | C90: =CONCATENATE(VLOOKUP($D90,CODIFICACIÓN_DPA!$A$2:$B$66,2,FALSE),VLOOKUP($G90,CODIFICACIÓN_DPA!$D$2:$E$6,2,FALSE),CONCATENATE(VLOOKUP($E90,CODIFICACIÓN_DPA!$G$2:$H$3,2,FALSE),VLOOKUP($F90,CODIFICACIÓN_DPA!$J$2:$K$10,2,FALSE)),A90) -> 170123GA0102089 | D90: MARISCAL SUCRE | E90: URBANO | F90: La Mariscal | G90: GASTRONÓMICO | H90: Vermutería Clandestina | I90: Ubicada en el barrio La Floresta, Vermutería Clandestina es el primer bar especializado en vermouth en Ecuador, un espacio diseñado para celebrar esta bebida con alma local. Aquí se elaboran vermuts únicos a partir de botánicos ecuatorianos, combinando creatividad con tradición y sabor autóctono. Los visitantes pueden disfrutar degustaciones guiadas, maridajes con tapas y tablas de embutidos, además de un ambiente cálido y sofisticado que invita a relajarse y conversar. Durante las noches, la música y la estética íntima transforman el lugar en un refugio perfecto para quienes buscan una experiencia distinta dentro de la vida nocturna quiteña. | J90: Calle Pontevedra y Francisco Salazar. | K90: -0.20741778 | L90: -78.482698 | M90: 0.03125 | N90: Bajo reserva | P90: Bajo reserva | Q90: No menores de edad | R90: Cecilia Carolina Quijano Tel: 0969067981 https://www.instagram.com/la_vermuteria_clandestina/?igsh=MTR1djFhNXhseGoxNg%3D%3D
A91: 090 | B91: ACTIVO | C91: =CONCATENATE(VLOOKUP($D91,CODIFICACIÓN_DPA!$A$2:$B$66,2,FALSE),VLOOKUP($G91,CODIFICACIÓN_DPA!$D$2:$E$6,2,FALSE),CONCATENATE(VLOOKUP($E91,CODIFICACIÓN_DPA!$G$2:$H$3,2,FALSE),VLOOKUP($F91,CODIFICACIÓN_DPA!$J$2:$K$10,2,FALSE)),A91) -> 170103GA0101090 | D91: CENTRO HISTÓRICO | E91: URBANO | F91: Centro Histórico | G91: GASTRONÓMICO | H91: Leña Quiteña | I91: Leña Quiteña celebra la cocina ecuatoriana con una propuesta que rinde homenaje a los sabores de antaño, preparados con técnicas modernas y el inconfundible toque del fuego de leña. Cada plato es una reinterpretación de la gastronomía quiteña y nacional, donde los ingredientes locales cobran protagonismo y se transforman en una experiencia culinaria llena de aroma, textura y autenticidad. El ambiente del restaurante combina elegancia y calidez, invitando a disfrutar de una comida que conecta la tradición con la innovación. Ya sea para un almuerzo entre amigos o una cena especial, Leña Quiteña ofrece una experiencia gastronómica que despierta los sentidos y resalta lo mejor del patrimonio culinario ecuatoriano. | J91: Calle Guayaquil S1-76 Calle de la Ronda, Morales | K91: -0.22415342 | L91: -78.513673 | M91: 1 hora | N91: Bajo reserva | P91: Depende del grupo | R91: Patricia 09888033084 https://www.instagram.com/lena_quitena/
A92: 091 | B92: ACTIVO | C92: =CONCATENATE(VLOOKUP($D92,CODIFICACIÓN_DPA!$A$2:$B$66,2,FALSE),VLOOKUP($G92,CODIFICACIÓN_DPA!$D$2:$E$6,2,FALSE),CONCATENATE(VLOOKUP($E92,CODIFICACIÓN_DPA!$G$2:$H$3,2,FALSE),VLOOKUP($F92,CODIFICACIÓN_DPA!$J$2:$K$10,2,FALSE)),A92) -> 170154GA0205091 | D92: CALACALÍ | E92: RURAL | F92: Chocó Andino | G92: GASTRONÓMICO | H92: El Patio Organic Tradicional Food | I92: El Patio Organic Tradicional Food ofrece una experiencia culinaria única en la que los comensales, con los ojos vendados, descubren cómo se adaptan las personas no videntes en su vida diaria. Con guías que orientan y platos de material resistente, el restaurante transforma el desafío de comer a ciegas en una lección de empatía. La comida, elaborada con ingredientes del huerto local, se sirve en un formato innovador y solo se puede disfrutar con reserva previa, preservando la frescura. Tras la comida, el chef explica los ingredientes, cerrando una experiencia que fomenta la tolerancia y la reflexión. | J92: Calacalí, Bolivar N5 - 86 y Miranda | K92: 0.0035267853 | L92: -78.514608 | M92: 1 hora | N92: Bajo reserva | P92: Depende del grupo | R92: Alfredo Guamaní 0983749723 https://www.facebook.com/elpatioecorestaurante/?locale=es_LA
A93: 092 | B93: ACTIVO | C93: =CONCATENATE(VLOOKUP($D93,CODIFICACIÓN_DPA!$A$2:$B$66,2,FALSE),VLOOKUP($G93,CODIFICACIÓN_DPA!$D$2:$E$6,2,FALSE),CONCATENATE(VLOOKUP($E93,CODIFICACIÓN_DPA!$G$2:$H$3,2,FALSE),VLOOKUP($F93,CODIFICACIÓN_DPA!$J$2:$K$10,2,FALSE)),A93) -> 170112GA0103092 | D93: IÑAQUITO | E93: URBANO | F93: Centro Norte | G93: GASTRONÓMICO | H93: Papa Cacao | I93: Papá Cacao representa un legado viviente del chocolate ecuatoriano. Fundación, investigación y formación se unen en su misión de valorar las raíces del cacao nacional y empoderar a nuevos productores. Bajo su visión, se desarrollan programas educativos, diplomados y experiencias inmersivas que revelan el arte de transformar el grano en exquisitez. Al visitarlo, los amantes del chocolate pueden conocer de cerca el trabajo con variedades aromáticas, procesos de fermentación y secado, y participar en degustaciones que elevan la experiencia sensorial. Papá Cacao no solo celebra el sabor, sino que cultiva conocimiento, comunidad y sostenibilidad, reafirmando por qué Ecuador es cuna de cacao de clase mundial. | J93: Av. 10 de Agosto N36-174 | K93: -0.17539565 | L93: -78.488042 | M93: 1 hora | N93: Bajo reserva | P93: Depende del grupo | R93: https://www.facebook.com/escueladenegocioscacaoychocolate/?locale=es_LA
A94: 093 | B94: ACTIVO | C94: =CONCATENATE(VLOOKUP($D94,CODIFICACIÓN_DPA!$A$2:$B$66,2,FALSE),VLOOKUP($G94,CODIFICACIÓN_DPA!$D$2:$E$6,2,FALSE),CONCATENATE(VLOOKUP($E94,CODIFICACIÓN_DPA!$G$2:$H$3,2,FALSE),VLOOKUP($F94,CODIFICACIÓN_DPA!$J$2:$K$10,2,FALSE)),A94) -> 170123GA0102093 | D94: MARISCAL SUCRE | E94: URBANO | F94: La Mariscal | G94: GASTRONÓMICO | H94: La Roveta - Cafería | I94: Roveta Cafetería ofrece una experiencia gastronómica encantadora, en un ambiente acogedor que combina arquitectura contemporánea, luz natural y detalles de diseño cálido. Su menú destaca por opciones deliciosas y creativas, desde cafés artesanales de origen hasta pasteles frescos y elaborados con esmero, ideales para acompañar una conversación o una pausa inspiradora. Más que una cafetería, Roveta es un espacio donde se vive el café como una experiencia sensorial: cada taza es el resultado de un proceso cuidadoso, desde el grano hasta el aroma final. Ideal para quienes buscan calidad, confort y autenticidad en cada bocado, este rincón se ha convertido en un imprescindible para los amantes del buen café y los espacios con alma. | J94: J.L. Tamayo, y N24-359 | K94: -0.20501765 | L94: -78.486598 | M94: 1 hora | N94: Bajo reserva | R94: 099 595 6712 https://www.facebook.com/p/Roveta-100077302664491/?locale=es_LA
A95: 094 | B95: ACTIVO | C95: =CONCATENATE(VLOOKUP($D95,CODIFICACIÓN_DPA!$A$2:$B$66,2,FALSE),VLOOKUP($G95,CODIFICACIÓN_DPA!$D$2:$E$6,2,FALSE),CONCATENATE(VLOOKUP($E95,CODIFICACIÓN_DPA!$G$2:$H$3,2,FALSE),VLOOKUP($F95,CODIFICACIÓN_DPA!$J$2:$K$10,2,FALSE)),A95) -> 170130GA0101094 | D95: SAN JUAN | E95: URBANO | F95: Centro Histórico | G95: GASTRONÓMICO | H95: Runa Tulpa Andina | I95: Runa Tulpa Andina es un espacio de encuentro donde los sabores, las historias y la calidez humana se entrelazan alrededor del fuego. Inspirado en la tradicional “tulpa” andina —el fogón que reúne a las familias para compartir alimentos y relatos—, este restaurante invita a revivir la esencia del compartir, la memoria y la conexión con la tierra. Más que una experiencia gastronómica, Runa Tulpa Andina promueve un lazo directo con productores locales y agroecológicos de las comunidades cercanas a Quito, valorando los ingredientes que nacen de la sostenibilidad y el respeto por la naturaleza. Cada plato es una expresión de identidad, un gesto de hospitalidad y una celebración del fuego que une a todos. | J95: García Moreno N7-68 y Manabí. | K95: -0.21678895 | L95: -78.510544 | N95: Bajo reserva | P95: Depende del grupo | R95: 096 254 6392 https://runatulpaandina.com/menu/
A96: 095 | B96: ACTIVO | C96: =CONCATENATE(VLOOKUP($D96,CODIFICACIÓN_DPA!$A$2:$B$66,2,FALSE),VLOOKUP($G96,CODIFICACIÓN_DPA!$D$2:$E$6,2,FALSE),CONCATENATE(VLOOKUP($E96,CODIFICACIÓN_DPA!$G$2:$H$3,2,FALSE),VLOOKUP($F96,CODIFICACIÓN_DPA!$J$2:$K$10,2,FALSE)),A96) -> 170130GA0101095 | D96: SAN JUAN | E96: URBANO | F96: Centro Histórico | G96: GASTRONÓMICO | H96: X lo Alto | I96: En el corazón del Centro Histórico, X lo Alto eleva la experiencia culinaria con una propuesta que fusiona platos innovadores y sabores intensos, inspirados en la riqueza gastronómica del Ecuador. Su atmósfera elegante, el servicio atento y las vistas panorámicas de la ciudad crean una velada excepcional que cautiva todos los sentidos. Ideal para quienes buscan disfrutar de la buena comida en un entorno sofisticado, X lo Alto ofrece una experiencia gastronómica única que combina creatividad, calidez y una vista inolvidable de Quito. ¡Una parada imperdible para los amantes del sabor y la altura! | J96: Montevideo Oe-648 y Panamá | K96: -0.20971955 | L96: -78.508384 | N96: Bajo reserva | R96: 098 712 2205 https://www.facebook.com/p/X-LO-ALTO-100061845891879/?locale=hi_IN
A97: 096 | B97: ACTIVO | C97: =CONCATENATE(VLOOKUP($D97,CODIFICACIÓN_DPA!$A$2:$B$66,2,FALSE),VLOOKUP($G97,CODIFICACIÓN_DPA!$D$2:$E$6,2,FALSE),CONCATENATE(VLOOKUP($E97,CODIFICACIÓN_DPA!$G$2:$H$3,2,FALSE),VLOOKUP($F97,CODIFICACIÓN_DPA!$J$2:$K$10,2,FALSE)),A97) -> 170154CU0204096 | D97: CALACALÍ | E97: RURAL | F97: Parroquias Equinocciales | G97: CULTURAL | H97: Templo del sol | I97: La experiencia en el Museo Templo El Sol nos lleva por experiencias sensoriales de aromas, pintura, escultura, vino y chocolate. Los aromas exquisitos se combinan con el ambiente místico en el Templo del Sol y de la Luna mientras exploras el legado cultural del lugar. | J97: En el Mirador de la reserva geobotanica pululahua Manuel Córdova Galarza E28 y, Eduardo Kingman Oe12 174 | K97: 0.026571812 | L97: -78.488143 | M97: 2 horas | N97: Abierto al público. Lunes a Domingos y Feriados de 9:00am a 17:00pm | O97: Adultos y extranjeros $4. Niños y adulto mayor $2 | P97: Se puede planificar la visita para grupos | R97: 098 484 1851 Cristobal Ortega https://www.facebook.com/MuseoTemplodelSolOficial/
A98: 097 | B98: ACTIVO | C98: =CONCATENATE(VLOOKUP($D98,CODIFICACIÓN_DPA!$A$2:$B$66,2,FALSE),VLOOKUP($G98,CODIFICACIÓN_DPA!$D$2:$E$6,2,FALSE),CONCATENATE(VLOOKUP($E98,CODIFICACIÓN_DPA!$G$2:$H$3,2,FALSE),VLOOKUP($F98,CODIFICACIÓN_DPA!$J$2:$K$10,2,FALSE)),A98) -> 170123CU0102097 | D98: MARISCAL SUCRE | E98: URBANO | F98: La Mariscal | G98: CULTURAL | H98: Centro de artesanías Pimkay | I98: La tienda de artesanías Pincay es un verdadero tesoro de creatividad y tradición. Cada pieza refleja un trabajo meticuloso y auténtico, con una variedad impresionante de artesanías locales. El ambiente acogedor y el servicio amable hacen que cada visita sea una experiencia encantadora. ¡Perfecto para encontrar recuerdos únicos y apoyar el talento artesanal! | J98: Jerónimo Carrión E6 - 43 y Reina Victoria | K98: -0.20436612 | L98: -78.493335 | N98: Abierto al público | R98: 25133888 https://www.instagram.com/pimkay_ec/?hl=es
A99: 098 | B99: ACTIVO | C99: =CONCATENATE(VLOOKUP($D99,CODIFICACIÓN_DPA!$A$2:$B$66,2,FALSE),VLOOKUP($G99,CODIFICACIÓN_DPA!$D$2:$E$6,2,FALSE),CONCATENATE(VLOOKUP($E99,CODIFICACIÓN_DPA!$G$2:$H$3,2,FALSE),VLOOKUP($F99,CODIFICACIÓN_DPA!$J$2:$K$10,2,FALSE)),A99) -> 170155CU0209098 | D99: CALDERÓN | E99: RURAL | F99: Calderón | G99: CULTURAL | H99: Kitu Samay Wasi | I99: Kitu Samay Wasi integra saberes ancestrales y creación contemporánea en una experiencia pedagógica viva, donde talleres interactivos acercan a niñas y niños a su historia cultural de la mano de abuelos y abuelas—guardianes de la memoria—que comparten relatos, cantos y oficios. El resultado es un encuentro inspirador que fortalece identidad, despierta creatividad y convierte el patrimonio en aprendizaje significativo, cálido y memorable. | J99: Llano Grande | K99: -0.12404119 | L99: -78.424962 | N99: Bajo reserva | P99: Se puede planificar la visita para grupos | R99: Yarina 096383 6930 https://www.facebook.com/kitusamaywasi/?locale=es_LA
A100: 099 | B100: ACTIVO | C100: =CONCATENATE(VLOOKUP($D100,CODIFICACIÓN_DPA!$A$2:$B$66,2,FALSE),VLOOKUP($G100,CODIFICACIÓN_DPA!$D$2:$E$6,2,FALSE),CONCATENATE(VLOOKUP($E100,CODIFICACIÓN_DPA!$G$2:$H$3,2,FALSE),VLOOKUP($F100,CODIFICACIÓN_DPA!$J$2:$K$10,2,FALSE)),A100) -> 170123CU0102099 | D100: MARISCAL SUCRE | E100: URBANO | F100: La Mariscal | G100: CULTURAL | H100: Galeria de Arte Naif | I100: La Galería de Arte Naif, destaca por su enfoque en el arte latinoamericano. Con un museo dedicado al estilo naif, exposiciones temporales diversas y talleres en desarrollo, busca inspirar a los jóvenes y fomentar un amor duradero por el arte. ¡Un espacio vibrante y educativo! | J100: Av. 6 de diciembre N24-275 y Calle San Juan Rodríguez | K100: -0.20318975 | L100: -78.488759 | R100: Wilson Salas 099 213 9258 https://www.facebook.com/p/MANLA-Museo-de-Arte-Naif-Latinoamericano-100070070290314/
...
