Workbook

Sheet ESTRUCTURA CÓDIGO RUTA
A1: FICHA PARA EL LEVANTAMIENTO DE ATRACTIVOS TURÍSTICOS
A3: CÓDIGO DE LA RUTA TURÍSTICA
A5: El código, está compuesto por 09 dígitos (caracteres alfanuméricos), únicos e irrepetibles, mismo que aparecerá al inicio de la ficha para su identificación.
A7: 1. Clasificación de rutas turísticas (Nodo), (ver documento Centralidades - Nodos Turísticos Complementarios Urbanos y Rurales, 2024).
A8: 2. Se colocará la letra inicial de las dos primeras palabras que componen el nombre de la ruta ejemplo: Ruta Miradores codificación "RM"
A9: 3. Clasificación de rutas turísticas (Centralidad), (ver documento Centralidades - Nodos Turísticos Complementarios Urbanos y Rurales, 2024).
A10: 4. FInalmente; los tres dígitos finales corresponden al orden en que se levante la información de las rutas turísticas que iniciará desde 001.
A16: FUENTE: Manual Metodología para Jerarquización de Atractivos y Generación de Espacios Turísticos, MINTUR 2017.
A17: Centralidades - Nodos Turísticos Complementarios Urbanos y Rurales, QUITO TURISMO 2024.

Sheet CODIFICACIÓN_RUTA
B1: NODO_DESCRP | C1: COD_NODO | E1: CENTRALIDAD_DESCRIP | F1: COD_CENTRALIDAD | H1: ESTADO DEL ATRACTIVO
B2: URBANO | C2: 01 | E2: Centro Histórico | F2: 01 | H2: ACTIVO
B3: RURAL | C3: 02 | E3: La Mariscal | F3: 02 | H3: INACTIVO
E4: Centro Norte | F4: 03
E5: Parroquias Equinocciales | F5: 04
E6: Chocó Andino | F6: 05
E7: Ruta Escondida | F7: 06
E8: Valle de los Chillos | F8: 07
E9: Valle de Tumbaco | F9: 08
E10: Calderón | F10: 09
B17: CÓDIGO RUTA QT
B18: 01RM01002
B20: NODO | C20: NOMBRE DE LA RUTA TURÍSTICA | D20: CENTRALIDAD | E20: ORDEN EN LISTADO
B21: 01 | C21: RM | D21: 01 | E21: 002
B22: URBANO | C22: RUTA MIRADORES | D22: Centro Histórico | E22: 002

Sheet RUTAS
A1: N° | B1: ESTADO | C1: CÓDIGO QT | D1: NODO | E1: CENTRALIDAD | F1: NOMBRE DE LA RUTA TURÍSTICA | G1: CLASIFICACIÓN | H1: BREVE DESCRIPCIÓN | I1: MODALIDAD | J1: TIEMPO DE DURACIÓN DE RUTA (horas) | K1: DISTANCIA (Km) | L1: ALTITUD (m.s.n.m) | M1: DIFICULTAD | N1: LINK DE RUTA | O1: NOMBRE DEL ATRACTIVO / RECURSO ASOCIADO A LA RUTA 1 | P1: NOMBRE DEL ATRACTIVO / RECURSO ASOCIADO A LA RUTA 2 | Q1: NOMBRE DEL ATRACTIVO / RECURSO ASOCIADO A LA RUTA 3 | R1: NOMBRE DEL ATRACTIVO / RECURSO ASOCIADO A LA RUTA 4 | S1: NOMBRE DEL ATRACTIVO / RECURSO ASOCIADO A LA RUTA 5 | T1: NOMBRE DEL ATRACTIVO / RECURSO ASOCIADO A LA RUTA 6 | U1: NOMBRE DEL ATRACTIVO / RECURSO ASOCIADO A LA RUTA 7 | V1: NOMBRE DEL ATRACTIVO / RECURSO ASOCIADO A LA RUTA 8 | W1: NOMBRE DEL ATRACTIVO / RECURSO ASOCIADO A LA RUTA 9 | X1: NOMBRE DEL ATRACTIVO / RECURSO ASOCIADO A LA RUTA 10 | Y1: ESTABLECIMIENTO A&B | Z1: OBSERVACIÓN DE INACTIVACIÓN
A2: 001 | B2: ACTIVO | C2: =CONCATENATE(VLOOKUP($D2,CODIFICACIÓN_RUTA!$B$2:$C$3,2,0),MID($F2,1,1)&MID($F2,6,1),VLOOKUP($E2,CODIFICACIÓN_RUTA!$E$2:$F$10,2,0),$A2) -> 01RD01001 | D2: URBANO | E2: Centro Histórico | F2: RUTA DE LAS 7 CRUCES | G2: RUTAS CONSOLIDADAS | H2: Esta ruta se realiza en el Centro Histórico | I2: Cultural | J2: 1 | K2: 1.2 KM | L2: 2830 | M2: BAJA | N2: https://www.google.com/maps/d/u/0/edit?mid=1RjWO7kyHX4EsnPZu0Ll1cRFgkG4ECsI&usp=sharing | O2: Museo de la Ciudad | P2: Museo del Carmen Alto | Q2: Casa Museo María Augusta Urrutia | R2: Museo Numismático del Banco Central | S2: Iglesia Compañía de Jesús | T2: Centro Cultural Metropolitano | U2: Iglesia El Sagrario | V2: Catedral Metropolitana de Quito | W2: Iglesia Inmaculada Concepción
A3: 002 | B3: ACTIVO | C3: =CONCATENATE(VLOOKUP($D3,CODIFICACIÓN_RUTA!$B$2:$C$3,2,0),MID($F3,1,1)&MID($F3,6,1),VLOOKUP($E3,CODIFICACIÓN_RUTA!$E$2:$F$10,2,0),$A3) -> 01RM01002 | D3: URBANO | E3: Centro Histórico | F3: RUTA MIRADORES | G3: RUTAS CON POTENCIAL | H3: Se podrá disfrutar de los distintos miradores que posee la ciudad de Quito, junto con Quito Tour Bus | I3: Natural | J3: 5 | K3: 17 KM | L3: 3100 | M3: BAJA | N3: https://www.google.com/maps/d/edit?mid=1upWwdyGKcSFM8yEOjftREmBG9ap95MI&usp=sharing | O3: Basílica del Voto Nacional | P3: Museo del agua YAKU | Q3: Centro Cultural Itchimbía | R3: Museo Templo de la Patria | S3: Monumento Virgen de El Panecillo
A4: 003 | B4: ACTIVO | C4: =CONCATENATE(VLOOKUP($D4,CODIFICACIÓN_RUTA!$B$2:$C$3,2,0),MID($F4,1,1)&MID($F4,6,1),VLOOKUP($E4,CODIFICACIÓN_RUTA!$E$2:$F$10,2,0),$A4) -> 01RA03003 | D4: URBANO | E4: CENTRO NORTE | F4: RUTA ARQUEOLÓGICA | G4: RUTAS CON POTENCIAL | H4: Conocer sobre las culturas y habitantes antiguos de Quito. | I4: Histórica | J4: 5 | K4: 23 KM | L4: 2800 | M4: BAJA | N4: https://www.google.com/maps/d/edit?mid=1UIGgFhBe6Z3u0nI8BmeggIxUUrbLpbQ&usp=drive_link | O4: Museo de Sitio La Florida | P4: Parque Arqueológico y Ecológico Rumipamba | Y4: SANTHORNO
A5: 004 | B5: ACTIVO | C5: =CONCATENATE(VLOOKUP($D5,CODIFICACIÓN_RUTA!$B$2:$C$3,2,0),MID($F5,1,1)&MID($F5,6,1),VLOOKUP($E5,CODIFICACIÓN_RUTA!$E$2:$F$10,2,0),$A5) -> 01RD02004 | D5: URBANO | E5: La Mariscal | F5: RUTA DE LA PALABRA | G5: RUTAS CON POTENCIAL | H5: Nos permite conocer la Plaza de los Presidentes, la Iglesia de Santa Teresita, la Casa de Camilo Ponce Enríquez, el palacete González Artigas, el Centro Cultural Benjamín Carrión, el Patio de Comedias y el espacio sociocultural Buenaventura. | I5: Cultural | J5: 3 | K5: 1.5 KM | L5: 2850 | M5: BAJA | N5: https://www.google.com/maps/d/edit?mid=11FnWDoB3rJsva7gtAKabLoeJWKLEJpI&usp=drive_link | O5: Iglesia de Santa Teresita | P5: Centro Cultural Benjamín Carrión | Q5: Museo MUNA Ecuador
A6: 005 | B6: ACTIVO | C6: =CONCATENATE(VLOOKUP($D6,CODIFICACIÓN_RUTA!$B$2:$C$3,2,0),MID($F6,1,1)&MID($F6,6,1),VLOOKUP($E6,CODIFICACIÓN_RUTA!$E$2:$F$10,2,0),$A6) -> 01RC01005 | D6: URBANO | E6: Centro Histórico | F6: RUTA CHOCOLATE ENTRE CÚPULAS Y TORRES | G6: RUTAS CONSOLIDADAS | H6: Se podran disfrutar de las cúpulas de la Basílica del Voto Nacional y la Iglesia de La Compañia además de una cata de chocolate fino. | I6: Gastronómica | J6: 4 | K6: 1 KM | L6: 2820 | M6: BAJA | N6: https://www.google.com/maps/d/edit?mid=18vd0Hx6XK01LFkorLhnokI_vDp3EeM0&usp=drive_link | O6: Basílica del Voto Nacional | P6: Iglesia Compañía de Jesús | Q6: Catedral Metropolitana de Quito | Y6: CHOCOLATE CHEZ TIFF
A7: 006 | B7: ACTIVO | C7: =CONCATENATE(VLOOKUP($D7,CODIFICACIÓN_RUTA!$B$2:$C$3,2,0),MID($F7,1,1)&MID($F7,6,1),VLOOKUP($E7,CODIFICACIÓN_RUTA!$E$2:$F$10,2,0),$A7) -> 01RR01006 | D7: URBANO | E7: Centro Histórico | F7: RUTA ROMANCE Y LIBERTADORES | G7: RUTAS CON POTENCIAL | H7: Disfrutaremos de mano de los libertadores las historias de amores,política del Quito revolucionario. | I7: Cultural | J7: 3 | K7: 0.77 KM | L7: 2850 | M7: BAJA | N7: https://www.google.com/maps/d/edit?mid=1BmEgyZffuOaFNfpA9kjukiV5BAmn6aY&usp=drive_link | O7: Convento de San Francisco | P7: Iglesia Compañía de Jesús | Q7: Centro Cultural Metropolitano | R7: Catedral Metropolitana de Quito | Y7: HELADERIA DE SAN AGUSTIN
A8: 007 | B8: ACTIVO | C8: =CONCATENATE(VLOOKUP($D8,CODIFICACIÓN_RUTA!$B$2:$C$3,2,0),MID($F8,1,1)&MID($F8,6,1),VLOOKUP($E8,CODIFICACIÓN_RUTA!$E$2:$F$10,2,0),$A8) -> 01RD01007 | D8: URBANO | E8: Centro Histórico | F8: RUTA DE OFICIOS Y PERSONAJES QUITEÑOS | G8: RUTAS POR FORTALECER | H8: Conocermos sobre los nobles oficios que todavián prevalecen en la ciudad capitalina. | I8: Histórica | J8: 4 | K8: 2.7 KM | L8: 2825 | M8: BAJA | N8: https://www.google.com/maps/d/edit?mid=1gfoDaWH4tRywZ4FAAwdlp2C5sJAAxi0&usp=sharing | O8: Museo Casa Manuela Sáenz | P8: Museo Fray Pedro Bedón | Y8: CASA 925
A9: 008 | B9: ACTIVO | C9: =CONCATENATE(VLOOKUP($D9,CODIFICACIÓN_RUTA!$B$2:$C$3,2,0),MID($F9,1,1)&MID($F9,6,1),VLOOKUP($E9,CODIFICACIÓN_RUTA!$E$2:$F$10,2,0),$A9) -> 01RC01008 | D9: URBANO | E9: Centro Histórico | F9: RUTA CÚPULAS Y TORRES | G9: RUTAS CONSOLIDADAS | H9: Se podran disfrutar de las cúpulas de la Basílica del Voto Nacional y la Iglesia de La Compañia además de una cata de chocolate fino. | I9: Cultural | J9: 4 | K9: 1.6 KM | L9: 2850 | M9: BAJA | N9: https://www.google.com/maps/d/edit?mid=1m291Fej0LC17aa9Mrk7SeyOr76wGXe0&usp=sharing | O9: Basílica del Voto Nacional | P9: Catedral Metropolitana de Quito | Q9: Museo Fray Pedro Bedón | Y9: CASA925
A10: 009 | B10: ACTIVO | C10: =CONCATENATE(VLOOKUP($D10,CODIFICACIÓN_RUTA!$B$2:$C$3,2,0),MID($F10,1,1)&MID($F10,6,1),VLOOKUP($E10,CODIFICACIÓN_RUTA!$E$2:$F$10,2,0),$A10) -> 01RP01009 | D10: URBANO | E10: Centro Histórico | F10: RUTA PLAZAS Y MONUMENTOS | G10: RUTAS POR FORTALECER | H10: Visitaremos y aprenderemos sobre las plazas y monumentos que habitan en el Centro Histórico. (Plaza del Teatro- Plaza Huerto San Agustín - Plaza de la Independencia – Plazoleta Gonzáles Suárez - Plaza Santa Domingo – Plaza Santa Clara- Plaza San Francisco) | I10: Cultural | J10: 4 | K10: 2.4 KM | L10: 2830 | M10: BAJA | N10: https://www.google.com/maps/d/edit?mid=1zcXCzE4agYintmlQhUJoTZ62eKDYP14&usp=sharing | O10: Convento de San Agustín | P10: Teatro Sucre | Q10: Catedral Metropolitana de Quito | R10: Convento de Santo Domingo | S10: Iglesia de Santa Clara | T10: Convento de San Francisco
A11: 010 | B11: ACTIVO | C11: =CONCATENATE(VLOOKUP($D11,CODIFICACIÓN_RUTA!$B$2:$C$3,2,0),MID($F11,1,1)&MID($F11,6,1),VLOOKUP($E11,CODIFICACIÓN_RUTA!$E$2:$F$10,2,0),$A11) -> 01SA01010 | D11: URBANO | E11: Centro Histórico | F11: SAN MARCOS – ARTE PATRIMONIO Y CULTURA | G11: RUTAS CON POTENCIAL | H11: Disfrutaremos de este barrio emblématico de Quito y conoceremos el arte que habita en él. | I11: Cultural | J11: 4 | K11: 2.4 KM | L11: 2830 | M11: BAJA | N11: https://www.google.com/maps/d/edit?mid=13MkAa7jCO5tg1sZbr4478dbRaWSGyHc&usp=sharing | O11: Museo Casa Manuela Sáenz | P11: Museo Muñoz Mariño | Q11: Museo de Arquitectura | R11: Iglesia de San Marcos
A12: 011 | B12: ACTIVO | C12: =CONCATENATE(VLOOKUP($D12,CODIFICACIÓN_RUTA!$B$2:$C$3,2,0),MID($F12,1,1)&MID($F12,6,1),VLOOKUP($E12,CODIFICACIÓN_RUTA!$E$2:$F$10,2,0),$A12) -> 01RC01011 | D12: URBANO | E12: Centro Histórico | F12: RUTA CITY TOUR CIUDAD DE QUITO | G12: RUTAS CON POTENCIAL | H12: Contemplaremos nuestra carita de Dios, mientras aprendemos sobre sus monumentos, historias, tradiciones. | I12: Cultural | J12: 4 | K12: 1.25 KM | L12: 2850 | M12: BAJA | N12: https://www.google.com/maps/d/edit?mid=11MgTI4xtbGHxjnoLXYtJbs9e9OdW_QQ&usp=sharing | O12: Catedral Metropolitana de Quito | P12: Centro Cultural Metropolitano | Q12: Iglesia Compañía de Jesús | R12: Convento de San Francisco | S12: Monumento Virgen de El Panecillo | Y12: Casa 925
A13: 012 | B13: ACTIVO | C13: =CONCATENATE(VLOOKUP($D13,CODIFICACIÓN_RUTA!$B$2:$C$3,2,0),MID($F13,1,1)&MID($F13,6,1),VLOOKUP($E13,CODIFICACIÓN_RUTA!$E$2:$F$10,2,0),$A13) -> 02RE04012 | D13: RURAL | E13: Parroquias Equinocciales | F13: RUTA EQUINOCCIAL ANCESTRAL Y CULTURAL | G13: RUTAS CONSOLIDADAS | H13: El objetivo de esta ruta es vincular propuestas culturales de la Parroquias rurales de Pomasqui, San Antonio de Pichincha y Calacalí. | I13: Histórica | J13: 9 | K13: 16.5 KM | L13: 2800 | M13: BAJA | N13: https://www.google.com/maps/d/u/0/edit?mid=1hLFaHdE51z9g8iAhOcMvKGespI-utM8&usp=sharing | O13: Chucchurillos Ñaupa Ayllu Manta | P13: Puracá de Rumicucho | Q13: Casa Museo Carlota Jaramillo | Y13: EL PATIO ORGANIC TRADICIONAL FOOD
A14: 013 | B14: ACTIVO | C14: =CONCATENATE(VLOOKUP($D14,CODIFICACIÓN_RUTA!$B$2:$C$3,2,0),MID($F14,1,1)&MID($F14,6,1),VLOOKUP($E14,CODIFICACIÓN_RUTA!$E$2:$F$10,2,0),$A14) -> 02RC07013 | D14: RURAL | E14: VALLE DE LOS CHILLOS | F14: RUTA CHAKANA - EN BUSCA DEL CÓNDOR ANDINO Y EL OSO DE ANTEOJOS | G14: RUTAS CONSOLIDADAS | H14: El objetivo de esta ruta es poder conocer distintos lugares y sus miradoes donde se puede avistar al cóndor andino, venados de cola blanca y oso de anteojos. | I14: CAVE | J14: 10 | K14: 46 KM | L14: 2830 | M14: BAJA | N14: https://www.google.com/maps/d/edit?mid=1WfFDmpjbXAMjNtlV6xomg4tkf6LlDDQ&usp=drive_link | O14: Chakana - Antisanilla Peñón del Isco | P14: Laguna de Secas | Y14: Chakana Tambo Cóndor
A15: 014 | B15: ACTIVO | C15: =CONCATENATE(VLOOKUP($D15,CODIFICACIÓN_RUTA!$B$2:$C$3,2,0),MID($F15,1,1)&MID($F15,6,1),VLOOKUP($E15,CODIFICACIÓN_RUTA!$E$2:$F$10,2,0),$A15) -> 02RE05014 | D15: RURAL | E15: CHOCÓ ANDINO | F15: RUTA EN BUSCA DEL JARDÍN DE COLIBRÍES + GASTRONOMÍA LOCAL (YANACOCHA) | G15: RUTAS CONSOLIDADAS | H15: Es un recorrido donde se podran avistar aves como tangaras y gralarias, se conocera el bosque nublado donde se puede disfrutar del canto de las aves. | I15: CAVE | J15: 7 | K15: 46 KM | L15: 2830 | M15: BAJA | N15: https://www.google.com/maps/d/edit?mid=1yS4As1P4RYZBvsSt5_CfKH8_vd1IABs&usp=drive_link | O15: Yanacocha
A16: 015 | B16: ACTIVO | C16: =CONCATENATE(VLOOKUP($D16,CODIFICACIÓN_RUTA!$B$2:$C$3,2,0),MID($F16,1,1)&MID($F16,6,1),VLOOKUP($E16,CODIFICACIÓN_RUTA!$E$2:$F$10,2,0),$A16) -> 02RE06015 | D16: RURAL | E16: RUTA ESCONDIDA | F16: RUTA ESCONDIDA PUÉLLARO Y PERUCHO PUÉLLARO – PERUCHO | G16: RUTAS CONSOLIDADAS | H16: Se podrá disfrutar de las maravillas escondidas dentro de la Ruta Escondida, su historia, cultura y arquitectura. | I16: Cultural | J16: 8 | K16: 70 KM | L16: 2850 | M16: BAJA | N16: https://www.google.com/maps/d/edit?mid=1CHPVBnxTtTGfGbt5HSeKJizmcw-P6Dc&usp=drive_link | O16: Iglesia de Puéllaro | P16: Cerro La Luz | Q16: Iglesia de Perucho | R16: Museo del Aguacate
A17: 016 | B17: ACTIVO | C17: =CONCATENATE(VLOOKUP($D17,CODIFICACIÓN_RUTA!$B$2:$C$3,2,0),MID($F17,1,1)&MID($F17,6,1),VLOOKUP($E17,CODIFICACIÓN_RUTA!$E$2:$F$10,2,0),$A17) -> 02RM05016 | D17: RURAL | E17: CHOCÓ ANDINO | F17: RUTA MUSEO DE TULIPE – FINCA RUMISITANA | G17: RUTAS POR FORTALECER | H17: El Museo de sitio funciona en los vestigios de un centro ceremonial de los yumbos, en este lugar se puede encontrar estructuras hundidas con muros de piedra relacionadas al agua. Se realizará el “Tour del café con leche” caminata corta a los cultivos de café de altura, el proceso de secado y campos de producción lechera. Se degustará café y como obsequio una bolsa de café producido en la finca. | I17: CAVE | J17: 7 | K17: 101 KM | L17: 1400 | M17: BAJA | N17: https://www.google.com/maps/d/edit?mid=1EJ_ZcmLL5V_YxyTR-DR0v3voFkFu2II&usp=drive_link | O17: Museo de Sitio Tulipe | Y17: FINCA RUMISTINA
A18: 017 | B18: ACTIVO | C18: =CONCATENATE(VLOOKUP($D18,CODIFICACIÓN_RUTA!$B$2:$C$3,2,0),MID($F18,1,1)&MID($F18,6,1),VLOOKUP($E18,CODIFICACIÓN_RUTA!$E$2:$F$10,2,0),$A18) -> 02RD09017 | D18: RURAL | E18: Calderón | F18: RUTA DE LOS BORDADOS Y HUERTOS | G18: RUTAS CONSOLIDADAS | H18: Visitaremos diversos huertos de Llano Grande para conocer sobre las tradiciones del pueblo Kitu Kara. | I18: Cultural | J18: 8 | K18: 70 KM | L18: 2850 | M18: BAJA | N18: https://www.google.com/maps/d/edit?mid=1xECrXgFMf3CJLAbbk8RgNNh1g3wbLn8&usp=drive_link | O18: Mindalae | P18: Museo Capilla del Hombre | Q18: Parque Metropolitano Guanguilagua
A19: 018 | B19: ACTIVO | C19: =CONCATENATE(VLOOKUP($D19,CODIFICACIÓN_RUTA!$B$2:$C$3,2,0),MID($F19,1,1)&MID($F19,6,1),VLOOKUP($E19,CODIFICACIÓN_RUTA!$E$2:$F$10,2,0),$A19) -> 02RD04018 | D19: RURAL | E19: PARROQUIAS EQUINOCCIALES | F19: RUTA DESCUBRIENDO EL CENTRO DEL MUNDO | G19: RUTAS CON POTENCIAL | H19: Se puede disfrutar de un recorrido a Calacalí, Museo Carlota Jaramillo, Museo del Intiñan y Casa Agave | I19: Cultural | J19: 6 | K19: 46 KM | L19: 2830 | M19: BAJA | N19: https://www.google.com/maps/d/edit?mid=1JwEH-1fjjFncTMoXKZ9n4RPqfkNPsoY&usp=drive_link | O19: Museo Capilla del Hombre | P19: Museo Templo del Sol | Q19: Museo Intiñan | R19: Casa Agave | S19: Casa Museo Carlota Jaramillo
A20: 019 | B20: ACTIVO | C20: =CONCATENATE(VLOOKUP($D20,CODIFICACIÓN_RUTA!$B$2:$C$3,2,0),MID($F20,1,1)&MID($F20,6,1),VLOOKUP($E20,CODIFICACIÓN_RUTA!$E$2:$F$10,2,0),$A20) -> 02RC04019 | D20: RURAL | E20: PARROQUIAS EQUINOCCIALES | F20: RUTA CENTRO DEL MUNDO | G20: RUTAS CON POTENCIAL | H20: Podremos visitar uno de los templos dedicados al arte y vivir la experiencia de los saberes ancestrales, además de visitar el magestuoso Pululahua y el museo Carlota Jaramillo. | I20: Cultural | J20: 8 | K20: 46 KM | L20: 2830 | M20: BAJA | N20: https://www.google.com/maps/d/edit?mid=1Pc4frukcLLeckLXfd1NipMh4jSDbgTQ&usp=drive_link | O20: Reserva Geobotánica Pululahua | P20: MUSEO TEMPLO DEL SOL | Q20: MUSEO CARLOTA JARAMILLO
A21: 020 | B21: ACTIVO | C21: =CONCATENATE(VLOOKUP($D21,CODIFICACIÓN_RUTA!$B$2:$C$3,2,0),MID($F21,1,1)&MID($F21,6,1),VLOOKUP($E21,CODIFICACIÓN_RUTA!$E$2:$F$10,2,0),$A21) -> 02RC04020 | D21: RURAL | E21: PARROQUIAS EQUINOCCIALES | F21: RUTA CENTRO DEL MUNDO CON EL QUITO TOUR BUS | G21: RUTAS CON POTENCIAL | H21: Podremos visitar la Ciudad Mitad del Mundo y además apreciar el magestuoso Pululahua. | I21: Cultural | J21: 8 | K21: 40 KM | L21: 2800 | M21: BAJA | N21: https://www.google.com/maps/d/viewer?mid=1YAiHbP_szS9lt85Q0ZmVgnBw-uCjr5w&ll=-0.01814251929989333%2C-78.46965506884766&z=13 | O21: Galería Kingman | P21: Alianza Francesa | Q21: Museo Capilla del Hombre | R21: Museo Templo del Sol | S21: RESERVA GEOBOTÁNICA PULULAHUA | Y21: CERVECERÍA SANTA ANA
A22: 021 | B22: ACTIVO | C22: =CONCATENATE(VLOOKUP($D22,CODIFICACIÓN_RUTA!$B$2:$C$3,2,0),MID($F22,1,1)&MID($F22,6,1),VLOOKUP($E22,CODIFICACIÓN_RUTA!$E$2:$F$10,2,0),$A22) -> 02RC04021 | D22: RURAL | E22: Parroquias Equinocciales | F22: RUTA CULUNCO YUNGUILLA | G22: RUTAS POR FORTALECER | H22: Visitaremos la Comunidad e Yunguilla y su ejeompo de Turismo Comunitario, disfrutaremos de una maravillosas caminira donde podremos conocer los caminos pre-incaicos de la cultura Yumbo. | I22: Natural | J22: 7 | K22: 100 KM | L22: 3100 | M22: MEDIA | N22: https://www.google.com/maps/d/edit?mid=1tzpaRD6f6ZlpsAwRWhvkG9oZImX6nqA&usp=drive_link | O22: Museo Templo del Sol | P22: Museo Intiñan | Q22: Casa Museo Carlota Jaramillo | R22: Comunidad de Yunguilla | S22: Culunco Guantopungo
A23: 022 | B23: ACTIVO | C23: =CONCATENATE(VLOOKUP($D23,CODIFICACIÓN_RUTA!$B$2:$C$3,2,0),MID($F23,1,1)&MID($F23,6,1),VLOOKUP($E23,CODIFICACIÓN_RUTA!$E$2:$F$10,2,0),$A23) -> 02RH08022 | D23: RURAL | E23: Valle de Tumbaco | F23: RUTA HISTORIA, FAUNA Y GASTRONOMÍA EL QUINCHE - GUAYLLABAMBA | G23: RUTAS CON POTENCIAL | H23: Podremos disfrutar de esta ruta donde visitaremos el Santuario del Quinche y sus cúpulas, el zoológico de Guayllabamba y la fauna que habita en el. | I23: Cultural | J23: 8 | K23: 50 KM | L23: 2850 | M23: BAJA | N23: https://www.google.com/maps/d/edit?mid=1VDavNZhOfRds6GiNyo--oSyh9VzGP2g&usp=drive_link | O23: Santuario de Nuestra Señora del Quinche | P23: Zoológico de Guayllabamba
A24: 023 | B24: ACTIVO | C24: =CONCATENATE(VLOOKUP($D24,CODIFICACIÓN_RUTA!$B$2:$C$3,2,0),MID($F24,1,1)&MID($F24,6,1),VLOOKUP($E24,CODIFICACIÓN_RUTA!$E$2:$F$10,2,0),$A24) -> 02RM05023 | D24: RURAL | E24: Chocó Andino | F24: RUTA MAQUIPUCUNA | G24: RUTAS POR FORTALECER | H24: Disfrutaremos de esta maravillosa Reserva donde caminaremos por sus diversos senderos y avistaremos fauna endémica del lugar, más su deliciosa gastronomía. | I24: CAVE | J24: 7 | K24: 100 KM | L24: 3100 | M24: MEDIA | N24: https://www.google.com/maps/d/edit?mid=1-CFiq0E6k5sMmjOj7_7qeTo61CAMFCc&usp=drive_link | O24: Casa Museo Carlota Jaramillo | P24: Reserva Orquideologica Pahuma | Q24: Reserva Maquipucuna
A25: 024 | B25: ACTIVO | C25: =CONCATENATE(VLOOKUP($D25,CODIFICACIÓN_RUTA!$B$2:$C$3,2,0),MID($F25,1,1)&MID($F25,6,1),VLOOKUP($E25,CODIFICACIÓN_RUTA!$E$2:$F$10,2,0),$A25) -> 01RM01024 | D25: URBANO | E25: Centro Histórico | F25: RUTA MÚSICA, HISTORIA, TRADICIÓN Y ARTESANOS. | G25: RUTAS CON POTENCIAL | H25: El objetivo de esta ruta es conocer sobre las historias de las calles del Quito Colonial, visitaremos el Museo de la Ciudad y degustaremos de la gastronomía Quiteña en la famosa calle La Ronda | I25: Cultural | J25: 4 | K25: 1 KM | L25: 2830 | M25: BAJA | N25: https://www.google.com/maps/d/edit?mid=1H4_hh0ulWv-1xk4dTlmYvKj3FRMn_as&usp=drive_link | O25: Catedral Metropolitana de Quito | P25: Museo de la Ciudad | Y25: Casa 925
A26: 025 | B26: ACTIVO | C26: =CONCATENATE(VLOOKUP($D26,CODIFICACIÓN_RUTA!$B$2:$C$3,2,0),MID($F26,1,1)&MID($F26,6,1),VLOOKUP($E26,CODIFICACIÓN_RUTA!$E$2:$F$10,2,0),$A26) -> 02RP08025 | D26: RURAL | E26: Valle de Tumbaco | F26: RUTA PIFO,CULTURA, NATURALEZA Y TRADICIÓN | G26: RUTAS POR FORTALECER | H26: Conoceremos sobre la historia de este maravillos lugar, visitaremos la Hacienda Ecuestre Chantag, su Iglesia entre otros espacios. | I26: Cultural | J26: 6 | K26: 70 KM | L26: 2850 | M26: BAJA | N26: https://www.google.com/maps/d/edit?mid=1yWOw43xtH4FbNqo9xCSThqvD2WOaDkA&usp=drive_link | Y26: Hacienda Ecuestre Chantag
A27: 026 | B27: ACTIVO | C27: =CONCATENATE(VLOOKUP($D27,CODIFICACIÓN_RUTA!$B$2:$C$3,2,0),MID($F27,1,1)&MID($F27,6,1),VLOOKUP($E27,CODIFICACIÓN_RUTA!$E$2:$F$10,2,0),$A27) -> 01RT01026 | D27: URBANO | E27: Centro Histórico | F27: RUTA TRADICIONES Y LEGADO FRANCISCANO | G27: RUTAS CON POTENCIAL | H27: Visitaremos uno de los mercados más antiguios de la ciudad quiteña y de la mano de las hierbateras conocermos sobre los saberes ancestrales y uso de plantas medicinales , degustación de dulces tradicionales y una visita dentro del convento más grande de latinoamerica. | I27: Cultural | J27: 3 | K27: 0.7 KM | L27: 2850 | M27: BAJA | N27: https://www.google.com/maps/d/edit?mid=1wDE7ScASCtjFylIgEV7crp_HLIPp4Mk&usp=drive_link | O27: Mercado de San Francisco | P27: Convento de San Francisco
A28: 027 | B28: INACTIVO | C28: =CONCATENATE(VLOOKUP($D28,CODIFICACIÓN_RUTA!$B$2:$C$3,2,0),MID($F28,1,1)&MID($F28,6,1),VLOOKUP($E28,CODIFICACIÓN_RUTA!$E$2:$F$10,2,0),$A28) -> 02RG08027 | D28: RURAL | E28: Valle de Tumbaco | F28: RUTA GASTRONÓMICA | G28: RUTAS CON POTENCIAL | H28: El objetivo de esta ruta es poder degustar y vivir de una manera innovadora la gastronomía del DMQ. | I28: Gastronómica | J28: 7 | L28: 2600 | M28: BAJA | N28: https://www.google.com/maps/d/viewer?mid=1f5eVi_Jy8pNHTR0P9R547e9Q5muBQa0&ll=-0.2003635849838867%2C-78.34611313492223&z=12 | O28: Iglesia de Santa Teresita | P28: Parque Metropolitano Guanguilagua | Q28: Santuario de Nuestra Señora del Quinche | Z28: Es circuito (No operativo)
A29: 028 | B29: ACTIVO | C29: =CONCATENATE(VLOOKUP($D29,CODIFICACIÓN_RUTA!$B$2:$C$3,2,0),MID($F29,1,1)&MID($F29,6,1),VLOOKUP($E29,CODIFICACIÓN_RUTA!$E$2:$F$10,2,0),$A29) -> 01RH02028 | D29: URBANO | E29: La Mariscal | F29: RUTA HISTORIA Y CULTURA EN LA MARISCAL | G29: RUTAS CONSOLIDADAS | H29: Nos sumergiremos en la historia de este barrio que mezcla da modernidad con la arquitectura del siglo XX, recorreremos monumentos como el Arco de la Circasiana, disfrutaremos de la calidad y variedad de productos que ese encuentran el Mercado artesanal, hablaremos de Benjamin Carrión y su hogar que ahora forma el Centro Cultural con su mismo nombre y conoceremos sobre la vida religiosa del barrio en la Iglesia de Santa Teresita. | I29: Cultural | J29: 4 | K29: 1 KM | L29: 2830 | M29: BAJA | N29: https://www.google.com/maps/d/u/0/edit?mid=1sTpy2NuchI3ofXDPfLloqyoMdtIAVhE&usp=sharing | O29: Arco de la Circasiana | P29: Mercado Artesanal | Q29: Centro Cultural Benjamín Carrión | R29: Iglesia de Santa Teresita
A30: 029 | B30: ACTIVO | C30: =CONCATENATE(VLOOKUP($D30,CODIFICACIÓN_RUTA!$B$2:$C$3,2,0),MID($F30,1,1)&MID($F30,6,1),VLOOKUP($E30,CODIFICACIÓN_RUTA!$E$2:$F$10,2,0),$A30) -> 02RL05029 | D30: RURAL | E30: Chocó Andino | F30: RUTA LAS PUERTAS DEL CHOCÓ ANDINO | G30: RUTAS CONSOLIDADAS | H30: Visitaremos esl sitio arqueológico Rumicucho. Recorreremos el templo del sol y la luna, descubriremos obras de arte del maestro Cristóbal Ortega, dentro de la Reserva Geobotánica Pululahua visitaremos el Mirador Ventanillas, degustaremos de exquisito al muerzo en la "Cuchara orgánica", y recorreremos el centro de Calacalí | I30: Cultural | J30: 6 | K30: 2.72 KM | L30: 1400 | M30: BAJA | N30: https://www.google.com/maps/d/u/0/edit?mid=1ehyfYRvJ4ehSjTKcX9GjcgU-TsqyzI0&usp=sharing | O30: Puracá de Rumicucho | P30: Museo Templo del Sol Pintor Cristobal Orteaga | Q30: Reserva Geobotánica Pululahua | R30: Monumento a la Mitad del Mundo - Calacalí | S30: Casa Museo Carlota Jaramillo
A31: 030 | B31: ACTIVO | C31: =CONCATENATE(VLOOKUP($D31,CODIFICACIÓN_RUTA!$B$2:$C$3,2,0),MID($F31,1,1)&MID($F31,6,1),VLOOKUP($E31,CODIFICACIÓN_RUTA!$E$2:$F$10,2,0),$A31) -> 02RC08030 | D31: RURAL | E31: Valle de Tumbaco | F31: RUTA CHAQUIÑAN - CUMBAYA | G31: RUTAS CON POTENCIAL | H31: Disfrutaremos de uno de los parque más grandes de Quito , conoceremos uno de los antiguos tramos del ferrocaril, podremos aprender sobre la historia de Cumbaya en su Iglesia. | I31: Cultural | J31: 6 | K31: 2.72 KM | L31: 2420 | M31: MEDIA | N31: https://www.google.com/maps/d/u/0/edit?mid=1vuSoWg_3Qfxs68PSgRuS4YE6EpCt8_U&usp=sharing | O31: Parque Ecológico Los Algarrobos | P31: Ruta Ecológica El Chaquiñán de Cumbaya | Q31: Iglesia San Pedro de Cumbayá
A32: 031 | B32: ACTIVO | C32: =CONCATENATE(VLOOKUP($D32,CODIFICACIÓN_RUTA!$B$2:$C$3,2,0),MID($F32,1,1)&MID($F32,6,1),VLOOKUP($E32,CODIFICACIÓN_RUTA!$E$2:$F$10,2,0),$A32) -> 01RU01031 | D32: URBANO | E32: Centro Histórico | F32: RUTA UN DÍA DE GUAGUAS | G32: RUTAS CON POTENCIAL | H32: MEDIA | I32: Cultural | J32: 5 | K32: 2.24 KM | L32: 2850 | M32: BAJA | N32: https://www.google.com/maps/d/u/0/edit?mid=1vuSoWg_3Qfxs68PSgRuS4YE6EpCt8_U&usp=sharing | O32: Museo Templo de la Patria | P32: Museo Interactivo de Ciencias | Y32: Casa 925
A33: 032 | B33: ACTIVO | C33: =CONCATENATE(VLOOKUP($D33,CODIFICACIÓN_RUTA!$B$2:$C$3,2,0),MID($F33,1,1)&MID($F33,6,1),VLOOKUP($E33,CODIFICACIÓN_RUTA!$E$2:$F$10,2,0),$A33) -> 02RP08032 | D33: RURAL | E33: Valle de Tumbaco | F33: RUTA PIFO: NATURALEZA Y DIVERSIÓN EN FAMILIA | G33: RUTAS CONSOLIDADAS | H33: Disfrutaremos de un día lleno de experiencias relacionadas con el medio ambiente en Atukpamba Mulauco además de recorrer Escorza granja orgánica, em la Granja Inga podremos visitar a las avestruces e interactuaremos con los animales de la granja. | I33: Cultural | J33: 8 | K33: 22.6 KM | L33: 2770 | M33: BAJA | N33: https://www.google.com/maps/d/u/0/edit?mid=17CtkarX0KqwP73BOMqyOm39RM3XJPak&usp=sharing | Y33: Atukpamba Mulauco Escorza granja órganica Itulcachi Granja Inga
A34: 033 | B34: ACTIVO | C34: =CONCATENATE(VLOOKUP($D34,CODIFICACIÓN_RUTA!$B$2:$C$3,2,0),MID($F34,1,1)&MID($F34,6,1),VLOOKUP($E34,CODIFICACIÓN_RUTA!$E$2:$F$10,2,0),$A34) -> 01RP01033 | D34: URBANO | E34: Centro Histórico | F34: RUTA PARQUES NOCTURNA | G34: RUTAS CON POTENCIAL | H34: Conoceremos sobre el emblemático Parque iItchimbia junto con personajes de leyenda, además de visitar la Hacienda de Piedrahita cuya historia trae recuerdos de la primera estación comercial de TV | I34: Cultural | J34: 2.3 | K34: 1.3 KM | L34: 2910 | M34: BAJA | N34: https://www.google.com/maps/d/u/0/edit?mid=10qtml-aGHZtUslN2XTfvIxABsZOiCjo&usp=sharing | O34: Centro Cultural Itchimbía
A35: 034 | B35: ACTIVO | C35: =CONCATENATE(VLOOKUP($D35,CODIFICACIÓN_RUTA!$B$2:$C$3,2,0),MID($F35,1,1)&MID($F35,6,1),VLOOKUP($E35,CODIFICACIÓN_RUTA!$E$2:$F$10,2,0),$A35) -> 01RB01034 | D35: URBANO | E35: Centro Histórico | F35: RUTA BARRIOS TRADICIONALES (SAN BLAS) | G35: RUTAS CON POTENCIAL | H35: Visitaremos el templo más antiguo de Quito, conoceremos astronomía en el observatorio, conoceremos sobre el monumento a Simón Bolívar, Círculo Militar la Filantrópica, Iglesia de San Blas, entre otros lugares. | I35: Cultural | J35: 3 | K35: 2.4 KM | L35: 2230 | M35: BAJA | N35: https://www.google.com/maps/d/u/0/edit?mid=1TRYg5TbzKkeQD-_7KT97aGa-6tn9HaU&usp=sharing | O35: Iglesia El Belén | P35: Museo del Observatorio Astronómico de Quito | Q35: Iglesia de San Blas | Y35: Plaza Belmonte
A36: 035 | B36: ACTIVO | C36: =CONCATENATE(VLOOKUP($D36,CODIFICACIÓN_RUTA!$B$2:$C$3,2,0),MID($F36,1,1)&MID($F36,6,1),VLOOKUP($E36,CODIFICACIÓN_RUTA!$E$2:$F$10,2,0),$A36) -> 01RB01035 | D36: URBANO | E36: Centro Histórico | F36: RUTA BARRIOS TRADICIONALES (LA TOLA) | G36: RUTAS CON POTENCIAL | H36: Hablaremos de la historia de este barrio colonial, sus tradiciones y leyendas además de disfrutar de demostraciones de arte. | I36: Cultural | J36: 3 | K36: 2.3 KM | L36: 2910 | M36: BAJA | N36: https://www.google.com/maps/d/u/0/edit?mid=1sAJh2cq3jTUGW7scwVvUD97CMgPaIns&usp=sharing | O36: Centro Cultural Itchimbía
A37: 036 | B37: ACTIVO | C37: =CONCATENATE(VLOOKUP($D37,CODIFICACIÓN_RUTA!$B$2:$C$3,2,0),MID($F37,1,1)&MID($F37,6,1),VLOOKUP($E37,CODIFICACIÓN_RUTA!$E$2:$F$10,2,0),$A37) -> 02RL07036 | D37: RURAL | E37: Valle de los Chillos | F37: RUTA LAGUNA DE SECAS - PINTAG | G37: RUTAS CONSOLIDADAS | H37: Visitaremos el Parque Central de Pintag, y podremos realizar caminatas alrededor de diversas lagunas como: Micacocha, laguna de secas,visitaremos el Peñon del Isco y degustaremos de un almuerzo típico de la zona | I37: Natural | J37: 7 | K37: 50 KM | L37: 3460 | M37: MEDIA | N37: https://www.google.com/maps/d/u/0/edit?mid=131L5esv4Jicj3Ntl8cAptNDtARjxYc0&usp=sharing | O37: Volcán Antisana | P37: Peñon del Isco | Q37: Laguna de Secas | R37: Laguna de la Mica
A38: 037 | B38: ACTIVO | C38: =CONCATENATE(VLOOKUP($D38,CODIFICACIÓN_RUTA!$B$2:$C$3,2,0),MID($F38,1,1)&MID($F38,6,1),VLOOKUP($E38,CODIFICACIÓN_RUTA!$E$2:$F$10,2,0),$A38) -> 02E 07037 | D38: RURAL | E38: Valle de los Chillos | F38: ENTRE LAGUNAS Y PÁRAMOS | G38: RUTAS CONSOLIDADAS | H38: En esta aventura podremos disfrutar de del Volcán Antisana y sus paisajes que lo rodean, visitaremos uno de los miradores naturales que permiten observar el vuelo de los imponentes cóndores, además de de realizar un recorrido por el sendero Pato Urco a 4100 m.s.n.m | I38: Natural | J38: 7 | K38: 50 KM | L38: 3460 | M38: ALTA | N38: https://www.google.com/maps/d/u/0/edit?mid=1pOLRarYCsoE7QLFo-HYTJbTe9PYrwMM&usp=sharing | O38: Volcán Antisana | P38: Peñon del Isco | Q38: Laguna de Secas | R38: Laguna de la Mica
A39: 038 | B39: ACTIVO | C39: =CONCATENATE(VLOOKUP($D39,CODIFICACIÓN_RUTA!$B$2:$C$3,2,0),MID($F39,1,1)&MID($F39,6,1),VLOOKUP($E39,CODIFICACIÓN_RUTA!$E$2:$F$10,2,0),$A39) -> 01RC01038 | D39: URBANO | E39: Centro Histórico | F39: RUTA CONVENTO DE SANTO DOMINGO: CRIPTAS, LEYENDAS Y MISTERIO | G39: RUTAS CON POTENCIAL | H39: Se visitará el Refectorio del Convento, el Museo con una muestra de arte religioso, la capilla del Rosario, la iglesia y las catacumbas. Esto acompañados de personajes teatralizados que nos contarán historias y leyendas de esta convento. | I39: Cultural | J39: 1 | K39: 0.5 KM | L39: 2850 | M39: BAJA | N39: https://www.google.com/maps/d/u/0/edit?mid=1vWjsRCzlkrZE3GVnV5RzkejmqO0RX14&usp=sharing | O39: Museo de Santo Domingo Fray Pedro Bedón
A40: 039 | B40: ACTIVO | C40: =CONCATENATE(VLOOKUP($D40,CODIFICACIÓN_RUTA!$B$2:$C$3,2,0),MID($F40,1,1)&MID($F40,6,1),VLOOKUP($E40,CODIFICACIÓN_RUTA!$E$2:$F$10,2,0),$A40) -> 01RL01039 | D40: URBANO | E40: Centro Histórico | F40: RUTA LEGADO DE LOS FRANCISCANOS | G40: RUTAS CON POTENCIAL | H40: Conoceremos los dos complejos franciscanos que habitan en el Centro Histórico con gran influencia de arte quiteño, historia y vida religiosa. | I40: Cultural | J40: 4 | K40: 0.2 KM | L40: 2850 | M40: BAJA | N40: https://www.google.com/maps/d/u/0/edit?mid=1XxBokk1yWaWhGsSbfoSqf_romOBQaD8&usp=sharing | O40: Museo Fray Pedro Gocial San Francisco | P40: Iglesia de Santa Clara
A41: 040 | B41: ACTIVO | C41: =CONCATENATE(VLOOKUP($D41,CODIFICACIÓN_RUTA!$B$2:$C$3,2,0),MID($F41,1,1)&MID($F41,6,1),VLOOKUP($E41,CODIFICACIÓN_RUTA!$E$2:$F$10,2,0),$A41) -> 01RD02040 | D41: URBANO | E41: La Mariscal | F41: RUTA DE LA CREATIVIDAD | G41: RUTAS CON POTENCIAL | H41: Abarcaremos diversos temas desde arquitéctura, visita al mercado artesanal, hablaremo sobre los castillos que habitan en este maravilloso barrio. | I41: Cultural | J41: 3 | K41: 2.5 KM | L41: 2850 | M41: BAJA | N41: https://www.google.com/maps/d/u/0/edit?mid=1ZkceVByiwiR92byeO4xOKtkrFvnChxY&usp=sharing | O41: Museo Nacional del Ecuador (MUNA) | P41: El Útero
A42: 041 | B42: ACTIVO | C42: =CONCATENATE(VLOOKUP($D42,CODIFICACIÓN_RUTA!$B$2:$C$3,2,0),MID($F42,1,1)&MID($F42,6,1),VLOOKUP($E42,CODIFICACIÓN_RUTA!$E$2:$F$10,2,0),$A42) -> 02RP07041 | D42: RURAL | E42: Valle de los Chillos | F42: RUTA PARQUE METROPLITANO DEL SUR. OBSERVACIÓN DE AVES | G42: RUTAS CON POTENCIAL | H42: Realizaremos un recorrido de descenso por el sendero Ushay Ñan para poder avistar las aves respetivas del Distrito, a través del sendero Pita Tambo - Casa Morga, donde podremos observar un humedal artificial. | I42: Natural | J42: 6 | K42: 27 KM | L42: 3460 | M42: MEDIA | N42: https://www.google.com/maps/d/u/0/edit?mid=1FxMSe1jO8CCwF-lht1BcgyT6EWcM1EI&usp=sharing | O42: Parque Metropolitano del Sur
A43: 042 | B43: ACTIVO | C43: =CONCATENATE(VLOOKUP($D43,CODIFICACIÓN_RUTA!$B$2:$C$3,2,0),MID($F43,1,1)&MID($F43,6,1),VLOOKUP($E43,CODIFICACIÓN_RUTA!$E$2:$F$10,2,0),$A43) -> 01RJ03042 | D43: URBANO | E43: Centro Norte | F43: RUTA JARDÍN BOTÁNICO. OBSERVACIÓN DE AVES. | G43: RUTAS CON POTENCIAL | H43: Se realizará un recorrido por todo el circuito del jardín, para la identificación de aves de la mano de nuestro guía naturalista. | I43: Natural | J43: 3 | K43: 1 KM | L43: 3460 | M43: MEDIA | N43: https://www.google.com/maps/d/u/0/edit?mid=15xLBSKwPsVpb9Z0hrb4r6e8xxtCW6v8&usp=sharing | O43: Jardín Botánico de Quito
A44: 043 | B44: ACTIVO | C44: =CONCATENATE(VLOOKUP($D44,CODIFICACIÓN_RUTA!$B$2:$C$3,2,0),MID($F44,1,1)&MID($F44,6,1),VLOOKUP($E44,CODIFICACIÓN_RUTA!$E$2:$F$10,2,0),$A44) -> 01RM01043 | D44: URBANO | E44: Centro Histórico | F44: RUTA MÁS ALLÁ DE LA MUERTE. CONVENTO Y CEMENTERIO DEL TEJAR | G44: RUTAS POR FORTALECER | H44: Mediante una interpretación teatralizada conoceremos sobre la historia del Convento del Tejar, recorreremos su cpnvento, iglesia, criptas y cementerio. | I44: Cultural | J44: 1 | K44: 0.5 KM | L44: 2850 | M44: BAJA | N44: https://www.google.com/maps/d/u/0/edit?mid=1ACnIJq_sB2XA17HYzVN-gIstK8baiGQ&usp=sharing | O44: Iglesia El Tejar
A45: 044 | B45: ACTIVO | C45: =CONCATENATE(VLOOKUP($D45,CODIFICACIÓN_RUTA!$B$2:$C$3,2,0),MID($F45,1,1)&MID($F45,6,1),VLOOKUP($E45,CODIFICACIÓN_RUTA!$E$2:$F$10,2,0),$A45) -> 01RQ01044 | D45: URBANO | E45: Centro Histórico | F45: RUTA QUITO DESDE LAS ALTURAS | G45: RUTAS CONSOLIDADAS | H45: Los visitantes harán una visita inédita, conociendo las torres , podrán desde este sitio ver de manera majestuosa el norte, centro histórico de Quito y la Virgen de El Panecillo; además bajarán también a las criptas de la Basílica del Voto Nacional, viviendo sin duda una experiencia inolvidable en el templo neogótico de América. | I45: Cultural | J45: 4 | K45: 4.5 KM | L45: 3100 | M45: BAJA | N45: https://www.google.com/maps/d/u/0/edit?mid=1WHO5DNZArzaEw9vIcB3qNMWtiqeytbw&usp=sharing | O45: Basílica del Voto Nacional | P45: Plaza Grande | Q45: Iglesia Compañía de Jesús | Y45: Restaurante San Ignacio
A46: 045 | B46: ACTIVO | C46: =CONCATENATE(VLOOKUP($D46,CODIFICACIÓN_RUTA!$B$2:$C$3,2,0),MID($F46,1,1)&MID($F46,6,1),VLOOKUP($E46,CODIFICACIÓN_RUTA!$E$2:$F$10,2,0),$A46) -> 02RE05045 | D46: RURAL | E46: Chocó Andino | F46: RUTA EXPLORANDO EL BOSQUE NUBLADO | G46: RUTAS CONSOLIDADAS | H46: Visitaremos en la red de senderos con uno de los guías locales para tener un encuentro íntimo con este Mágico Bosque y unas hermosos paisajes del Valle de Tandayapa. | I46: CAVE | J46: 8 | K46: 60 KM | L46: 2800 | M46: MEDIA | N46: https://www.google.com/maps/d/u/0/edit?mid=1fZc3TkLdpjG1xDtA4oMkZxer_RwbmgA&usp=sharing | O46: Bellavista Cloud Forest
A47: 046 | B47: ACTIVO | C47: =CONCATENATE(VLOOKUP($D47,CODIFICACIÓN_RUTA!$B$2:$C$3,2,0),MID($F47,1,1)&MID($F47,6,1),VLOOKUP($E47,CODIFICACIÓN_RUTA!$E$2:$F$10,2,0),$A47) -> 01RB01046 | D47: URBANO | E47: Centro Histórico | F47: RUTA BARRIOS TRADICIONALES (LA LOMA GRANDE) | G47: RUTAS CON POTENCIAL | H47: Durante esta ruta podremos conocer la historia de este emblemático barrio, sus leyendas, tradicones y disfrutaremos de una degustación de café | I47: Cultural | J47: 3 | K47: 1 KM | L47: 3100 | M47: BAJA | N47: https://www.google.com/maps/d/u/0/edit?mid=1QJ9K3hg71oclbqZO1Miw10emDfA0vO0&usp=sharing | O47: Museo de Santo Domingo Fray Pedro Bedón | P47: Centro Cultural Mama Cuchara | Y47: Casa Instinto Ecuador Cafetería- Mirador La Loma Grande
A48: 047 | B48: ACTIVO | C48: =CONCATENATE(VLOOKUP($D48,CODIFICACIÓN_RUTA!$B$2:$C$3,2,0),MID($F48,1,1)&MID($F48,6,1),VLOOKUP($E48,CODIFICACIÓN_RUTA!$E$2:$F$10,2,0),$A48) -> 01RB01047 | D48: URBANO | E48: Centro Histórico | F48: RUTA BARRIOS TRADICIONALES – LA TOLA-SAN BLAS | G48: RUTAS CON POTENCIAL | H48: Demostración de técnicas de la escuela Quiteña, juegos tradicionales, visita a la Virgen del Muro donde coeciste con una sere de leyendas populares, parque Itchimbia junto conla interpretación de personajes icónicos. (el recorrido se realizará en Chiva tradicional) Talleres- Virgen del Muro- Parque Itchimbia | I48: Cultural | J48: 3 | K48: 1.5 KM | L48: 2850 | M48: BAJA | N48: https://www.google.com/maps/d/u/0/edit?mid=1TDnkP46smXmAxk4z2ad-ly7Vu4l4GqE&usp=sharing | O48: Taller de Arte el Rincón de los Arcángeles | P48: Centro Cultural Itchimbía
A49: 048 | B49: ACTIVO | C49: =CONCATENATE(VLOOKUP($D49,CODIFICACIÓN_RUTA!$B$2:$C$3,2,0),MID($F49,1,1)&MID($F49,6,1),VLOOKUP($E49,CODIFICACIÓN_RUTA!$E$2:$F$10,2,0),$A49) -> 01RS01048 | D49: URBANO | E49: Centro Histórico | F49: RUTA SAN JUAN - LA GUARAGUA – SAN FRANCISCO- EL PANECILLO | G49: RUTAS CON POTENCIAL | H49: Visitaremos uno de los templos más emblemáticos de la urbe quiteña, recorreremos la calle tradicional de la Guaragua, donde se puede observar su arquitectura colonial y republicana, y junto con una Chiva y un personaje tradicional recorremos la plaza de San Francisco y el Panecillo. (Basílica del Voto Nacional–La Guaragua– Plaza de San Francisco – El Panecillo – Plaza de San Francisco) | I49: Cultural | J49: 3 | K49: 6 KM | L49: 2850 | M49: BAJA | N49: https://www.google.com/maps/d/u/0/edit?mid=1gno2-C5_QN9CWWC-olLGlJ7JuFt3zL0&usp=sharing | O49: Basílica del Voto Nacional | P49: Plaza de San Francisco | Q49: Monumento Virgen de El Panecillo
A50: 049 | B50: ACTIVO | C50: =CONCATENATE(VLOOKUP($D50,CODIFICACIÓN_RUTA!$B$2:$C$3,2,0),MID($F50,1,1)&MID($F50,6,1),VLOOKUP($E50,CODIFICACIÓN_RUTA!$E$2:$F$10,2,0),$A50) -> 01RB01049 | D50: URBANO | E50: Centro Histórico | F50: RUTA BELENES I | G50: RUTAS CON POTENCIAL | H50: Podremos conocer alrededor de 30 pesebres de diferentes artesanso ubicados dento del Convento de San Francisco, además podremos conocer uno de los pesebres más antiguos de Quito que data del año 1596. ( Belenes del Monasterio de Santa Clara y Convento de San Francisco) | I50: Cultural | J50: 3 | K50: 1 KM | L50: 2850 | M50: BAJA | N50: https://www.google.com/maps/d/u/0/edit?mid=1z203KKOwAqjWrZLr2Jth4CcscydF8cU&usp=sharing | O50: Museo Fray Pedro Gocial San Francisco | P50: Iglesia de Santa Clara
A51: 050 | B51: ACTIVO | C51: =CONCATENATE(VLOOKUP($D51,CODIFICACIÓN_RUTA!$B$2:$C$3,2,0),MID($F51,1,1)&MID($F51,6,1),VLOOKUP($E51,CODIFICACIÓN_RUTA!$E$2:$F$10,2,0),$A51) -> 01RB01050 | D51: URBANO | E51: Centro Histórico | F51: RUTA BELENES II | G51: RUTAS CON POTENCIAL | H51: Conoceremos uno de los pesebre más llamativos de la Escuela Quiteña con 200 años de historia ubicado en el Convento del Carmen Bajo, Cada año el Pesebre Carmelita plantea narrativas diferentes para conocer su riqueza artística desde múltiples perspectivas educativas. Estos relatos son contados mediante piezas de colección, correspondientes a los siglos XVIII y XIX, dentro del Carmen Alto (Belenes del Carmen Bajo y Carmen Bajo) | I51: Cultural | J51: 3 | K51: 1.5 KM | L51: 2850 | M51: BAJA | N51: https://www.google.com/maps/d/u/0/edit?mid=1yTPAbnQ-GX4BUr9UlfiDHV9Y7bvXrVU&usp=sharing | O51: Convento del Carmen Bajo | P51: Museo del Carmen Alto | Y51: Casa 925
A52: 051 | B52: ACTIVO | C52: =CONCATENATE(VLOOKUP($D52,CODIFICACIÓN_RUTA!$B$2:$C$3,2,0),MID($F52,1,1)&MID($F52,6,1),VLOOKUP($E52,CODIFICACIÓN_RUTA!$E$2:$F$10,2,0),$A52) -> 01RB01051 | D52: URBANO | E52: Centro Histórico | F52: RUTA BELENES – BARRIO LA LOMA GRANDE | G52: RUTAS CON POTENCIAL | H52: El recorrido iniciara en la plaza de Santo Domingo, donde visitaremos el templo con el mismo nombre. Conoceremos el primer Belén en el Taller Arte con Amor, donde podeemos observar figuras en movimiento. En la antigua marmolería Tomebamba, se encuentra el pesebre de la familia Gallegos, quienes tienen a su cargo un niño que provebiene de Cojitambo y tiene más de 200 años. (Cúpulas de Santo Domingo- Belenes y Experiencias del Barrio de la Loma Grande) | I52: Cultural | J52: 4 | K52: 1 KM | L52: 2850 | M52: BAJA | N52: https://www.google.com/maps/d/u/0/edit?mid=1-QsaYCEtH7q3EnrMjWumVZPdW1IFPLI&usp=sharing | O52: Museo de Santo Domingo Fray Pedro Bedón | Y52: Galería de Cacao y artesanos
A53: 052 | B53: ACTIVO | C53: =CONCATENATE(VLOOKUP($D53,CODIFICACIÓN_RUTA!$B$2:$C$3,2,0),MID($F53,1,1)&MID($F53,6,1),VLOOKUP($E53,CODIFICACIÓN_RUTA!$E$2:$F$10,2,0),$A53) -> 02RU01052 | D53: RURAL | E53: Centro Histórico | F53: RUTA UNA VISTA A LA AVANZADA DE SUCRE DESDE LAS ALTURAS | G53: RUTAS CON POTENCIAL | H53: Visitaremos el Templo de la Patria, sitio de homenaje a la batalla en el que Ejercito del Mariscal Antonio José de Sucre, visitaremos la Comunidad de San Francisco de Cruz Loma y su casacada Quitu Cara, en el Mirador de Humbolt encuentro con mujeres emprendedoras de la Ruta de Humbolt. (Cima de La Libertad – Comunidad San Francisco de Cruz Loma- Mirador de Humboldt) | I53: Histórica | J53: 6 | K53: 25 | L53: 3642 | N53: https://www.google.com/maps/d/edit?mid=1KLGLpxKLwXtatH4__a1jy8HN8FyO0sU&usp=sharing | O53: Museo de la Defensa Templo de La Patria | P53: Comunidad San Francisco de Cruz Loma | Q53: Mirador de Humboldt
A54: 053 | B54: ACTIVO | C54: =CONCATENATE(VLOOKUP($D54,CODIFICACIÓN_RUTA!$B$2:$C$3,2,0),MID($F54,1,1)&MID($F54,6,1),VLOOKUP($E54,CODIFICACIÓN_RUTA!$E$2:$F$10,2,0),$A54) -> 01 01053 | D54: URBANO | E54: Centro Histórico | F54: RUTA RECORDANDO AL MARISCAL SUCRE | G54: RUTAS CON POTENCIAL | H54: Visitaremos el Centro Cultural Metropolitano, donde podremos observar un lienzo del Mariscal, realizado por el centenario; Museo Casa de Sucre dedicado a conocer la vida familiar del mariscal y su esposa la Marquesa de Solanda, la estatua del Libertador ubicada en la plaza de Santo Domingo y finalizaremos con una degustación en La Ronda. (Plaza Grande- CCM- Casa de Sucre-Plaza Santo Domingo (Monumento de Sucre)- La Ronda- Boulevard 24 de Mayo) | I54: Histórica | J54: 2.5 | K54: 1 KM | L54: 2830 | M54: BAJA | N54: https://www.google.com/maps/d/edit?mid=1aGTvl9FSO1YMEKqC1pGXOvF4I1CmKO0&usp=sharing | O54: Centro Cultural Metropolitano | P54: Museo de La Defensa Casa de Sucre | Q54: Plaza de Santo Domingo | Y54: Casa 925
A55: 054 | B55: ACTIVO | C55: =CONCATENATE(VLOOKUP($D55,CODIFICACIÓN_RUTA!$B$2:$C$3,2,0),MID($F55,1,1)&MID($F55,6,1),VLOOKUP($E55,CODIFICACIÓN_RUTA!$E$2:$F$10,2,0),$A55) -> 01 01054 | D55: URBANO | E55: Centro Histórico | F55: RUTA SIGUIENDO LA PISTA DE SUCRE | G55: RUTAS POR FORTALECER | H55: Desde la Cima de La Libertad, podremos visitar el mirador y el museo Templo de la Patria, el Centro Cívico Cultural Mariscal Sucre, antigua casa hacienda de la parroquia de Chilllogallo paso la noche el 22 de mayo de 1822 y activación cultural. (Cima de La Libertad – Centro Cívico Cultural Mariscal Sucre) | I55: Histórica | J55: 6 | K55: 15.4 KM | L55: 33800 | M55: BAJA | N55: https://www.google.com/maps/d/edit?mid=1kNSnKp_VvF0R_EZ7QTAUyK1uJs8ybJI&usp=sharing | O55: Museo de la Defensa Templo de La Patria | P55: Centro Cívico Cultural Mariscal Sucre
A56: 055 | B56: ACTIVO | C56: =CONCATENATE(VLOOKUP($D56,CODIFICACIÓN_RUTA!$B$2:$C$3,2,0),MID($F56,1,1)&MID($F56,6,1),VLOOKUP($E56,CODIFICACIÓN_RUTA!$E$2:$F$10,2,0),$A56) -> 01 01055 | D56: URBANO | E56: Centro Histórico | F56: RUTA EL HALLAZGO INESPERADO | G56: RUTAS CONSOLIDADAS | H56: Conoceremos el primer sitio de descanso de los restos del Mariscal, en el Centro Cultural Metropolitano, podremos observar un lienzo del Mariscal realizado por el centenario de la batalla. En la Catedral visitaremos el retablo mayor, la capilla de Sucre y morada final de los restos del Mariscal y sus cúpulas. (Carmen Bajo - Centro Cultural Metropolitano – Catedral) | I56: Histórica | J56: 3 | K56: 0.7 KM | L56: 2850 | M56: BAJA | N56: https://www.google.com/maps/d/edit?mid=1VPe7XhZqhvixSjsLuxxnKehBfkutjhI&usp=sharing | O56: Convento del Carmen Bajo | P56: Centro Cultural Metropolitano | Q56: Catedral Metropolitana de Quito | R56: Plaza Grande
A57: 056 | B57: ACTIVO | C57: =CONCATENATE(VLOOKUP($D57,CODIFICACIÓN_RUTA!$B$2:$C$3,2,0),MID($F57,1,1)&MID($F57,6,1),VLOOKUP($E57,CODIFICACIÓN_RUTA!$E$2:$F$10,2,0),$A57) -> 01RL01056 | D57: URBANO | E57: Centro Histórico | F57: RUTA LAS DELICIAS DEL LIBERTADOR | G57: RUTAS CONSOLIDADAS | H57: Experiencia Teatral que nos traslada al siglo XIX, a los años decisivos de la Gesta Libertaria en la que a travez de 4 personajes descubriremos algunos momentos de la vida del Libertador Simón Bolívar, hábitos, costumbres, y platillos predilectos. (CENTENARIO DE LA MARISCAL) Casa Patrimonial Silberstein , Santhorno de empanadas | I57: Gastronómica | J57: 3 | K57: 1.5 KM | L57: 2850 | M57: BAJA | N57: https://www.google.com/maps/d/u/0/edit?mid=14Bwseh226BN9-AFeoePyUsukFdH3V0I&usp=sharing | Y57: Casa Patrimonial Silberstein
A58: 057 | B58: ACTIVO | C58: =CONCATENATE(VLOOKUP($D58,CODIFICACIÓN_RUTA!$B$2:$C$3,2,0),MID($F58,1,1)&MID($F58,6,1),VLOOKUP($E58,CODIFICACIÓN_RUTA!$E$2:$F$10,2,0),$A58) -> 02RR05057 | D58: RURAL | E58: Chocó Andino | F58: RUTA RESERVA PAHUMA - RAPEL | G58: RUTAS CON POTENCIAL | H58: Se conocerá sobre esta reserva, con una breve capacitación previa, se realizará senderismo y se podrá observar aves; además, se visitará el jardín de las orquídeas que existe en la reserva con las más representativas especies del sector. Se realizará una caminata hacia la Cascada Gallo de la Peña, en donde se hará rapel. (Cráter del Pululahua – Reserva Pahuma – Cascada Gallo de la Peña) | I58: Natural | J58: 7 | K58: 66 KM | L58: 3100 | M58: BAJA | N58: https://www.google.com/maps/d/edit?mid=1NX7novbzkaXp47vPT3f1rWanYB3TyTU&usp=sharing | O58: Reserva Geobotánica Pululahua | P58: Reserva Orquideológiva Pahuma
A59: 058 | B59: ACTIVO | C59: =CONCATENATE(VLOOKUP($D59,CODIFICACIÓN_RUTA!$B$2:$C$3,2,0),MID($F59,1,1)&MID($F59,6,1),VLOOKUP($E59,CODIFICACIÓN_RUTA!$E$2:$F$10,2,0),$A59) -> 02RQ05058 | D59: RURAL | E59: Chocó Andino | F59: RUTA QUITO-NANEGAL CASCADA DE LA PIRAGUA-PIEDRA ORONZONA | G59: RUTAS CON POTENCIAL | H59: “Disfruta de un refrescante baño proveniente del Guagua Pichincha en el Bosque nublado de Nanegal” Conoceremos sobre las tradiciones ancestrales de la Cultura Yumbo, caminata hacia la cascada con explicación de flora y fauna y baño energético al arribo. Se realizará el "Tour del café con leche", una caminata a los cultivos de café de altura, el proceso de secado y campos de producción lechera. | I59: Natural | J59: 7 | K59: 1.8 KM | L59: 2832 | M59: BAJA | N59: https://www.google.com/maps/d/edit?mid=1skUKjNhVVmPZJkST1-_qNYSQS-_rfqU&usp=sharing | O59: Cascada La Piragua
A60: 059 | B60: ACTIVO | C60: =CONCATENATE(VLOOKUP($D60,CODIFICACIÓN_RUTA!$B$2:$C$3,2,0),MID($F60,1,1)&MID($F60,6,1),VLOOKUP($E60,CODIFICACIÓN_RUTA!$E$2:$F$10,2,0),$A60) -> 02RQ05059 | D60: RURAL | E60: Chocó Andino | F60: RUTA QUITO-YANACOCHA | G60: RUTAS CONSOLIDADAS | H60: Se realizará una caminata para realizar observación de aves de la zona que incluye una explicación sobre fauna y flora y del ecosistema del Bosque Montano Alto. | I60: CAVE | J60: 5 | K60: 3.9 KM | L60: 3180 | M60: BAJA | N60: https://www.google.com/maps/d/edit?mid=15xd_oSvv-ThdQP4DGaFgkxxkjOAGfkU&usp=sharing | O60: Reserva Yanacocha
A61: 060 | B61: ACTIVO | C61: =CONCATENATE(VLOOKUP($D61,CODIFICACIÓN_RUTA!$B$2:$C$3,2,0),MID($F61,1,1)&MID($F61,6,1),VLOOKUP($E61,CODIFICACIÓN_RUTA!$E$2:$F$10,2,0),$A61) -> 02RT04060 | D61: RURAL | E61: Parroquias Equinocciales | F61: RUTA TUCANOPY | G61: RUTAS CON POTENCIAL | H61: Esta actividad consiste en un sistema de cables que atraviesan por el canopy o copas de los árboles, ofreciendo a nuestros visitantes, la oportunidad única de observar la biodiversidad de los bosques nublados de Ecuador desde una perspectiva diferente | I61: Natural | J61: 5 | K61: 3.9 KM | L61: 2800 | M61: MEDIA | N61: https://www.google.com/maps/d/edit?mid=1tNU9gyHqZuzbA1TTn8fXoTaf_KM0P9Q&usp=sharing | O61: Reserva Geobotánica Pululahua | P61: Reserva Intillacta Tucanopy - canopy - puentes de altura
A62: 061 | B62: ACTIVO | C62: =CONCATENATE(VLOOKUP($D62,CODIFICACIÓN_RUTA!$B$2:$C$3,2,0),MID($F62,1,1)&MID($F62,6,1),VLOOKUP($E62,CODIFICACIÓN_RUTA!$E$2:$F$10,2,0),$A62) -> 02RA07061 | D62: RURAL | E62: Valle de los Chillos | F62: RUTA AVENTURA Y NATURALEZA | G62: RUTAS CONSOLIDADAS | H62: En esta reserva se encuentran sitios que son utilizados por los cóndores como perchas y dormideros. Y protege páramos y pantanos que son importantes fuentes de agua para comunidades aledañas. Aquí se realizará una caminata y una visita al mirador del Peñón del Cóndor. (Reserva Chakana- Laguna de Secas) | I62: CAVE | J62: 7 | K62: 50 KM | L62: 4800 | M62: MEDIA | N62: https://www.google.com/maps/d/edit?mid=1MO45o29Bdn9YYp_Id4XbHrhg-EbTqao&usp=sharing | O62: Reserva Chakana- Hacienda Antisanilla | P62: Laguna de Secas
A63: 062 | B63: ACTIVO | C63: =CONCATENATE(VLOOKUP($D63,CODIFICACIÓN_RUTA!$B$2:$C$3,2,0),MID($F63,1,1)&MID($F63,6,1),VLOOKUP($E63,CODIFICACIÓN_RUTA!$E$2:$F$10,2,0),$A63) -> 01RM01062 | D63: URBANO | E63: Centro Histórico | F63: RUTA MUSEOS EN MIRADORES | G63: RUTAS CON POTENCIAL | H63: El Yaku es un espacio de interacción y aprendizaje para grandes y pequeños, aquí se puede reconocer y reflexionar sobre la relación del agua con los ecosistemas de páramo y bosque montano. Es un espacio privilegiado que tiene una vista excepcional del centro histórico. Sus instalaciones se levantan sobre lo que fue la antigua planta de tratamiento del agua y algunos elementos se adecuaron para el desarrollo del museo. (La Mariscal - YAKU - El Panecillo – La Mariscal) | I63: Cultural | J63: 4 | K63: 10 KM | L63: 3100 | M63: BAJA | N63: https://www.google.com/maps/d/edit?mid=1odZMbpF6718MTTD2RDVDNU88rTEivrg&usp=sharing | O63: Yaku Parque Mueso del Agua | P63: Monumento Virgen de El Panecillo
A64: 063 | B64: ACTIVO | C64: =CONCATENATE(VLOOKUP($D64,CODIFICACIÓN_RUTA!$B$2:$C$3,2,0),MID($F64,1,1)&MID($F64,6,1),VLOOKUP($E64,CODIFICACIÓN_RUTA!$E$2:$F$10,2,0),$A64) -> 01RC01063 | D64: URBANO | E64: Centro Histórico | F64: RUTA CALLE GARCÍA MORENO, TRADICIÓN QUITEÑA | G64: RUTAS CON POTENCIAL | H64: Visitaremos la edificación religiosa del siglo XVI, acogio a ls primeros jesuitas, ademas visitaremos la Casa Guillespi que fue elaborada por Francisco Durini, La casa del Higo donde podremos difrutar de la cata de choclate junto con la chocolateria ChezTiff, los tradicionales sanduches Menses y hablaremos de la importancia historia y política de la plaza grande. (Iglesia de Santa Bárbara - Casa Guillespi y García Moreno - Casa del Higo- Sánduches Meneses - Plaza Grande - El Quinde) | I64: Cultural | J64: 3 | K64: 0.7 KM | L64: 2850 | M64: MEDIA | N64: https://www.google.com/maps/d/edit?mid=1NM_V2cAS2U1bpBuLvsUlR2rHeDLj53k&usp=sharing | O64: Iglesia de Santa Bárbara | P64: Casa del HIgo | Q64: Plaza Grande
A65: 064 | B65: ACTIVO | C65: =CONCATENATE(VLOOKUP($D65,CODIFICACIÓN_RUTA!$B$2:$C$3,2,0),MID($F65,1,1)&MID($F65,6,1),VLOOKUP($E65,CODIFICACIÓN_RUTA!$E$2:$F$10,2,0),$A65) -> 01RT02064 | D65: URBANO | E65: La Mariscal | F65: RUTA TRAS LAS CENIZAS DEL VIEJO LUCHADOR | G65: RUTAS CON POTENCIAL | H65: Durante el recorrido podremos disfrutar de la arquitectura de este barrio marcado por la influencia de Ruben Vinci, su iglesia de estilo Neogótico, y la representación de la muerte del viejo luchador en la plaza de los Presidentes. (Arco de la Circasiana- mercado Artesanal-Castillo Silva del Pozo- Casa del Patio Parado- Casa de las 7 Terrazas-Antigua Residencia Carmelita-Iglesia de Santa Teresita- Plaza de los Presidentes.) | I65: Histórica | J65: 2 | K65: 1.7 KM | L65: 2850 | M65: BAJA | N65: https://www.google.com/maps/d/edit?mid=1E-RW2JpfAcl1Z6OpvDO86JsIIlUMiDc&usp=sharing | O65: Iglesia de Santa Teresita | P65: Plaza de los Presidentes
A66: 065 | B66: ACTIVO | C66: =CONCATENATE(VLOOKUP($D66,CODIFICACIÓN_RUTA!$B$2:$C$3,2,0),MID($F66,1,1)&MID($F66,6,1),VLOOKUP($E66,CODIFICACIÓN_RUTA!$E$2:$F$10,2,0),$A66) -> 01RE01065 | D66: URBANO | E66: Centro Histórico | F66: RUTA EL FUERTE DE LOS REALISTAS | G66: RUTAS CON POTENCIAL | H66: En el recorrido conoceremos sobre datos interesantes del monumento de Antonio José de Sucre, y de varias de las edificaciones que rodean este concurrido espacio del centro histórico. (Santo Domingo- Boulevard 24 Mayo- Panecillo- Museo de la Ciudad) | I66: Histórica | J66: 3 | K66: 4 KM | L66: 2820 | M66: MEDIA | N66: https://www.google.com/maps/d/edit?mid=1yHSSZ41gBq9yM2COypKD3iqTYCdHzuQ&usp=sharing | O66: Plaza de Santo Domingo | P66: Bulevar 24 de Mayo | Q66: Monumento Virgen de El Panecillo | R66: Museo de La Ciudad
A67: 066 | B67: ACTIVO | C67: =CONCATENATE(VLOOKUP($D67,CODIFICACIÓN_RUTA!$B$2:$C$3,2,0),MID($F67,1,1)&MID($F67,6,1),VLOOKUP($E67,CODIFICACIÓN_RUTA!$E$2:$F$10,2,0),$A67) -> 01RE01066 | D67: URBANO | E67: Centro Histórico | F67: RUTA EL CAMINO A LA INDEPENDENCIA | G67: RUTAS CONSOLIDADAS | H67: Conoceremos lugares trascendentales en la gesta libertaria, como la Plaza Grande, Iglesia y conventp de San Agustín, Lugar directamente relacionado con el inicio de la gesta libertaria. En sus Sala Capitular se firmó el acta del primer grito de Independencia. (Activación Cultural). Desmotración de helados de paila en la Heladería San Agustín, Casa de Sucre donde conoceremos sobre la vida familiar del Mariscal. (Plaza de la Independencia – Fachada de la iglesia y Convento de San Agustín- Casa de Sucre) | I67: Histórica | J67: 3 | K67: 2.4 KM | L67: 2830 | M67: BAJA | N67: https://www.google.com/maps/d/edit?mid=1Vd3QM8TS19-SUhB1kN1FhG2B3vtcnm4&usp=sharing | O67: Plaza Grande | P67: Museo Miguel de Santiago Convento de San Agustín | Q67: Museo de La Defensa Casa de Sucre | Y67: Heladería de San Agustín
A68: 067 | B68: ACTIVO | C68: =CONCATENATE(VLOOKUP($D68,CODIFICACIÓN_RUTA!$B$2:$C$3,2,0),MID($F68,1,1)&MID($F68,6,1),VLOOKUP($E68,CODIFICACIÓN_RUTA!$E$2:$F$10,2,0),$A68) -> 02RD01067 | D68: RURAL | E68: Centro Histórico | F68: RUTA DE SUCRE | G68: RUTAS POR FORTALECER | H68: Conoceremos el Camino precolombino por la tropa liderada por el Mariscal Antonio José de Sucre en la batalla de Pichincha. Visita a la comunidad de San Francisco de Cruz Loma. (Cima de La Libertad – Culunco- Comunidad San Francisco de Cruz Loma ) | I68: Natural | J68: 6 | K68: 8 KM | L68: 3595 | M68: MEDIA | N68: https://www.google.com/maps/d/u/0/edit?mid=1_GJm5bNlVJ6Nqciiq_wcXKHOvwApkog&usp=sharing | O68: Museo de La Defensa Templo de La Patria | P68: Comunidad San Francisco de Cruz Loma
A69: 068 | B69: ACTIVO | C69: =CONCATENATE(VLOOKUP($D69,CODIFICACIÓN_RUTA!$B$2:$C$3,2,0),MID($F69,1,1)&MID($F69,6,1),VLOOKUP($E69,CODIFICACIÓN_RUTA!$E$2:$F$10,2,0),$A69) -> 01RM01068 | D69: URBANO | E69: Centro Histórico | F69: RUTA MUSEOS DE LA DEFENSA | G69: RUTAS CONSOLIDADAS | H69: Hablaremos de la importancia de los museos de la defensa y su función en preservar edificios que han sobrevivido a la historia y su relevancia en la misma. (Casa de Sucre- Antiguo Círculo Militar) | I69: Cultural | J69: 6 | K69: 1 KM | L69: 33800 | M69: BAJA | N69: https://www.google.com/maps/d/edit?mid=16kUKlNptksgCp0eqwdhGfMSIzFAmYNU&usp=sharing | O69: Centro Cultural del Antiguo Círculo Militar | P69: Museo de La Defensa Casa de Sucre
A70: 069 | B70: ACTIVO | C70: =CONCATENATE(VLOOKUP($D70,CODIFICACIÓN_RUTA!$B$2:$C$3,2,0),MID($F70,1,1)&MID($F70,6,1),VLOOKUP($E70,CODIFICACIÓN_RUTA!$E$2:$F$10,2,0),$A70) -> 02RR02069 | D70: RURAL | E70: La Mariscal | F70: RUTA RUMBO AL PICHINCHA | G70: RUTAS CONSOLIDADAS | H70: Desde el teleférico un sendero que inicia a los 4050 m.sn.m, se explicará acerca de la flora y fauna que habita en el viejo Pichincha. (Teleférico – Rucu Pichincha) | I70: Natural | J70: 7 | K70: 6.4 KM | L70: 3990 | M70: MEDIA | N70: https://www.google.com/maps/d/u/0/edit?mid=1dTCysE3lwBFbuIGqtoSL942MSe3RbZo&usp=sharing | O70: Teleférico Quito | P70: Volcán Guagua Pichincha
A71: 070 | B71: ACTIVO | C71: =CONCATENATE(VLOOKUP($D71,CODIFICACIÓN_RUTA!$B$2:$C$3,2,0),MID($F71,1,1)&MID($F71,6,1),VLOOKUP($E71,CODIFICACIÓN_RUTA!$E$2:$F$10,2,0),$A71) -> 01RD01070 | D71: URBANO | E71: Centro Histórico | F71: RUTA DEL CENTRO HISTÓRICO DESDE LAS ALTURAS | G71: RUTAS POR FORTALECER | H71: Este recorrido panorámico empieza desde la Plaza Quinde a bordo del Quito Tour Bus. Visitaremos las cúpulas de iglesias como La Compañia, San Francisco, Santo Domingo, degustación de un cocktail y demostración de las limpias tradicionales. (Cúpulas de La Compañía- Torres de San Francisco – Cúpulas de Santo Domingo) | I71: Cultural | J71: 4 | K71: 6.2 KM | L71: 3100 | M71: BAJA | N71: https://www.google.com/maps/d/edit?mid=1Btas5sRdGMRFpu7_u9T3wtzrNVNOEqo&usp=sharing | O71: Iglesia Compañía de Jesús | P71: Museo Fray Pedro Gocial San Francisco | Q71: Museo de Santo Domingo Fray Pedro Bedón
A72: 071 | B72: ACTIVO | C72: =CONCATENATE(VLOOKUP($D72,CODIFICACIÓN_RUTA!$B$2:$C$3,2,0),MID($F72,1,1)&MID($F72,6,1),VLOOKUP($E72,CODIFICACIÓN_RUTA!$E$2:$F$10,2,0),$A72) -> 01RQ03071 | D72: URBANO | E72: Centro Norte | F72: RUTA QUITO BIODIVERSO | G72: RUTAS CON POTENCIAL | H72: Recorriendo el Parque La Carolina, se dará a conocer datos importantes de este importante espacio de la ciudad. (Jardín Botánico – Vivarium ) | I72: Natural | J72: 3 | K72: 1 KM | L72: 2800 | M72: BAJA | N72: https://www.google.com/maps/d/u/0/edit?mid=1RyYMuXLHeo-8t6fwinDUDZsuF2qewsQ&usp=sharing | O72: Fundación Mundo Juvenil | P72: Jardín Botánico de Quito | Q72: Vivarium de Quito
A73: 072 | B73: ACTIVO | C73: =CONCATENATE(VLOOKUP($D73,CODIFICACIÓN_RUTA!$B$2:$C$3,2,0),MID($F73,1,1)&MID($F73,6,1),VLOOKUP($E73,CODIFICACIÓN_RUTA!$E$2:$F$10,2,0),$A73) -> 01RT01072 | D73: URBANO | E73: Centro Histórico | F73: RUTA TURÍSTICA DE SAN ROQUE | G73: RUTAS CON POTENCIAL | H73: Explicación externa de la iglesia y facha de San Francisco. Seguido se dirigirán hacia el monasterio de Santa Clara y terminarán en el Mercado de San Francisco para una demostración de limpias. (Iglesia y cúpulas del Monasterio de Santa Clara, mercado de San Francisco) | I73: Cultural | J73: 3 | K73: 0.5 KM | L73: 2850 | M73: BAJA | N73: https://www.google.com/maps/d/u/0/edit?mid=1HQjqt5a9ljwBpucCVyNmKO_rCV0r8s8&usp=sharing | O73: Plaza de San Francisco | P73: Iglesia de Santa Clara | Q73: Mercado de San Francisco
A74: 073 | B74: ACTIVO | C74: =CONCATENATE(VLOOKUP($D74,CODIFICACIÓN_RUTA!$B$2:$C$3,2,0),MID($F74,1,1)&MID($F74,6,1),VLOOKUP($E74,CODIFICACIÓN_RUTA!$E$2:$F$10,2,0),$A74) -> 02RT05073 | D74: RURAL | E74: Chocó Andino | F74: RUTA TURISMO COMUNITARIO YUNGUILLA - CALACALÍ | G74: RUTAS CONSOLIDADAS | H74: Se inicia el recorrido en este sector con una altura estimada de 2980 m.s.n.m., en el mirador y se continúa caminando por el Culunco de Guantopungo, en este recorrido se podrá observar una gran cantidad de aves, se realizará una explicación de flora y fauna. | I74: Natural | J74: 7 | K74: 100 KM | L74: 3100 | M74: BAJA | N74: https://www.google.com/maps/d/edit?mid=12apefFnvmNnK88UMnbsC4jpj5xsWFD4&usp=sharing | O74: Reserva Geobotánica Pululahua | P74: Comunidad Yunguilla
A75: 074 | B75: ACTIVO | C75: =CONCATENATE(VLOOKUP($D75,CODIFICACIÓN_RUTA!$B$2:$C$3,2,0),MID($F75,1,1)&MID($F75,6,1),VLOOKUP($E75,CODIFICACIÓN_RUTA!$E$2:$F$10,2,0),$A75) -> 01RT01074 | D75: URBANO | E75: Centro Histórico | F75: RUTA TURÍSTICA LA RONDA | G75: RUTAS POR FORTALECER | H75: En este recorrido conoceremos la historia de la Iglesia y convento de Santo Domingo, visita a las cúpulas, disfrutaremos de la calle 925 y sus talleresl de oficios tradicionales quiteños, la plalza Benítez y Valencia donde se abarca la trayectoria del famoso dúo Quiteño y visita al restaurante Casa de los Geranios. (Iglesia y cúpulas de Santo Domingo, La Ronda, Talleres de Manos en La Ronda y Plaza Benítez y Valencia) | I75: Cultural | J75: 3 | K75: 0.4 KM | L75: 2850 | M75: BAJA | N75: https://www.google.com/maps/d/u/0/edit?mid=1ELCoI16mDgK0PwkRQGufrsc5bwkNOlo&usp=sharing | O75: Plaza de Santo Domingo | P75: Museo de Santo Domingo Fray Pedro Bedón | Q75: Plaza Benítez y Valencia | Y75: Casa925 Casa de los Geranios
A76: 075 | B76: ACTIVO | C76: =CONCATENATE(VLOOKUP($D76,CODIFICACIÓN_RUTA!$B$2:$C$3,2,0),MID($F76,1,1)&MID($F76,6,1),VLOOKUP($E76,CODIFICACIÓN_RUTA!$E$2:$F$10,2,0),$A76) -> 01RT02075 | D76: URBANO | E76: La Mariscal | F76: RUTA TURÍSTICA DE GUÁPULO | G76: RUTAS CON POTENCIAL | H76: Visitaremos el mirador de Guápulo donde se puede observar el valle de Cumbayá y Tumbaco, el camino de los conquistadores, que se cuenta es el camino por donde Francisco de Orellana tomo rumbo al oriente. Santuario de Guápulo. (Mirador de Guápulo, Santuario de Guápulo y museo) | I76: Cultural | J76: 3 | K76: 2 KM | L76: 2850 | M76: BAJA | N76: https://www.google.com/maps/d/u/0/edit?mid=1UgVsoPj9Ee7Q-MsKbnR4FVaGSKHxTpQ&usp=sharing | O76: Iglesia de Gúapulo
A77: 076 | B77: ACTIVO | C77: =CONCATENATE(VLOOKUP($D77,CODIFICACIÓN_RUTA!$B$2:$C$3,2,0),MID($F77,1,1)&MID($F77,6,1),VLOOKUP($E77,CODIFICACIÓN_RUTA!$E$2:$F$10,2,0),$A77) -> 01RT01076 | D77: URBANO | E77: Centro Histórico | F77: RUTA TURÍSTICA SAN JUAN | G77: RUTAS CON POTENCIAL | H77: Recorreremos las instalaciones del Centro de Arte Contemporáneo, poco despues visitaremos las Torres de la Basílica del Voto Nacional desde este impresionante se podrá ver el barrio de San Juan y conocer más de su historia. Terminaremos el recorrido en el Monaserio de las Hermanas Agustinas , se puede conocer el estilo de vida monacal que llevan estas religiosas, una parte de sus instalaciones y se puede conocer los productos que realizan para la venta, además que se puede degustar de una bebida refrescante para finalizar este recorrido. (Centro de arte contemporáneo, Basílica del Voto Nacional, Monasterio de las Hermanas Agustinas) | I77: Cultural | J77: 3 | K77: 0.8 KM | L77: 2850 | M77: BAJA | N77: https://www.google.com/maps/d/u/0/edit?mid=1RYfSK8rZgeMaXaitPW2lRq-JbsvY6kk&usp=sharing | O77: Centro de Arte Contemporáneo de Quito | P77: Basílica del Voto Nacional | Q77: Monasterio de las Hermanas Agustinas
A78: 077 | B78: ACTIVO | C78: =CONCATENATE(VLOOKUP($D78,CODIFICACIÓN_RUTA!$B$2:$C$3,2,0),MID($F78,1,1)&MID($F78,6,1),VLOOKUP($E78,CODIFICACIÓN_RUTA!$E$2:$F$10,2,0),$A78) -> 01RD01077 | D78: URBANO | E78: Centro Histórico | F78: RUTA DE LOS BELENES : STA CATALINA | G78: RUTAS CON POTENCIAL | H78: En el monasterio de Santa Catalina de Siena conoceremos los bellos pesebres y esculturas del niño Jesús, obras religiosas de la Escuela Quiteña. En el monasterio del Carmen Bajo se podrá observar uno de los belenes más grandes de la ciudad. Disfrutaremos de la degustación de un deliciosos helado en el museo del cacao. (Plaza Grande – Monasterio de Sta. Catalina de Siena – Monasterio Carmen Bajo – Tienda El Quinde) | I78: Cultural | J78: 4 | K78: 1 KM | L78: 2820 | M78: BAJA | N78: https://www.google.com/maps/d/u/0/edit?mid=1Lc1BpnHvBZajjLa_FhOO6KSrz7dA9-Y&usp=sharing | O78: Plaza Grande | P78: Museo Monacal de Santa Catalina de Siena | Q78: Convento del Carmen Bajo | R78: República del Cacao
A79: 078 | B79: ACTIVO | C79: =CONCATENATE(VLOOKUP($D79,CODIFICACIÓN_RUTA!$B$2:$C$3,2,0),MID($F79,1,1)&MID($F79,6,1),VLOOKUP($E79,CODIFICACIÓN_RUTA!$E$2:$F$10,2,0),$A79) -> 01RL02078 | D79: URBANO | E79: La Mariscal | F79: RUTA LA MARISCAL DESDE LA CIRCASIANA (PALACETES) | G79: RUTAS POR FORTALECER | H79: Disfrutaremos de los jardines y el interior del Palacio de la Circasciana, visitaremos al Palacio Mena, para conocer su historia. Se hablara sobre la fachada del Palacio de Najas y Parque Borja Yerovi, Castillos de la calle Roca. | I79: Cultural | J79: 3 | K79: 2 KM | L79: 2825 | M79: MEDIA | N79: https://www.google.com/maps/d/edit?mid=1gYHfsDV8ZGW80nCp8-VrNXxny9wZFWU&usp=sharing | O79: Palacio de la Circasiana | P79: Palacio Mena | Q79: Parque Julio Andrade | R79: Palacio Najas | S79: Parque Borja Yerovi
A80: 079 | B80: ACTIVO | C80: =CONCATENATE(VLOOKUP($D80,CODIFICACIÓN_RUTA!$B$2:$C$3,2,0),MID($F80,1,1)&MID($F80,6,1),VLOOKUP($E80,CODIFICACIÓN_RUTA!$E$2:$F$10,2,0),$A80) -> 01RB01079 | D80: URBANO | E80: Centro Histórico | F80: RUTA BICENTENARIO HISTÓRICO PARA NIÑOS | G80: RUTAS CON POTENCIAL | H80: Podremos disfrutar de estación de Chimbacalle donde se ubica un busto del General Eloy Alfaro, visitaremos los Molinos Royal, cuyo origen data del siglo XX, Museo Interactivo de Ciencias donde funciono "La Industrial" fábrica de hilados y tejidos de algodón. | I80: Cultural | J80: 2.5 | K80: 1 KM | L80: 2830 | M80: BAJA | N80: https://www.google.com/maps/d/edit?mid=1sDe51LdH2uZOsYF8tRHJFBKnthwWTww&usp=sharing | O80: Ferrocarril de Chimbacalle | P80: Museo Interactivo de Ciencias
A81: 080 | B81: ACTIVO | C81: =CONCATENATE(VLOOKUP($D81,CODIFICACIÓN_RUTA!$B$2:$C$3,2,0),MID($F81,1,1)&MID($F81,6,1),VLOOKUP($E81,CODIFICACIÓN_RUTA!$E$2:$F$10,2,0),$A81) -> 01RB01080 | D81: URBANO | E81: Centro Histórico | F81: RUTA BICENTENARIO EN EL YAKU PARA NIÑOS | G81: RUTAS CON POTENCIAL | H81: Visitaremos lo antiguos tanques de agua de la Ciudad de Quito y disfrutaremos de la obre de títeres abuelita Lila. | I81: Cultural | J81: 2.5 | K81: 1 KM | L81: 2830 | M81: BAJA | N81: https://www.google.com/maps/d/u/0/edit?mid=1vWEtGhe7P65WqbX3pSe67yJqluqHRlk&usp=sharing | O81: Yaku Parque Mueso del Agua
A82: 081 | B82: ACTIVO | C82: =CONCATENATE(VLOOKUP($D82,CODIFICACIÓN_RUTA!$B$2:$C$3,2,0),MID($F82,1,1)&MID($F82,6,1),VLOOKUP($E82,CODIFICACIÓN_RUTA!$E$2:$F$10,2,0),$A82) -> 01RC01081 | D82: URBANO | E82: Centro Histórico | F82: RUTA CENTRO HISTÓRICO NOCTURNO | G82: RUTAS CONSOLIDADAS | H82: Visitaremos la Basílica del Voto Nacional y sus cúpulals, luego realizaremos un walking tpur en la Plaza Grande, San Francisco - Cúpulas de La Compañia | I82: Cultural | J82: 5 | K82: 17 KM | L82: 3100 | M82: BAJA | N82: https://www.google.com/maps/d/edit?mid=1YCG_VTUKrefYBUE7KVJMbf0tNDCgth4&usp=sharing | O82: Basílica del Voto Nacional | P82: Plaza Grande | Q82: Plaza de San Francisco | R82: Iglesia Compañía de Jesús
A83: 082 | B83: ACTIVO | C83: =CONCATENATE(VLOOKUP($D83,CODIFICACIÓN_RUTA!$B$2:$C$3,2,0),MID($F83,1,1)&MID($F83,6,1),VLOOKUP($E83,CODIFICACIÓN_RUTA!$E$2:$F$10,2,0),$A83) -> 01RT01082 | D83: URBANO | E83: Centro Histórico | F83: RUTA TALLER DE COMETAS | G83: RUTAS CON POTENCIAL | H83: Junto con personajes como el pregonero y la hierbatera conoceremos un poco de la historia del Quito antiguo y a su vez realizaremos un taller de cometas. | I83: Cultural | J83: 3 | K83: 0.7 KM | L83: 2850 | M83: BAJA | N83: https://www.google.com/maps/d/u/0/edit?mid=145_jTKCXwDFcMHz0CXGAV4sNeCUM8iE&usp=sharing | O83: Centro Cultural Itchimbía
A84: 083 | B84: ACTIVO | C84: =CONCATENATE(VLOOKUP($D84,CODIFICACIÓN_RUTA!$B$2:$C$3,2,0),MID($F84,1,1)&MID($F84,6,1),VLOOKUP($E84,CODIFICACIÓN_RUTA!$E$2:$F$10,2,0),$A84) -> 01RS01083 | D84: URBANO | E84: Centro Histórico | F84: RUTA SAN MARCOS | G84: RUTAS CON POTENCIAL | H84: Recorrido te hará conocer y entender la verdadera historia Manuela Sáenz, y su aporte al proceso de Independencia y a la construcción de la actual identidad ecuatoriana. | I84: Cultural | J84: 7 | K84: 101 KM | L84: 2825 | M84: BAJA | N84: https://www.google.com/maps/d/u/0/edit?mid=1_mcpKqQpqYRsi5rHqhW00-E1Ux7WSbE&usp=sharing | O84: Casa Museo Manuela Sáenz | P84: Iglesia de San Marcos | Y84: Artífice coffe Hula Cafetería - Pastelería La 5 paila del diablo
A85: 084 | B85: ACTIVO | C85: =CONCATENATE(VLOOKUP($D85,CODIFICACIÓN_RUTA!$B$2:$C$3,2,0),MID($F85,1,1)&MID($F85,6,1),VLOOKUP($E85,CODIFICACIÓN_RUTA!$E$2:$F$10,2,0),$A85) -> 01RL01084 | D85: URBANO | E85: Centro Histórico | F85: RUTA LA GRAN MASACRE DE QUITO | G85: RUTAS CON POTENCIAL | H85: Dentro del museo disfrutaremos de teatralizados sobre aconteciemiento del 9 y 10 de agosto de 1809, respresentación del 2 de agosto de 1810 y la degustación de un canelazo. | I85: Histórica | J85: 3 | K85: 1 KM | L85: 2850 | M85: BAJA | N85: https://www.google.com/maps/d/u/0/edit?mid=1bBCHY7_0P_6Y551_wl6EghIt_ZW3HOo&usp=sharing | O85: Iglesia El Tejar
A86: 085 | B86: ACTIVO | C86: =CONCATENATE(VLOOKUP($D86,CODIFICACIÓN_RUTA!$B$2:$C$3,2,0),MID($F86,1,1)&MID($F86,6,1),VLOOKUP($E86,CODIFICACIÓN_RUTA!$E$2:$F$10,2,0),$A86) -> 01RS01085 | D86: URBANO | E86: Centro Histórico | F86: RUTA SAN MARCOS + GASTRONOMÍA | G86: RUTAS CON POTENCIAL | H86: Recorreremos este barrio tradicional donde disfrutaremos de platos y bebidas traicionales, además de conocer lugares emblemáticos de este icónico barrio. | I86: Gastronómica | J86: 7 | K86: 101 KM | L86: 2825 | M86: BAJA | N86: https://www.google.com/maps/d/u/0/edit?mid=1oxY5cC8bd65eJjpfJSyxv93bnaaouA0&usp=sharing | O86: Iglesia de San Marcos | P86: Casa Museo Manuela Sáenz | Y86: La 5 paila del diablo. Coffe Catana Bar Hula Hotel Illa
A87: 086 | B87: ACTIVO | C87: =CONCATENATE(VLOOKUP($D87,CODIFICACIÓN_RUTA!$B$2:$C$3,2,0),MID($F87,1,1)&MID($F87,6,1),VLOOKUP($E87,CODIFICACIÓN_RUTA!$E$2:$F$10,2,0),$A87) -> 01RS01086 | D87: URBANO | E87: Centro Histórico | F87: RUTA SENSORIAL | G87: RUTAS CON POTENCIAL | H87: Conoceremos la historia del conjunto arquitéctonico de la Plaza Grande, visitaremos la iglesia, convento, museo, coro y torres de la Iglesia. Degustaremos chocolate en Yumbo Chocolate Urbano. | I87: Cultural | J87: 6 | K87: 46 KM | L87: 2800 | M87: BAJA | N87: https://www.google.com/maps/d/u/0/edit?mid=1EAACwtmjJS13s1hYj-N0V2fsovXlI3o&usp=sharing | O87: Plaza Grande | P87: Museo Fray Pedro Gocial San Francisco | Y87: Yumbo Chocolate Urbano
A88: 087 | B88: ACTIVO | C88: =CONCATENATE(VLOOKUP($D88,CODIFICACIÓN_RUTA!$B$2:$C$3,2,0),MID($F88,1,1)&MID($F88,6,1),VLOOKUP($E88,CODIFICACIÓN_RUTA!$E$2:$F$10,2,0),$A88) -> 01PR01087 | D88: URBANO | E88: Centro Histórico | F88: PESEBRES MONACALES I | G88: RUTAS CON POTENCIAL | H88: Visitaremos los pesebres del: Monasterio de Santa Clara, que posee imagenes de la escuela quiteña, Museo Fray Pedro Gocial, donde observaremos los pesebres que participan en la exposicion de pesebres que se realiza cada año. | I88: Cultural | J88: 3 | K88: 1.5 KM | L88: 2800 | M88: BAJA | N88: https://www.google.com/maps/d/u/0/edit?mid=1EmPg9cGsjwS7ulvX9GLc0IViS2DimW0&usp=sharing | O88: Iglesia de Santa Clara | P88: Museo Fray Pedro Gocial San Francisco | Q88: Museo del Carmen Alto
A89: 088 | B89: ACTIVO | C89: =CONCATENATE(VLOOKUP($D89,CODIFICACIÓN_RUTA!$B$2:$C$3,2,0),MID($F89,1,1)&MID($F89,6,1),VLOOKUP($E89,CODIFICACIÓN_RUTA!$E$2:$F$10,2,0),$A89) -> 01PR01088 | D89: URBANO | E89: Centro Histórico | F89: PESEBRES MONUMENTALES I | G89: RUTAS CON POTENCIAL | H89: Visitaremos el pesebre más grande de América ubicado en la Catedral Primada de Quito, además conceremos sobre sobre la Plaza Grande y disfrutaremos de uno de los pesebres más antiguos de Quito | I89: Cultural | J89: 3 | K89: 1 KM | L89: 2800 | M89: BAJA | N89: https://www.google.com/maps/d/u/0/edit?mid=11q0oAOvkbeHSlXasS8NTksPBpGZyg24&usp=sharing | O89: Convento del Carmen Bajo | P89: Plaza Grande | Q89: Catedral Metropolitana de Quito
A90: 089 | B90: ACTIVO | C90: =CONCATENATE(VLOOKUP($D90,CODIFICACIÓN_RUTA!$B$2:$C$3,2,0),MID($F90,1,1)&MID($F90,6,1),VLOOKUP($E90,CODIFICACIÓN_RUTA!$E$2:$F$10,2,0),$A90) -> 01CI01089 | D90: URBANO | E90: Centro Histórico | F90: CIRCUITO 1. PLAZA DE SAN FRANCISCO | G90: RUTAS POR FORTALECER | H90: Visitaremos espacios como el Mercado de San Francisco, lapalza de San Francisco (Antiguo tianguez precolombino), Iglesia de San Francisco, museo y cervecería. Degustaremos de chocolate en Yumbos chocolatería. | I90: Gastronómica | J90: 3 | K90: 0.98 KM | L90: 2850 | M90: BAJA | N90: https://www.google.com/maps/d/u/0/edit?mid=16Z4-uRqUTXaRCR3EMGLNlwa0NTCI7ho&usp=sharing | O90: Mercado de San Francisco | P90: Plaza de San Francisco | Q90: Museo Fray Pedro Gocial San Francisco | R90: Plaza Grande | Y90: Yumbos Chocolatería
A91: 090 | B91: ACTIVO | C91: =CONCATENATE(VLOOKUP($D91,CODIFICACIÓN_RUTA!$B$2:$C$3,2,0),MID($F91,1,1)&MID($F91,6,1),VLOOKUP($E91,CODIFICACIÓN_RUTA!$E$2:$F$10,2,0),$A91) -> 01CI01090 | D91: URBANO | E91: Centro Histórico | F91: CIRCUITO 2. PLAZA GRANDE | G91: RUTAS POR FORTALECER | H91: Degustaremos de dulces tradiconales como las colaciones de la Cruz Verde, en la cafetería modelo, disfrutaremos de bocaditos envueltos y chocolate en el museo del cacao, además de visitar la iglesia de La Compañia y la Plaza Grande. | I91: Gastronómica | J91: 3 | K91: 1.5 KM | L91: 2850 | M91: BAJA | N91: https://www.google.com/maps/d/u/0/edit?mid=14Csxasd1VjSXvD4KP4spCYki-WKX6V4&usp=sharing | O91: Iglesia Compañía de Jesús | P91: Plaza Grande | Y91: Colaciones Cruz Verde Cafetería Modelo República del Cacao
A92: 091 | B92: ACTIVO | C92: =CONCATENATE(VLOOKUP($D92,CODIFICACIÓN_RUTA!$B$2:$C$3,2,0),MID($F92,1,1)&MID($F92,6,1),VLOOKUP($E92,CODIFICACIÓN_RUTA!$E$2:$F$10,2,0),$A92) -> 01CI01091 | D92: URBANO | E92: Centro Histórico | F92: CIRCUITO 3. PLAZA DE SANTO DOMINGO | G92: RUTAS POR FORTALECER | H92: Visitaremos el museo Fray Pedron Bedón y su arte quiteño, heladería Dulce Placer, que rescata más de 180 sabores de nuestra tierra, la hojalatería Silva en donde observaremos como la hojaata se transforma en distintos juguetes, taller de taraceado donde ´pdremos observar la forja de diferentes muebles con esta técnica. | I92: Gastronómica | J92: 3 | K92: 0.3 KM | L92: 2850 | M92: BAJA | N92: https://www.google.com/maps/d/u/0/edit?mid=1-pnJR_gZN15UERRjGn3YWlSkTY87sU4&usp=sharing | O92: Museo de Santo Domingo Fray Pedro Bedón | P92: Plaza Grande | Y92: Casa 925 Altamira
A93: 092 | B93: ACTIVO | C93: =CONCATENATE(VLOOKUP($D93,CODIFICACIÓN_RUTA!$B$2:$C$3,2,0),MID($F93,1,1)&MID($F93,6,1),VLOOKUP($E93,CODIFICACIÓN_RUTA!$E$2:$F$10,2,0),$A93) -> 01CI01092 | D93: URBANO | E93: Centro Histórico | F93: CIRCUITO 4. COCINA DE VANGUARDIA EN SAN MARCOS | G93: RUTAS POR FORTALECER | H93: Podremos conocer sobre la historia de Manuela Saenz en la casa museo que lleva su nombre, seremos parte de los talleres artesanales de San Marcos, y una clase de cocina en el Restaurante Ines. | I93: Gastronómica | J93: 3 | K93: 0.2 KM | L93: 2850 | M93: BAJA | N93: https://www.google.com/maps/d/u/0/edit?mid=1h4M2N4KahZ4CFLyhfUwEocJDMtbbhBo&usp=sharing | O93: Casa Museo Manuela Sáenz | Y93: Casa 925 Talleres artesanales San Marcos Restaurante Ines
A94: 093 | B94: ACTIVO | C94: =CONCATENATE(VLOOKUP($D94,CODIFICACIÓN_RUTA!$B$2:$C$3,2,0),MID($F94,1,1)&MID($F94,6,1),VLOOKUP($E94,CODIFICACIÓN_RUTA!$E$2:$F$10,2,0),$A94) -> 01CI01093 | D94: URBANO | E94: Centro Histórico | F94: CIRCUITO 5. CATA EN EL BARRIO SAN MARCOS | G94: RUTAS CON POTENCIAL | H94: Conoceremos la Iglesia y parque de San Marcos, donde conoceremos sobre la historia y tradición de este barrio patrimonial, visitaremos talleres artesanales y tasting room en Hula Restaurant. | I94: Gastronómica | J94: 3 | K94: 0.3 KM | L94: 2850 | M94: BAJA | N94: https://www.google.com/maps/d/u/0/edit?mid=1eEltaXIEvSDHGEGm6Re9KEhpj0lXNys&usp=sharing | O94: Iglesia de Santa Clara
A95: 094 | B95: ACTIVO | C95: =CONCATENATE(VLOOKUP($D95,CODIFICACIÓN_RUTA!$B$2:$C$3,2,0),MID($F95,1,1)&MID($F95,6,1),VLOOKUP($E95,CODIFICACIÓN_RUTA!$E$2:$F$10,2,0),$A95) -> 01CI01094 | D95: URBANO | E95: Centro Histórico | F95: CIRCUITO 6. BASÍLICA Y EXPERIENCIA GASTRONÓMICA "QUITEÑISIMA" | G95: RUTAS POR FORTALECER | H95: Recorreremos las torres de la Basílica del Voto Nacional, las cúpulas de la Iglesia de Santa Bárbara, el mercado central, degustaremos de las tradicionales "Corvinas de Gloria", el palacio del batido y porbaremos un plato exótico como es la colada de Churos. | I95: Gastronómica | J95: 3 | K95: 0.8 KM | L95: 2850 | M95: BAJA | N95: https://www.google.com/maps/d/u/0/edit?mid=1pvYjVFww8Q7Ib1SvXB8lT3QI2BHj3Ag&usp=sharing | O95: Basílica del Voto Nacional | P95: Iglesia de Santa Bárbara | Q95: Mercado Central | Y95: "Las corvinas de Gloria" El palacio del Batido Colada de Churos
A96: 095 | B96: ACTIVO | C96: =CONCATENATE(VLOOKUP($D96,CODIFICACIÓN_RUTA!$B$2:$C$3,2,0),MID($F96,1,1)&MID($F96,6,1),VLOOKUP($E96,CODIFICACIÓN_RUTA!$E$2:$F$10,2,0),$A96) -> 01CI01095 | D96: URBANO | E96: Centro Histórico | F96: CIRCUITO 7. BASÍLICA Y SABORES TRADICIONALES GOURMET | G96: RUTAS POR FORTALECER | H96: Visitaremos la Basílica y sus torres de estilo neogótico, degustaremos y aprenderemos sobre la producción de pasta de cacao junto con Chez Tiff, en la Chacotta disfrutaremos de una copa de vino y pizza que combina las técnicas de la alta cocina con un menú típico ecuatoriano. | I96: Gastronómica | J96: 5 | K96: 1.8 KM | L96: 2850 | M96: MEDIA | N96: https://www.google.com/maps/d/u/0/edit?mid=1U_8PK-WF0AO7UmHQax5wYmbG33eUtQs&usp=sharing | O96: Basílica del Voto Nacional | Y96: Chez Tiff Chacotta
A97: 096 | B97: ACTIVO | C97: =CONCATENATE(VLOOKUP($D97,CODIFICACIÓN_RUTA!$B$2:$C$3,2,0),MID($F97,1,1)&MID($F97,6,1),VLOOKUP($E97,CODIFICACIÓN_RUTA!$E$2:$F$10,2,0),$A97) -> 01CI01096 | D97: URBANO | E97: Centro Histórico | F97: CIRCUITO 8. CENTRO HISTÓRICO - TEATRO BOLÍVAR | G97: RUTAS CON POTENCIAL | H97: Empezaremos nuestro recorrido con la visita a la C ruz Verde donde podremos disfrutar de golosinas tradicionales, en el Teatro Bolívar podremos conocer la histria de este edifcio patrimonial, en Sacrum Restaurant conoceremos sobre la comida ecuatoriana de vanguardia y licores. Pizza S.A. quienes elaboran su comida con productos ecuatoriane e innovacion en su uso. | I97: Gastronómica | J97: 5 | K97: 1.8 KM | L97: 2850 | M97: MEDIA | N97: https://www.google.com/maps/d/u/0/edit?mid=1f42VkJGbxe0nJ4BFCFSgVaKIMefWVbc&usp=sharing | O97: Plaza de San Francisco | P97: Teatro Bolívar | Y97: Sacrum Restaurant Pizza SA.
A98: 097 | B98: ACTIVO | C98: =CONCATENATE(VLOOKUP($D98,CODIFICACIÓN_RUTA!$B$2:$C$3,2,0),MID($F98,1,1)&MID($F98,6,1),VLOOKUP($E98,CODIFICACIÓN_RUTA!$E$2:$F$10,2,0),$A98) -> 01CI02097 | D98: URBANO | E98: La Mariscal | F98: CIRCUITO 1. IDENTIDAD CULINARIA Y CHOCOLATE | G98: RUTAS POR FORTALECER | H98: Podrán explorar uno de los mercados tradicionales de Quito, durante 3 horas podrán disfrutar de un menú degustación en el restaurante Quitu Identidad y junto con Paccari podremos degustar de sus deliciosos chcoaletes. | I98: Gastronómica | J98: 4 | K98: 0.5 KM | L98: 2850 | M98: BAJA | N98: https://www.google.com/maps/d/u/0/edit?mid=1kYPvatl4ZhuuOscTGsSNO-tRNnanqKg&usp=sharing | O98: Mercado la Floresta | Y98: Restaurante Quitu Identidad Paccari casa de experiencias
A99: 098 | B99: ACTIVO | C99: =CONCATENATE(VLOOKUP($D99,CODIFICACIÓN_RUTA!$B$2:$C$3,2,0),MID($F99,1,1)&MID($F99,6,1),VLOOKUP($E99,CODIFICACIÓN_RUTA!$E$2:$F$10,2,0),$A99) -> 02CI04098 | D99: RURAL | E99: Parroquias Equinocciales | F99: CIRCUITO 1. LOS SABORES DE LA MITAD DEL MUNDO | G99: RUTAS POR FORTALECER | H99: Visitaremos Ciudad Mitad del Mundo la plaza del cacao y cata de café Guayasamín, ademas de degustación de cerveza y disfrutaremos de un recorrido en el Museo Agave. | I99: Gastronómica | J99: 5 | K99: 7.2 KM | L99: 2400 | M99: BAJA | N99: https://www.google.com/maps/d/u/0/edit?mid=1X7YpwJ5Olomfa9YHOXfrK9KsJ5gbPXA&usp=sharing | O99: Ciudad Mitad del Mundo | P99: Casa Agave Ecuador | Y99: Santana Brewing Company
A100: 099 | B100: ACTIVO | C100: =CONCATENATE(VLOOKUP($D100,CODIFICACIÓN_RUTA!$B$2:$C$3,2,0),MID($F100,1,1)&MID($F100,6,1),VLOOKUP($E100,CODIFICACIÓN_RUTA!$E$2:$F$10,2,0),$A100) -> 02CI04099 | D100: RURAL | E100: Parroquias Equinocciales | F100: CIRCUITO 2. SABORES Y NATURALEZA EN LA MITAD DEL MUNDO | G100: RUTAS POR FORTALECER | H100: Visitaremos el complejo turístico Mitad del Mundo, el cráter Pululahua, disfrutaremos del PatioOrganic Traditional Food, Casa Agave disfrutaremos del recorrido por el Museo del Agave | I100: Gastronómica | J100: 6 | K100: 30.40 KM | L100: 2400 | M100: BAJA | N100: https://www.google.com/maps/d/u/0/edit?mid=1pgvi30KUqFrInUqTCFyUngi5s8UJSso&usp=sharing | O100: Ciudad Mitad del Mundo | P100: Reserva Geobotánica El Pululahua | Q100: Casa Agave Ecuador | Y100: Patio Organic Traditional Food
...

Sheet Hoja1
C1: # | D1: TICKET | E1: ASUNTO | F1: ESTADO | G1: FECHA CIERRE | H1: FECHA APERTURA | I1: PRIORIDAD | J1: SOLICITANTE | K1: TÉCNICO ASIGNADO | L1: CATEGORÍA | M1: OBSERVACIÓN
C2: =ROW()-1 -> 1 | D2: 2 055 | E2: error sistema de facturación | F2: Cerrado | G2: 46140.384 | H2: 46140.378 | I2: Media | J2: Guamán Lizano Cristina Alejandra | K2: Chiluisa Armas Luis Patricio | L2: Soporte de aplicaciones de negocio > ERP Olympo
C3: =ROW()-1 -> 2 | D3: 2 054 | E3: SIN NÚMERO DE PREDIO | F3: En curso (asignado) | G3: 46140.361 | H3: 46140.349 | I3: Media | J3: Simbaña Chancusig Cristina de los Angeles | K3: Medina Iturre Edgar Fabricio | L3: Soporte de aplicaciones de negocio > SICET
C4: =ROW()-1 -> 3 | D4: 2 053 | E4: Acceso al NAS del Financiero | F4: Nuevo | G4: 46139.714 | H4: 46139.714 | I4: Media | J4: Solórzano Bomboza María Fernanda | K4: Medina Iturre Edgar Fabricio | L4: Servicios de Infraestructura y Seguridad > Gestión de Identidad y Acceso
C5: =ROW()-1 -> 4 | D5: 2 052 | E5: NÚMERO DE PREDIO VACIO | F5: En curso (asignado) | G5: 46139.688 | H5: 46139.661 | I5: Media | J5: Martínez Arias Adriana Elizabeth | K5: Medina Iturre Edgar Fabricio | L5: Soporte de aplicaciones de negocio > SICET
C6: =ROW()-1 -> 5 | D6: 2 051 | E6: SOLICITUD DE SOPORTE | F6: Cerrado | G6: 46139.647 | H6: 46139.598 | I6: Media | J6: Rea Sopalo Washington Manuel | K6: Chiluisa Armas Luis Patricio | L6: Soporte de aplicaciones de negocio > ERP Olympo
C7: =ROW()-1 -> 6 | D7: 2 050 | E7: Solicitud de apertura de tickets: Socialización de procesos de actualización y pasos a producción – ERP Olympo | F7: Resuelto | G7: 46139.467 | H7: 46139.449 | I7: Media | J7: Pacha Andrango Carlos Javier | K7: Chiluisa Armas Luis Patricio | L7: Soporte de aplicaciones de negocio > ERP Olympo
C8: =ROW()-1 -> 7 | D8: 2 049 | E8: NÚMERO DE PREDIO VACIO | F8: En curso (asignado) | G8: 46139.451 | H8: 46139.421 | I8: Media | J8: Martínez Arias Adriana Elizabeth | K8: Medina Iturre Edgar Fabricio | L8: Soporte de aplicaciones de negocio > SICET
C9: =ROW()-1 -> 8 | D9: 2 047 | E9: RV: Receptor correo administrativo | F9: Cerrado | G9: 46139.401 | H9: 46139.358 | I9: Media | J9: Pacha Andrango Carlos Javier | K9: Chiluisa Armas Luis Patricio | L9: Gestión de Software de Ofimática y Colaboración > Correo Electrónico Institucional
C10: =ROW()-1 -> 9 | D10: 2 048 | E10: RV: Solicitud de cambio de equipo electrónico – Coordinación de Gerencia | F10: En curso (asignado) | G10: 46139.374 | H10: 46139.37 | I10: Media | J10: Pacha Andrango Carlos Javier | K10: Chiluisa Armas Luis Patricio | L10: Soporte a Equipos de Cómputo y Periféricos > Computadora o laptop
C11: =ROW()-1 -> 10 | D11: 2 043 | E11: INSISTENCIA: [GLPI #0002038] ✔ Solicitud registrada | F11: Cerrado | G11: 46139.356 | H11: 46136.498 | I11: Media | J11: Ponce Solórzano Verónica Yolanda | K11: glpi | L11: Soporte de aplicaciones de negocio > ERP Olympo
C12: =ROW()-1 -> 11 | D12: 2 046 | E12: Pantallas Tiendas Quito | F12: En curso (asignado) | G12: 46139.356 | H12: 46136.67 | I12: Media | J12: Sánchez Uquillas Gabriel Sebastián | K12: Medina Iturre Edgar Fabricio | L12: Soporte a Equipos de Cómputo y Periféricos > Pantallas digitales
C13: =ROW()-1 -> 12 | D13: 2 011 | E13: RV: Vinculación de personal 21 de abril de 2026 | F13: Cerrado | G13: 46139.356 | H13: 46133.39 | I13: Media | J13: Pacha Andrango Carlos Javier | K13: Chiluisa Armas Luis Patricio | L13: Servicios de Infraestructura y Seguridad > Gestión de Identidad y Acceso
C14: =ROW()-1 -> 13 | D14: 2 045 | E14: CAMBIO DE PREDIO | F14: Cerrado | G14: 46138.666 | H14: 46136.645 | I14: Media | J14: Martínez Arias Adriana Elizabeth
C15: =ROW()-1 -> 14 | D15: 2 044 | E15: CAMBIO DE CORREO ELECTRONICO | F15: Cerrado | G15: 46138.666 | H15: 46136.599 | I15: Media | J15: Martínez Arias Adriana Elizabeth | K15: Medina Iturre Edgar Fabricio | L15: Soporte de aplicaciones de negocio > SICET
C16: =ROW()-1 -> 15 | D16: 2 038 | E16: SEGUIMIENTO: ESTADO DE CUENTA CONSEJO NACIONAL ELECTORAL DELEGACION PROVINCIAL DE PICHINCHA : REPORTE INCIDENCIA | F16: Cerrado | G16: 46136.498 | H16: 46135.403 | I16: Media | J16: Ponce Solórzano Verónica Yolanda
C17: =ROW()-1 -> 16 | D17: 2 014 | E17: RV: ACTUALIZACIÓN DE PREDIO | F17: Cerrado | G17: 46136.375 | H17: 46133.456 | I17: Media | J17: Pacha Andrango Carlos Javier | K17: Medina Iturre Edgar Fabricio | L17: Soporte de aplicaciones de negocio > SICET
C18: =ROW()-1 -> 17 | D18: 2 021 | E18: CAMBIO DE CORREO ELECTRÓNICO | F18: Cerrado | G18: 46136.375 | H18: 46133.537 | I18: Media | J18: Simbaña Chancusig Cristina de los Angeles | K18: Medina Iturre Edgar Fabricio | L18: Soporte de aplicaciones de negocio > SICET
C19: =ROW()-1 -> 18 | D19: 2 024 | E19: NÚMERO DE PREDIO VACIO | F19: Cerrado | G19: 46136.375 | H19: 46133.589 | I19: Media | J19: Simbaña Chancusig Cristina de los Angeles | K19: Medina Iturre Edgar Fabricio | L19: Soporte de aplicaciones de negocio > SICET
C20: =ROW()-1 -> 19 | D20: 2 025 | E20: ACTUALIZACION DE CORREO ELECTONICO | F20: Cerrado | G20: 46136.374 | H20: 46133.636 | I20: Media | J20: Bonilla Benavides Ana Cristina | K20: Medina Iturre Edgar Fabricio | L20: Soporte de aplicaciones de negocio > SICET
C21: =ROW()-1 -> 20 | D21: 2 026 | E21: ACCESO CARPETA DIRECTORIO | F21: Cerrado | G21: 46136.374 | H21: 46133.675 | I21: Media | J21: Rosero Marcillo María José | K21: Medina Iturre Edgar Fabricio | L21: Servicios de Infraestructura y Seguridad > Gestión de Identidad y Acceso
C22: =ROW()-1 -> 21 | D22: 2 028 | E22: DUPLICACIÓN DE REGISTRO TURÍSTICO | F22: Cerrado | G22: 46136.374 | H22: 46133.691 | I22: Media | J22: Simbaña Chancusig Cristina de los Angeles | K22: Medina Iturre Edgar Fabricio | L22: Soporte de aplicaciones de negocio > SICET
C23: =ROW()-1 -> 22 | D23: 2 027 | E23: RE: ACCESO CARPETA DIRECTORIO | F23: Cerrado | G23: 46136.374 | H23: 46133.68 | I23: Media | J23: Bucheli García Franklin Gustabo | K23: Medina Iturre Edgar Fabricio | L23: Servicios de Infraestructura y Seguridad > Gestión de Identidad y Acceso
C24: =ROW()-1 -> 23 | D24: 2 029 | E24: RV: DUPLICACIÓN DE REGISTRO TURÍSTICO | F24: Cerrado | G24: 46136.374 | H24: 46133.692 | I24: Media | J24: Simbaña Chancusig Cristina de los Angeles | K24: Medina Iturre Edgar Fabricio | L24: Soporte de aplicaciones de negocio > SICET
C25: =ROW()-1 -> 24 | D25: 2 030 | E25: CAMBIO DE CORREO ELECTRÓNICO | F25: Cerrado | G25: 46136.374 | H25: 46134.474 | I25: Media | J25: Simbaña Chancusig Cristina de los Angeles | K25: Medina Iturre Edgar Fabricio | L25: Soporte de aplicaciones de negocio > SICET
C26: =ROW()-1 -> 25 | D26: 2 033 | E26: ACTUALIZACIÓN DE LUAE CODIGO CIUU | F26: Cerrado | G26: 46136.373 | H26: 46134.551 | I26: Media | J26: Simbaña Chancusig Cristina de los Angeles | K26: Medina Iturre Edgar Fabricio | L26: Soporte de aplicaciones de negocio > SICET
C27: =ROW()-1 -> 26 | D27: 2 035 | E27: RV: REGISTRO TURÍSTICO EUROVIAJES ( RUC 1791226054001) | F27: Cerrado | G27: 46136.373 | H27: 46134.649 | I27: Media | J27: Simbaña Chancusig Cristina de los Angeles | K27: Medina Iturre Edgar Fabricio | L27: Soporte de aplicaciones de negocio > SICET
C28: =ROW()-1 -> 27 | D28: 2 036 | E28: RV: REGISTRO TURÍSTICO EUROVIAJES ( RUC 1791226054001) | F28: Cerrado | G28: 46136.373 | H28: 46134.649 | I28: Media | J28: Simbaña Chancusig Cristina de los Angeles | K28: Medina Iturre Edgar Fabricio | L28: Soporte de aplicaciones de negocio > SICET
... C41: =ROW()-1 -> 40 | D41: 2 023 | E41: Solicitud de modificación de estado de reforma presupuestaria | F41: Cerrado | G41: 46133.603 | H41: 46133.586 | I41: Media | J41: López Vásquez Jheisy Germania | K41: Chiluisa Armas Luis Patricio | L41: Soporte de aplicaciones de negocio > ERP Olympo
C42: =ROW()-1 -> 41 | D42: 2 022 | E42: Solicitud de modificación de estado de reforma presupuestaria | F42: Cerrado | G42: 46133.594 | H42: 46133.576 | I42: Media | J42: López Vásquez Jheisy Germania | K42: Chiluisa Armas Luis Patricio
C43: =ROW()-1 -> 42 | D43: 2 015 | E43: SOPORTE TECNICO NOTAS DE CREDITO: REPORTE INCIDENCIA (14-04-2024) | F43: Cerrado | G43: 46133.593 | H43: 46133.478 | I43: Media | J43: Ponce Solórzano Verónica Yolanda | K43: Chiluisa Armas Luis Patricio | L43: Soporte de aplicaciones de negocio > ERP Olympo
C44: =ROW()-1 -> 43 | D44: 2 020 | E44: SOPORTE TECNICO NOTAS DE CREDITO: REPORTE INCIDENCIA (14-04-2024) | F44: Cerrado | G44: 46133.592 | H44: 46133.515 | I44: Media | J44: Ponce Solórzano Verónica Yolanda
C45: =ROW()-1 -> 44 | D45: 2 013 | E45: RV: Proceso Reforma | F45: Cerrado | G45: 46133.461 | H45: 46133.456 | I45: Media | J45: Pacha Andrango Carlos Javier
C46: =ROW()-1 -> 45 | D46: 2 008 | E46: CAMBIO DE CORREO ELECTRÓNICO | F46: Cerrado | G46: 46133.459 | H46: 46132.597 | I46: Alta | J46: Simbaña Chancusig Cristina de los Angeles | K46: Medina Iturre Edgar Fabricio | L46: Soporte de aplicaciones de negocio > SICET
C47: =ROW()-1 -> 46 | D47: 2 010 | E47: Fw: Proceso reforma | F47: Cerrado | G47: 46133.459 | H47: 46132.948 | I47: Media | J47: Pacha Andrango Carlos Javier | K47: Medina Iturre Edgar Fabricio | L47: Soporte de aplicaciones de negocio > Sitra
C48: =ROW()-1 -> 47 | D48: 2 009 | E48: CAMBIO DE CORREO ELECTRÓNICO | F48: Cerrado | G48: 46133.456 | H48: 46132.683 | I48: Media | J48: Simbaña Chancusig Cristina de los Angeles | K48: Medina Iturre Edgar Fabricio | L48: Soporte de aplicaciones de negocio > SICET
C49: =ROW()-1 -> 48 | D49: 2 003 | E49: Publicación Barómetro | F49: Cerrado | G49: 46133.456 | H49: 46132.359 | I49: Media | J49: Utreras Fuentes Ruth Elena | K49: Medina Iturre Edgar Fabricio | L49: Soporte de aplicaciones de negocio > Portal Institución
C50: =ROW()-1 -> 49 | D50: 1 985 | E50: Solicitud de implementación de numeración en la Gaceta Tributaria Digital de la EPMGDTR | F50: Cerrado | G50: 46133.456 | H50: 46128.512 | I50: Media | J50: Tipán Gavilanes Daysi Lizbeth | K50: Medina Iturre Edgar Fabricio | L50: Soporte de aplicaciones de negocio > Portal Institución
C51: =ROW()-1 -> 50 | D51: 2 001 | E51: CAMBIO DE CORREO ELECTRÓNICO | F51: Cerrado | G51: 46133.455 | H51: 46129.63 | I51: Media | J51: Simbaña Chancusig Cristina de los Angeles | K51: Medina Iturre Edgar Fabricio | L51: Soporte de aplicaciones de negocio > SICET
C52: =ROW()-1 -> 51 | D52: 1 969 | E52: Infocus | F52: Cerrado | G52: 46133.455 | H52: 46128.476 | I52: Media | J52: Plaza Chicaiza Karla Gabriela | K52: Medina Iturre Edgar Fabricio | L52: Soporte a Equipos de Cómputo y Periféricos > Proyectores
C53: =ROW()-1 -> 52 | D53: 1 984 | E53: Solicitud de creación de carpeta MICE para archivos digitalizados | F53: Cerrado | G53: 46133.455 | H53: 46128.512 | I53: Media | J53: Cevallos Hidalgo María Gabriela | K53: Medina Iturre Edgar Fabricio | L53: Soporte a Equipos de Cómputo y Periféricos > Impresora
C54: =ROW()-1 -> 53 | D54: 2 000 | E54: CAMBIO DE CORREO ELECTRONICO | F54: Cerrado | G54: 46133.454 | H54: 46129.607 | I54: Alta | J54: Martínez Arias Adriana Elizabeth | K54: Medina Iturre Edgar Fabricio | L54: Soporte de aplicaciones de negocio > SICET
C55: =ROW()-1 -> 54 | D55: 1 999 | E55: Activación de la opción de Informe en el sistema SITRA | F55: Cerrado | G55: 46133.454 | H55: 46129.602 | I55: Media | J55: Cevallos Hidalgo María Gabriela | K55: Medina Iturre Edgar Fabricio | L55: Soporte de aplicaciones de negocio > Sitra
C56: =ROW()-1 -> 55 | D56: 1 998 | E56: DUPLICACION DE REGISTRO TURISTICO | F56: Cerrado | G56: 46133.454 | H56: 46129.463 | I56: Media | J56: Martínez Arias Adriana Elizabeth | K56: Medina Iturre Edgar Fabricio | L56: Soporte de aplicaciones de negocio > SICET
C57: =ROW()-1 -> 56 | D57: 1 994 | E57: CAMBIO DE CORREO ELECTRÓNICO | F57: Cerrado | G57: 46133.454 | H57: 46129.42 | I57: Media | J57: Simbaña Chancusig Cristina de los Angeles | K57: Medina Iturre Edgar Fabricio | L57: Soporte de aplicaciones de negocio > SICET
... C73: =ROW()-1 -> 72 | D73: 1 991 | E73: Solicitud de instalación de programa NITRO en la PC | F73: Cerrado | G73: 46129.478 | H73: 46128.606 | I73: Media | J73: Castillo Castellano Jimmy Bolívar | K73: Chiluisa Armas Luis Patricio | L73: Soporte a Equipos de Cómputo y Periféricos > Otros
C74: =ROW()-1 -> 73 | D74: 1 996 | E74: Facilitacion pantalla táctil | F74: Cerrado | G74: 46129.454 | H74: 46129.42 | I74: Media | J74: Plaza Chicaiza Karla Gabriela
C75: =ROW()-1 -> 74 | D75: 1 993 | E75: Revisión de accesos a respositorios, scanener e imprsiones - Belén Pacheco | F75: Cerrado | G75: 46128.644 | H75: 46128.641 | I75: Media | J75: bpacheco@quito-turismo.gob.ec | K75: Chiluisa Armas Luis Patricio | L75: Servicios de Infraestructura y Seguridad > Gestión de Identidad y Acceso
C76: =ROW()-1 -> 75 | D76: 1 988 | E76: Envío de Sitras | F76: Cerrado | G76: 46128.615 | H76: 46128.606 | I76: Media | J76: Guamán Cornejo Diego Fernando | K76: Chiluisa Armas Luis Patricio | L76: Soporte de aplicaciones de negocio > Sitra
C77: =ROW()-1 -> 76 | D77: 1 990 | E77: Solicitud de soporte de pago de liquidación de haberes | F77: Cerrado | G77: 46128.615 | H77: 46128.606 | I77: Alta | J77: Morales Portuguez David Hernán | K77: Chiluisa Armas Luis Patricio | L77: Soporte de aplicaciones de negocio > ERP Olympo
C78: =ROW()-1 -> 77 | D78: 1 986 | E78: Solicitud de Soporte Tecnico - Modulo de Gestion administrativa | F78: Cerrado | G78: 46128.604 | H78: 46128.512 | I78: Media | J78: Ponce Solórzano Verónica Yolanda | K78: Chiluisa Armas Luis Patricio | L78: Soporte de aplicaciones de negocio > ERP Olympo
C79: =ROW()-1 -> 78 | D79: 1 982 | E79: Solicitud de certificación de ingreso de trámite al sistema SITRA | F79: Cerrado | G79: 46128.59 | H79: 46128.512 | I79: Media | J79: Tipán Gavilanes Daysi Lizbeth
C80: =ROW()-1 -> 79 | D80: 1 977 | E80: Encargo Jefatura Administrativa | F80: Cerrado | G80: 46128.506 | H80: 46128.504 | I80: Media | J80: Carrera Lloré Ana Lucía | K80: Chiluisa Armas Luis Patricio | L80: Soporte de aplicaciones de negocio > Sitra
C81: =ROW()-1 -> 80 | D81: 1 968 | E81: RE: Solicitud de coordinación de reunión telemática | F81: Cerrado | G81: 46128.499 | H81: 46128.476 | I81: Media | J81: Castillo Castellano Jimmy Bolívar | K81: Chiluisa Armas Luis Patricio | L81: Gestión de Software de Ofimática y Colaboración > Teams
C82: =ROW()-1 -> 81 | D82: 1 963 | E82: Solicitud de mantenimiento urgente - Computadora y impresora en oficinas de Seguridad Turística | F82: En curso (asignado) | G82: 46128.495 | H82: 46125.441 | I82: Media | J82: Arboleda Gordillo Paulina Fernanda | K82: Medina Iturre Edgar Fabricio | L82: Soporte a Equipos de Cómputo y Periféricos > Computadora o laptop
C83: =ROW()-1 -> 82 | D83: 1 972 | E83: ASIGANACIÓN DE TRAMITES DE LUAE | F83: Cerrado | G83: 46128.494 | H83: 46128.476 | I83: Alta | J83: Simbaña Chancusig Cristina de los Angeles | K83: Medina Iturre Edgar Fabricio | L83: Soporte de aplicaciones de negocio > SICET
C84: =ROW()-1 -> 83 | D84: 1 965 | E84: asistencia para paso a paso para generar un enlace de ondrive - Gerson Arias | F84: Cerrado | G84: 46128.492 | H84: 46127.431 | I84: Media | J84: Arias Díaz Gerson Fredy | K84: Medina Iturre Edgar Fabricio | L84: Gestión de Software de Ofimática y Colaboración > Onedrive
C85: =ROW()-1 -> 84 | D85: 1 962 | E85: crear directorio online para CCMQ abril 2026 | F85: Cerrado | G85: 46128.492 | H85: 46125.36 | I85: Alta | J85: Rosero Marcillo María José | K85: Medina Iturre Edgar Fabricio
C86: =ROW()-1 -> 85 | D86: 1 975 | E86: CAMBIO DE CORREO ELECTRONICO | F86: Cerrado | G86: 46128.492 | H86: 46128.476 | I86: Alta | J86: Martínez Arias Adriana Elizabeth | K86: Medina Iturre Edgar Fabricio | L86: Soporte de aplicaciones de negocio > SICET
C87: =ROW()-1 -> 86 | D87: 1 976 | E87: DESBLOQUEO DE TRAMITES DE LUAE | F87: Cerrado | G87: 46128.492 | H87: 46128.476 | I87: Alta | J87: Simbaña Chancusig Cristina de los Angeles | K87: Medina Iturre Edgar Fabricio | L87: Soporte de aplicaciones de negocio > SICET
C88: =ROW()-1 -> 87 | D88: 1 974 | E88: CAMBIO DE CORREO ELECTRÓNICO | F88: Cerrado | G88: 46128.492 | H88: 46128.476 | I88: Alta | J88: Simbaña Chancusig Cristina de los Angeles | K88: Medina Iturre Edgar Fabricio | L88: Soporte de aplicaciones de negocio > SICET
C89: =ROW()-1 -> 88 | D89: 1 964 | E89: Revisión de acceso al Olympo actiguo - Verónica Ponce | F89: Cerrado | G89: 46128.492 | H89: 46127.43 | I89: Media | J89: Ponce Solórzano Verónica Yolanda | K89: Medina Iturre Edgar Fabricio | L89: Gestión de Software de Ofimática y Colaboración
C90: =ROW()-1 -> 89 | D90: 1 960 | E90: CAMBIO DE CORREO ELECTRÓNICO | F90: Cerrado | G90: 46128.491 | H90: 46122.688 | I90: Media | J90: Simbaña Chancusig Cristina de los Angeles | K90: Medina Iturre Edgar Fabricio | L90: Soporte de aplicaciones de negocio > SICET
C91: =ROW()-1 -> 90 | D91: 1 958 | E91: Prueba de notificación de correo SITRA | F91: Cerrado | G91: 46128.491 | H91: 46122.455 | I91: Media | J91: Pacha Andrango Carlos Javier | K91: Medina Iturre Edgar Fabricio | L91: Soporte de aplicaciones de negocio > Sitra
C92: =ROW()-1 -> 91 | D92: 1 955 | E92: NÚMERO DE PREDIO VACIO EN SISTEMA SICET | F92: Cerrado | G92: 46128.491 | H92: 46121.472 | I92: Alta | J92: Martínez Arias Adriana Elizabeth | K92: Medina Iturre Edgar Fabricio | L92: Soporte de aplicaciones de negocio > SICET
C93: =ROW()-1 -> 92 | D93: 1 945 | E93: Apoyo a los directores de las áreas técnicas para que compartan sus agendas con Belén Pacheco | F93: Cerrado | G93: 46128.491 | H93: 46120.576 | I93: Media | J93: Pacha Andrango Carlos Javier | K93: Medina Iturre Edgar Fabricio | L93: Gestión de Software de Ofimática y Colaboración > Correo Electrónico Institucional
C94: =ROW()-1 -> 93 | D94: 1 928 | E94: Revisión de sincronización de NAS - usuario Belén Pacheco | F94: Cerrado | G94: 46128.49 | H94: 46119.381 | I94: Media | J94: bpacheco@quito-turismo.gob.ec | K94: Medina Iturre Edgar Fabricio | L94: Servicios de Infraestructura y Seguridad > Gestión de Identidad y Acceso
C95: =ROW()-1 -> 94 | D95: 1 966 | E95: prestamo de laptop - Ximena Ulloa | F95: Cerrado | G95: 46128.401 | H95: 46128.372 | I95: Media | J95: Ulloa loza Ximena Alexandra | K95: glpi | L95: Soporte a Equipos de Cómputo y Periféricos > Computadora o laptop
C96: =ROW()-1 -> 95 | D96: 1 908 | E96: Solicitud de liberación de IPs | F96: Cerrado | G96: 46128.374 | H96: 46113.358 | I96: Media | J96: Baquero Banderas Fabián Alejandro
C97: =ROW()-1 -> 96 | D97: 1 953 | E97: No me permite ingresar al sistema de TH | F97: Cerrado | G97: 46125.606 | H97: 46121.41 | I97: Media | J97: Egas Torres Jorge Eduardo | K97: Chiluisa Armas Luis Patricio | L97: Soporte de aplicaciones de negocio > ERP Olympo
C98: =ROW()-1 -> 97 | D98: 1 957 | E98: solicitud de pantalla táctil | F98: Cerrado | G98: 46125.449 | H98: 46122.361 | I98: Media | J98: Plaza Chicaiza Karla Gabriela | K98: Casa Chanaluisa Alex Wladimir | L98: Soporte a Equipos de Cómputo y Periféricos > Pantallas digitales
C99: =ROW()-1 -> 98 | D99: 1 961 | E99: Solicitud urgente de instalación de firma electrónica EC - Tienda Quito La Mariscal | F99: Cerrado | G99: 46125.435 | H99: 46122.715 | I99: Media | J99: Arboleda Gordillo Paulina Fernanda | K99: Chiluisa Armas Luis Patricio | L99: Servicios de Infraestructura y Seguridad > Gestión de Firma Electrónica
C100: =ROW()-1 -> 99 | D100: 1 959 | E100: RV: Habilitación salida de llamadas externas | F100: Cerrado | G100: 46125.434 | H100: 46122.628 | I100: Media | J100: Pacha Andrango Carlos Javier | K100: Chiluisa Armas Luis Patricio | L100: Servicios de Redes y Conectividad > Telefonía
C101: =ROW()-1 -> 100 | D101: 1 895 | E101: RV: Internet oficina Comercialización | F101: Cerrado | G101: 46122.696 | H101: 46111.663 | I101: Media | J101: Pacha Andrango Carlos Javier | K101: Chiluisa Armas Luis Patricio | L101: Servicios de Redes y Conectividad > Conectividad WIFI
C102: =ROW()-1 -> 101 | D102: 1 912 | E102: Envío de respaldo de correo y sitra abarreno@gmail.com | F102: Cerrado | G102: 46121.694 | H102: 46113.566 | I102: Media | J102: Pacha Andrango Carlos Javier | K102: Chiluisa Armas Luis Patricio | L102: Servicios de Infraestructura y Seguridad > Copias de Seguridad y Recuperación de Información
C103: =ROW()-1 -> 102 | D103: 1 951 | E103: Vinculación de personal | F103: Cerrado | G103: 46121.692 | H103: 46121.397 | I103: Media | J103: Palomino Granda Jessica Fernanda | K103: Chiluisa Armas Luis Patricio | L103: Servicios de Infraestructura y Seguridad > Gestión de Identidad y Acceso
C104: =ROW()-1 -> 103 | D104: 1 956 | E104: RV: Solicitud acceso carpeta compartida MICE | F104: Cerrado | G104: 46121.667 | H104: 46121.656 | I104: Media | J104: Pacha Andrango Carlos Javier | K104: Chiluisa Armas Luis Patricio | L104: Servicios de Infraestructura y Seguridad > Gestión de Identidad y Acceso
C105: =ROW()-1 -> 104 | D105: 1 954 | E105: RV: Vinculación de personal 9 de abril de 2026 | F105: Cerrado | G105: 46121.498 | H105: 46121.469 | I105: Media | J105: Pacha Andrango Carlos Javier | K105: Chiluisa Armas Luis Patricio | L105: Servicios de Infraestructura y Seguridad > Gestión de Identidad y Acceso
C106: =ROW()-1 -> 105 | D106: 1 952 | E106: RV: Solicitud urgente soporte puntos información y seguridad turística | F106: En curso (asignado) | G106: 46121.453 | H106: 46121.403 | I106: Media | J106: Pacha Andrango Carlos Javier | K106: Medina Iturre Edgar Fabricio | L106: Soporte a Equipos de Cómputo y Periféricos > Computadora o laptop
C107: =ROW()-1 -> 106 | D107: 1 946 | E107: ACTUALIZACIÓN DE CORREO ELECTRÓNICO EN SICET | F107: Cerrado | G107: 46121.392 | H107: 46120.639 | I107: Media | J107: Cedeño Gómez Tania Cristina | K107: Medina Iturre Edgar Fabricio | L107: Soporte de aplicaciones de negocio > SICET
C108: =ROW()-1 -> 107 | D108: 1 940 | E108: RV: CAMBIO DE CORREO ELECTRÓNICO | F108: Cerrado | G108: 46121.392 | H108: 46119.646 | I108: Alta | J108: Simbaña Chancusig Cristina de los Angeles | K108: Medina Iturre Edgar Fabricio | L108: Soporte de aplicaciones de negocio > SICET
... C133: =ROW()-1 -> 132 | D133: 1 941 | E133: Solicitud de soporte para aprobacion de costos de ventas y consumo de inventarios. | F133: Cerrado | G133: 46120.7 | H133: 46119.646 | I133: Alta | J133: Monge Castro María Leopoldina | K133: Chiluisa Armas Luis Patricio | L133: Soporte de aplicaciones de negocio > ERP Olympo
C134: =ROW()-1 -> 133 | D134: 1 943 | E134: Arreglo de la impresora de la Jefatura Administrativa | F134: Cerrado | G134: 46120.373 | H134: 46120.361 | I134: Media | J134: Jarrín Cornejo María Belén
C135: =ROW()-1 -> 134 | D135: 1 932 | E135: Revisión de impresora, las hojas salen opacas - Jefatura administrativa | F135: Cerrado | G135: 46119.704 | H135: 46119.465 | I135: Media | J135: Siguencia Guillén Jorge Enrique | K135: Chiluisa Armas Luis Patricio | L135: Soporte a Equipos de Cómputo y Periféricos > Impresora
C136: =ROW()-1 -> 135 | D136: 1 942 | E136: Revisión urgencia de impresora Jefatura Administrativa | F136: Cerrado | G136: 46119.701 | H136: 46119.656 | I136: Media | J136: Jarrín Cornejo María Belén | L136: Soporte a Equipos de Cómputo y Periféricos > Impresora
C137: =ROW()-1 -> 136 | D137: 1 930 | E137: No se enciende el monitor - Diego Guamán | F137: Cerrado | G137: 46119.492 | H137: 46119.458 | I137: Media | J137: Guamán Cornejo Diego Fernando | K137: Chiluisa Armas Luis Patricio | L137: Soporte a Equipos de Cómputo y Periféricos > Periféricos
C138: =ROW()-1 -> 137 | D138: 1 929 | E138: RV: Vinculación de persona 07 de abril de 2026 | F138: Cerrado | G138: 46119.49 | H138: 46119.434 | I138: Media | J138: Pacha Andrango Carlos Javier | K138: Chiluisa Armas Luis Patricio | L138: Servicios de Infraestructura y Seguridad > Gestión de Identidad y Acceso
C139: =ROW()-1 -> 138 | D139: 1 927 | E139: Cambio de clave ERP | F139: Cerrado | G139: 46118.629 | H139: 46118.628 | I139: Media | J139: Lara Salazar Ricardo Rubén | K139: Chiluisa Armas Luis Patricio | L139: Soporte de aplicaciones de negocio > ERP Olympo
C140: =ROW()-1 -> 139 | D140: 1 925 | E140: Revisión de acceso a sitio IESS | F140: Cerrado | G140: 46118.591 | H140: 46118.479 | I140: Media | J140: Pacha Andrango Carlos Javier | K140: Chiluisa Armas Luis Patricio
C141: =ROW()-1 -> 140 | D141: 1 924 | E141: Cambio de firma para Jefatura Financiera | F141: Cerrado | G141: 46118.47 | H141: 46118.458 | I141: Media | J141: Monge Castro María Leopoldina | K141: Chiluisa Armas Luis Patricio | L141: Soporte de aplicaciones de negocio > ERP Olympo
C142: =ROW()-1 -> 141 | D142: 1 923 | E142: Pie de pagina Jefatura Financiera | F142: Cerrado | G142: 46118.45 | H142: 46118.446 | I142: Media | J142: Morales Portuguez David Hernán | K142: Chiluisa Armas Luis Patricio | L142: Soporte de aplicaciones de negocio > ERP Olympo
C143: =ROW()-1 -> 142 | D143: 1 918 | E143: RE: Término de Encargo de la Dirección de Turismo de Negocios y Atracción de Eventos | F143: Cerrado | G143: 46114.61 | H143: 46114.559 | I143: Media | J143: Palomino Granda Jessica Fernanda | K143: Chiluisa Armas Luis Patricio | L143: Soporte de aplicaciones de negocio > Sitra
C144: =ROW()-1 -> 143 | D144: 1 916 | E144: Vinculación de personal | F144: Cerrado | G144: 46114.473 | H144: 46114.378 | I144: Media | J144: Palomino Granda Jessica Fernanda | K144: Chiluisa Armas Luis Patricio | L144: Servicios de Infraestructura y Seguridad > Gestión de Identidad y Acceso
C145: =ROW()-1 -> 144 | D145: 1 915 | E145: Problema en la contabilización de anticipo de sueldos | F145: Cerrado | G145: 46114.383 | H145: 46113.865 | I145: Alta | J145: Monge Castro María Leopoldina | K145: Chiluisa Armas Luis Patricio | L145: Soporte de aplicaciones de negocio > ERP Olympo
C146: =ROW()-1 -> 145 | D146: 1 914 | E146: RE: SOLICITUD DE CIERRE ANUAL Y TRASLADO DE SALDOS | F146: Cerrado | G146: 46114.383 | H146: 46113.858 | I146: Alta | J146: Monge Castro María Leopoldina | K146: Chiluisa Armas Luis Patricio | L146: Soporte de aplicaciones de negocio > ERP Olympo
C147: =ROW()-1 -> 146 | D147: 1 911 | E147: RE: Notificación de Término de Encargo de la Jefatura de Promoción | F147: Cerrado | G147: 46113.802 | H147: 46113.476 | I147: Media | J147: Palomino Granda Jessica Fernanda | K147: Chiluisa Armas Luis Patricio | L147: Servicios de Infraestructura y Seguridad > Gestión de Identidad y Acceso
C148: =ROW()-1 -> 147 | D148: 1 892 | E148: Estimado/a, Reciba un cordial saludo. En el marco de la socialización de los eventos de gran formato de Quito Turismo para el año 2026, me permito solicitar muy comedidamente se autorice el uso de la Sala de Capacitación de Quito Turismo para el día mié | F148: Cerrado | G148: 46113.667 | H148: 46111.601 | I148: Baja | J148: Ocampo Espín Byron Javier | K148: Chiluisa Armas Luis Patricio | L148: Soporte a Equipos de Cómputo y Periféricos > Pantallas digitales
C149: =ROW()-1 -> 148 | D149: 1 897 | E149: RV: Acceso sistema EPR V16 -PRESUPUESTO-CONTABILIDAD | F149: Cerrado | G149: 46113.643 | H149: 46112.458 | I149: Media | J149: Pacha Andrango Carlos Javier | K149: Chiluisa Armas Luis Patricio | L149: Soporte de aplicaciones de negocio > ERP Olympo
C150: =ROW()-1 -> 149 | D150: 1 904 | E150: RV: Desvinculación de personal y cumplimiento de plazos - María Gabriela Flores López | F150: Cerrado | G150: 46113.411 | H150: 46112.66 | I150: Media | J150: Pacha Andrango Carlos Javier | K150: Chiluisa Armas Luis Patricio | L150: Servicios de Infraestructura y Seguridad > Copias de Seguridad y Recuperación de Información
C151: =ROW()-1 -> 150 | D151: 1 909 | E151: Vinculación de personal | F151: Cerrado | G151: 46113.394 | H151: 46113.365 | I151: Media | J151: Palomino Granda Jessica Fernanda | K151: Chiluisa Armas Luis Patricio | L151: Servicios de Infraestructura y Seguridad > Gestión de Identidad y Acceso
...

Sheet Resumen
B1: 📊 RESUMEN DE TICKETS DE SOPORTE TÉCNICO
B3: INDICADORES CLAVE (KPIs)
B5: Total Tickets | C5: Cerrados | D5: Resueltos | E5: En Curso | F5: Nuevos | G5: Prioridad Alta
B6: =COUNTA(TablaTickets[TICKET]) -> 155 | C6: =COUNTIF(TablaTickets[ESTADO],"*Cerrado*") -> 145 | D6: =COUNTIF(TablaTickets[ESTADO],"*Resuelto*") -> 1 | E6: =COUNTIF(TablaTickets[ESTADO],"*En curso*") -> 8 | F6: =COUNTIF(TablaTickets[ESTADO],"*Nuevo*") -> 1 | G6: =COUNTIF(TablaTickets[PRIORIDAD],"*Alta*") -> 30
B9: 1. Tickets por ESTADO | E9: 2. Tickets por PRIORIDAD
B10: Estado | C10: Cantidad | E10: Prioridad | F10: Cantidad
B11: {=_xlfn._xlws.SORT(_xlfn.UNIQUE(TablaTickets[ESTADO]))} -> Cerrado | C11: {=COUNTIF(TablaTickets[ESTADO],_xlfn.ANCHORARRAY(B11))} -> 145 | E11: {=_xlfn._xlws.SORT(_xlfn.UNIQUE(TablaTickets[PRIORIDAD]))} -> Alta | F11: {=COUNTIF(TablaTickets[PRIORIDAD],_xlfn.ANCHORARRAY(E11))} -> 30
B12: En curso (asignado) | C12: 8 | E12: Baja | F12: 1
B13: Nuevo | C13: 1 | E13: Media | F13: 124
B14: Resuelto | C14: 1
B20: 3. Tickets por TÉCNICO ASIGNADO | E20: 4. Top 10 CATEGORÍAS
B21: Técnico | C21: Cantidad | E21: Categoría | F21: Cantidad
B22: {=_xlfn._xlws.SORT(_xlfn.UNIQUE(_xlfn._xlws.FILTER(TablaTickets[TÉCNICO ASIGNADO],TablaTickets[TÉCNICO ASIGNADO]<>"")))} -> Casa Chanaluisa Alex Wladimir | C22: {=COUNTIF(TablaTickets[TÉCNICO ASIGNADO],_xlfn.ANCHORARRAY(B22))} -> 1 | E22: {=_xlfn.LET(_xlpm.u,_xlfn.UNIQUE(_xlfn._xlws.FILTER(TablaTickets[CATEGORÍA],TablaTickets[CATEGORÍA]<>"")),_xlpm.c,COUNTIF(TablaTickets[CATEGORÍA],_xlpm.u),_xlpm.s,_xlfn.SORTBY(_xlpm.u,_xlpm.c,-1),_xlfn.TAKE(_xlpm.s,10))} -> Soporte de aplicaciones de negocio > SICET | F22: {=COUNTIF(TablaTickets[CATEGORÍA],_xlfn.ANCHORARRAY(E22))} -> 44
B23: Chiluisa Armas Luis Patricio | C23: 67 | E23: Soporte de aplicaciones de negocio > ERP Olympo | F23: 31
B24: glpi | C24: 1 | E24: Servicios de Infraestructura y Seguridad > Gestión de Identidad y Acceso | F24: 15
B25: glpi | C25: 2 | E25: Soporte de aplicaciones de negocio > Sitra | F25: 9
B26: Medina Iturre Edgar Fabricio | C26: 71 | E26: Soporte de aplicaciones de negocio > Portal Institución | F26: 8
E27: Soporte a Equipos de Cómputo y Periféricos > Computadora o laptop | F27: 7
E28: Soporte a Equipos de Cómputo y Periféricos > Pantallas digitales | F28: 4
E29: Soporte a Equipos de Cómputo y Periféricos > Impresora | F29: 3
E30: Servicios de Infraestructura y Seguridad > Copias de Seguridad y Recuperación de Información | F30: 3
E31: Gestión de Software de Ofimática y Colaboración > Correo Electrónico Institucional | F31: 2

Sheet MANZANA_RUTA_DPA
B1: DPA_MANZANA
A2: 01RD01001 | B2: 170150215005003
A3: 01RD01001 | B3: 170150214009002
A4: 01RD01001 | B4: 170150214009001 | D4: La codificación DPA por manzana se identifica en la totalidad de manzanas que suponen parte lineal de la ruta en mención
A5: 01RD01001 | B5: 170150214010001
A6: 01RD01001 | B6: 170150236008002
A7: 01RD01001 | B7: 170150215004001
A8: 01RD01001 | B8: 170150214008001
A9: 01RD01001 | B9: 170150215009004
A10: 01RD01001 | B10: 170150215008004
A11: 01RD01001 | B11: 170150215008003
A12: 01RD01001 | B12: 170150215008006
A13: 01RD01001 | B13: 170150215008005
A14: 01RD01001 | B14: 170150215008007
A15: 01RD01001 | B15: 170150215007003
A16: 01RD01001 | B16: 170150215007002
... A1927: 02RE05014 | B1927: 170150010008011
